[
  {
    "#": "252",
    "DATE": "2025-07-07",
    "TRADING CODE": "NCCBANK",
    "LTP*": "10.5",
    "HIGH": "10.6",
    "LOW": "10.3",
    "OPENP*": "10.3",
    "CLOSEP*": "10.5",
    "YCP": "10.2",
    "TRADE": "292",
    "VALUE (mn)": "9.435",
    "VOLUME": "901964"
  },
  {
    "#": "251",
    "DATE": "2025-07-08",
    "TRADING CODE": "NCCBANK",
    "LTP*": "10.4",
    "HIGH": "10.5",
    "LOW": "10.3",
    "OPENP*": "10.5",
    "CLOSEP*": "10.4",
    "YCP": "10.5",
    "TRADE": "123",
    "VALUE (mn)": "2.881",
    "VOLUME": "277389"
  },
  {
    "#": "250",
    "DATE": "2025-07-09",
    "TRADING CODE": "NCCBANK",
    "LTP*": "10.4",
    "HIGH": "10.6",
    "LOW": "10.3",
    "OPENP*": "10.4",
    "CLOSEP*": "10.4",
    "YCP": "10.4",
    "TRADE": "133",
    "VALUE (mn)": "5.143",
    "VOLUME": "493069"
  },
  {
    "#": "249",
    "DATE": "2025-07-10",
    "TRADING CODE": "NCCBANK",
    "LTP*": "10.5",
    "HIGH": "10.5",
    "LOW": "10.4",
    "OPENP*": "10.4",
    "CLOSEP*": "10.4",
    "YCP": "10.4",
    "TRADE": "82",
    "VALUE (mn)": "3.6",
    "VOLUME": "344401"
  },
  {
    "#": "248",
    "DATE": "2025-07-13",
    "TRADING CODE": "NCCBANK",
    "LTP*": "10.2",
    "HIGH": "10.5",
    "LOW": "10.2",
    "OPENP*": "10.4",
    "CLOSEP*": "10.3",
    "YCP": "10.4",
    "TRADE": "223",
    "VALUE (mn)": "7.658",
    "VOLUME": "744297"
  },
  {
    "#": "247",
    "DATE": "2025-07-14",
    "TRADING CODE": "NCCBANK",
    "LTP*": "10.2",
    "HIGH": "10.3",
    "LOW": "10.1",
    "OPENP*": "10.3",
    "CLOSEP*": "10.2",
    "YCP": "10.3",
    "TRADE": "214",
    "VALUE (mn)": "5.994",
    "VOLUME": "586148"
  },
  {
    "#": "246",
    "DATE": "2025-07-15",
    "TRADING CODE": "NCCBANK",
    "LTP*": "10.1",
    "HIGH": "10.3",
    "LOW": "10",
    "OPENP*": "10.2",
    "CLOSEP*": "10.1",
    "YCP": "10.2",
    "TRADE": "247",
    "VALUE (mn)": "6.939",
    "VOLUME": "684315"
  },
  {
    "#": "245",
    "DATE": "2025-07-16",
    "TRADING CODE": "NCCBANK",
    "LTP*": "10.1",
    "HIGH": "10.2",
    "LOW": "10",
    "OPENP*": "10.1",
    "CLOSEP*": "10.1",
    "YCP": "10.1",
    "TRADE": "292",
    "VALUE (mn)": "17.631",
    "VOLUME": "1744828"
  },
  {
    "#": "244",
    "DATE": "2025-07-17",
    "TRADING CODE": "NCCBANK",
    "LTP*": "10.1",
    "HIGH": "10.3",
    "LOW": "10",
    "OPENP*": "10.2",
    "CLOSEP*": "10.1",
    "YCP": "10.1",
    "TRADE": "383",
    "VALUE (mn)": "15.816",
    "VOLUME": "1556353"
  },
  {
    "#": "243",
    "DATE": "2025-07-20",
    "TRADING CODE": "NCCBANK",
    "LTP*": "10.2",
    "HIGH": "10.3",
    "LOW": "10",
    "OPENP*": "10.2",
    "CLOSEP*": "10.2",
    "YCP": "10.1",
    "TRADE": "320",
    "VALUE (mn)": "18.948",
    "VOLUME": "1872214"
  },
  {
    "#": "242",
    "DATE": "2025-07-21",
    "TRADING CODE": "NCCBANK",
    "LTP*": "10.5",
    "HIGH": "10.6",
    "LOW": "10.1",
    "OPENP*": "10.3",
    "CLOSEP*": "10.5",
    "YCP": "10.2",
    "TRADE": "539",
    "VALUE (mn)": "18.202",
    "VOLUME": "1752005"
  },
  {
    "#": "241",
    "DATE": "2025-07-22",
    "TRADING CODE": "NCCBANK",
    "LTP*": "10.7",
    "HIGH": "10.7",
    "LOW": "10.3",
    "OPENP*": "10.5",
    "CLOSEP*": "10.7",
    "YCP": "10.5",
    "TRADE": "521",
    "VALUE (mn)": "21.629",
    "VOLUME": "2054081"
  },
  {
    "#": "240",
    "DATE": "2025-07-23",
    "TRADING CODE": "NCCBANK",
    "LTP*": "11.4",
    "HIGH": "11.5",
    "LOW": "10.6",
    "OPENP*": "10.7",
    "CLOSEP*": "11.4",
    "YCP": "10.7",
    "TRADE": "1033",
    "VALUE (mn)": "45.885",
    "VOLUME": "4089504"
  },
  {
    "#": "239",
    "DATE": "2025-07-24",
    "TRADING CODE": "NCCBANK",
    "LTP*": "12",
    "HIGH": "12.1",
    "LOW": "11.2",
    "OPENP*": "11.2",
    "CLOSEP*": "12",
    "YCP": "11.4",
    "TRADE": "868",
    "VALUE (mn)": "40.071",
    "VOLUME": "3410418"
  },
  {
    "#": "238",
    "DATE": "2025-07-27",
    "TRADING CODE": "NCCBANK",
    "LTP*": "12",
    "HIGH": "12.2",
    "LOW": "11.6",
    "OPENP*": "11.8",
    "CLOSEP*": "12",
    "YCP": "12",
    "TRADE": "805",
    "VALUE (mn)": "37.032",
    "VOLUME": "3101953"
  },
  {
    "#": "237",
    "DATE": "2025-07-28",
    "TRADING CODE": "NCCBANK",
    "LTP*": "12",
    "HIGH": "12",
    "LOW": "11.7",
    "OPENP*": "11.9",
    "CLOSEP*": "11.9",
    "YCP": "12",
    "TRADE": "340",
    "VALUE (mn)": "15.637",
    "VOLUME": "1313235"
  },
  {
    "#": "236",
    "DATE": "2025-07-29",
    "TRADING CODE": "NCCBANK",
    "LTP*": "11.8",
    "HIGH": "12.1",
    "LOW": "11.5",
    "OPENP*": "11.8",
    "CLOSEP*": "11.8",
    "YCP": "11.9",
    "TRADE": "570",
    "VALUE (mn)": "30.571",
    "VOLUME": "2590715"
  },
  {
    "#": "235",
    "DATE": "2025-07-30",
    "TRADING CODE": "NCCBANK",
    "LTP*": "12.1",
    "HIGH": "12.3",
    "LOW": "11.7",
    "OPENP*": "11.8",
    "CLOSEP*": "12.1",
    "YCP": "11.8",
    "TRADE": "486",
    "VALUE (mn)": "21.291",
    "VOLUME": "1774538"
  },
  {
    "#": "234",
    "DATE": "2025-07-31",
    "TRADING CODE": "NCCBANK",
    "LTP*": "13",
    "HIGH": "13.2",
    "LOW": "12.2",
    "OPENP*": "12.2",
    "CLOSEP*": "13",
    "YCP": "12.1",
    "TRADE": "1394",
    "VALUE (mn)": "121.565",
    "VOLUME": "9437925"
  },
  {
    "#": "233",
    "DATE": "2025-08-03",
    "TRADING CODE": "NCCBANK",
    "LTP*": "13.1",
    "HIGH": "13.3",
    "LOW": "12.9",
    "OPENP*": "13",
    "CLOSEP*": "13.1",
    "YCP": "13",
    "TRADE": "700",
    "VALUE (mn)": "67.814",
    "VOLUME": "5159753"
  },
  {
    "#": "232",
    "DATE": "2025-08-04",
    "TRADING CODE": "NCCBANK",
    "LTP*": "12.9",
    "HIGH": "13.2",
    "LOW": "12.8",
    "OPENP*": "13.1",
    "CLOSEP*": "12.9",
    "YCP": "13.1",
    "TRADE": "572",
    "VALUE (mn)": "62.825",
    "VOLUME": "4834170"
  },
  {
    "#": "231",
    "DATE": "2025-08-06",
    "TRADING CODE": "NCCBANK",
    "LTP*": "12.8",
    "HIGH": "13",
    "LOW": "12.6",
    "OPENP*": "13",
    "CLOSEP*": "12.8",
    "YCP": "12.9",
    "TRADE": "372",
    "VALUE (mn)": "33.499",
    "VOLUME": "2614094"
  },
  {
    "#": "230",
    "DATE": "2025-08-07",
    "TRADING CODE": "NCCBANK",
    "LTP*": "13",
    "HIGH": "13.2",
    "LOW": "12.7",
    "OPENP*": "13",
    "CLOSEP*": "13",
    "YCP": "12.8",
    "TRADE": "809",
    "VALUE (mn)": "81.267",
    "VOLUME": "6260820"
  },
  {
    "#": "229",
    "DATE": "2025-08-10",
    "TRADING CODE": "NCCBANK",
    "LTP*": "12.6",
    "HIGH": "13.3",
    "LOW": "12.5",
    "OPENP*": "13.3",
    "CLOSEP*": "12.6",
    "YCP": "13",
    "TRADE": "639",
    "VALUE (mn)": "42.699",
    "VOLUME": "3327322"
  },
  {
    "#": "228",
    "DATE": "2025-08-11",
    "TRADING CODE": "NCCBANK",
    "LTP*": "12.5",
    "HIGH": "12.8",
    "LOW": "12.4",
    "OPENP*": "12.6",
    "CLOSEP*": "12.5",
    "YCP": "12.6",
    "TRADE": "378",
    "VALUE (mn)": "26.427",
    "VOLUME": "2096620"
  },
  {
    "#": "227",
    "DATE": "2025-08-12",
    "TRADING CODE": "NCCBANK",
    "LTP*": "12.3",
    "HIGH": "12.8",
    "LOW": "12.1",
    "OPENP*": "12.6",
    "CLOSEP*": "12.3",
    "YCP": "12.5",
    "TRADE": "368",
    "VALUE (mn)": "17.233",
    "VOLUME": "1380491"
  },
  {
    "#": "226",
    "DATE": "2025-08-13",
    "TRADING CODE": "NCCBANK",
    "LTP*": "12.3",
    "HIGH": "12.5",
    "LOW": "12",
    "OPENP*": "12",
    "CLOSEP*": "12.3",
    "YCP": "12.3",
    "TRADE": "382",
    "VALUE (mn)": "22.915",
    "VOLUME": "1870593"
  },
  {
    "#": "225",
    "DATE": "2025-08-14",
    "TRADING CODE": "NCCBANK",
    "LTP*": "12.6",
    "HIGH": "12.8",
    "LOW": "12.3",
    "OPENP*": "12.3",
    "CLOSEP*": "12.6",
    "YCP": "12.3",
    "TRADE": "372",
    "VALUE (mn)": "18.841",
    "VOLUME": "1513495"
  },
  {
    "#": "224",
    "DATE": "2025-08-17",
    "TRADING CODE": "NCCBANK",
    "LTP*": "12.8",
    "HIGH": "13",
    "LOW": "12.7",
    "OPENP*": "12.8",
    "CLOSEP*": "12.8",
    "YCP": "12.6",
    "TRADE": "476",
    "VALUE (mn)": "47.564",
    "VOLUME": "3715540"
  },
  {
    "#": "223",
    "DATE": "2025-08-18",
    "TRADING CODE": "NCCBANK",
    "LTP*": "12.5",
    "HIGH": "12.9",
    "LOW": "12.4",
    "OPENP*": "12.7",
    "CLOSEP*": "12.5",
    "YCP": "12.8",
    "TRADE": "370",
    "VALUE (mn)": "25.98",
    "VOLUME": "2063808"
  },
  {
    "#": "222",
    "DATE": "2025-08-19",
    "TRADING CODE": "NCCBANK",
    "LTP*": "12.1",
    "HIGH": "12.5",
    "LOW": "12",
    "OPENP*": "12.4",
    "CLOSEP*": "12.1",
    "YCP": "12.5",
    "TRADE": "801",
    "VALUE (mn)": "38.154",
    "VOLUME": "3123162"
  },
  {
    "#": "221",
    "DATE": "2025-08-20",
    "TRADING CODE": "NCCBANK",
    "LTP*": "11.9",
    "HIGH": "12.2",
    "LOW": "11.8",
    "OPENP*": "12",
    "CLOSEP*": "11.9",
    "YCP": "12.1",
    "TRADE": "565",
    "VALUE (mn)": "28.511",
    "VOLUME": "2380725"
  },
  {
    "#": "220",
    "DATE": "2025-08-21",
    "TRADING CODE": "NCCBANK",
    "LTP*": "11.8",
    "HIGH": "12.1",
    "LOW": "11.7",
    "OPENP*": "12",
    "CLOSEP*": "11.8",
    "YCP": "11.9",
    "TRADE": "373",
    "VALUE (mn)": "37.389",
    "VOLUME": "3155566"
  },
  {
    "#": "219",
    "DATE": "2025-08-24",
    "TRADING CODE": "NCCBANK",
    "LTP*": "11.7",
    "HIGH": "11.9",
    "LOW": "11.6",
    "OPENP*": "11.8",
    "CLOSEP*": "11.7",
    "YCP": "11.8",
    "TRADE": "582",
    "VALUE (mn)": "25.031",
    "VOLUME": "2140362"
  },
  {
    "#": "218",
    "DATE": "2025-08-25",
    "TRADING CODE": "NCCBANK",
    "LTP*": "12.2",
    "HIGH": "12.4",
    "LOW": "11.7",
    "OPENP*": "12.2",
    "CLOSEP*": "12.2",
    "YCP": "11.7",
    "TRADE": "521",
    "VALUE (mn)": "32.305",
    "VOLUME": "2679598"
  },
  {
    "#": "217",
    "DATE": "2025-08-26",
    "TRADING CODE": "NCCBANK",
    "LTP*": "12",
    "HIGH": "12.5",
    "LOW": "11.9",
    "OPENP*": "12.2",
    "CLOSEP*": "12",
    "YCP": "12.2",
    "TRADE": "520",
    "VALUE (mn)": "42.074",
    "VOLUME": "3455871"
  },
  {
    "#": "216",
    "DATE": "2025-08-27",
    "TRADING CODE": "NCCBANK",
    "LTP*": "12",
    "HIGH": "12.2",
    "LOW": "11.8",
    "OPENP*": "12.2",
    "CLOSEP*": "11.8",
    "YCP": "12",
    "TRADE": "284",
    "VALUE (mn)": "14.502",
    "VOLUME": "1220885"
  },
  {
    "#": "215",
    "DATE": "2025-08-28",
    "TRADING CODE": "NCCBANK",
    "LTP*": "12.1",
    "HIGH": "12.2",
    "LOW": "11.8",
    "OPENP*": "11.8",
    "CLOSEP*": "12.1",
    "YCP": "11.8",
    "TRADE": "273",
    "VALUE (mn)": "18.253",
    "VOLUME": "1516019"
  },
  {
    "#": "214",
    "DATE": "2025-08-31",
    "TRADING CODE": "NCCBANK",
    "LTP*": "12.1",
    "HIGH": "12.3",
    "LOW": "12",
    "OPENP*": "12.2",
    "CLOSEP*": "12.1",
    "YCP": "12.1",
    "TRADE": "284",
    "VALUE (mn)": "21.496",
    "VOLUME": "1766653"
  },
  {
    "#": "213",
    "DATE": "2025-09-01",
    "TRADING CODE": "NCCBANK",
    "LTP*": "12",
    "HIGH": "12.2",
    "LOW": "11.9",
    "OPENP*": "12.1",
    "CLOSEP*": "12",
    "YCP": "12.1",
    "TRADE": "215",
    "VALUE (mn)": "11.091",
    "VOLUME": "921841"
  },
  {
    "#": "212",
    "DATE": "2025-09-02",
    "TRADING CODE": "NCCBANK",
    "LTP*": "12.3",
    "HIGH": "12.3",
    "LOW": "11.8",
    "OPENP*": "12.1",
    "CLOSEP*": "12.1",
    "YCP": "12",
    "TRADE": "462",
    "VALUE (mn)": "28.721",
    "VOLUME": "2400917"
  },
  {
    "#": "211",
    "DATE": "2025-09-03",
    "TRADING CODE": "NCCBANK",
    "LTP*": "12.2",
    "HIGH": "12.5",
    "LOW": "12.1",
    "OPENP*": "12.2",
    "CLOSEP*": "12.2",
    "YCP": "12.1",
    "TRADE": "508",
    "VALUE (mn)": "29.821",
    "VOLUME": "2423395"
  },
  {
    "#": "210",
    "DATE": "2025-09-04",
    "TRADING CODE": "NCCBANK",
    "LTP*": "12.1",
    "HIGH": "12.4",
    "LOW": "12.1",
    "OPENP*": "12.2",
    "CLOSEP*": "12.1",
    "YCP": "12.2",
    "TRADE": "382",
    "VALUE (mn)": "24.028",
    "VOLUME": "1962959"
  },
  {
    "#": "209",
    "DATE": "2025-09-07",
    "TRADING CODE": "NCCBANK",
    "LTP*": "11.9",
    "HIGH": "12.2",
    "LOW": "11.9",
    "OPENP*": "12.1",
    "CLOSEP*": "11.9",
    "YCP": "12.1",
    "TRADE": "455",
    "VALUE (mn)": "25.645",
    "VOLUME": "2134557"
  },
  {
    "#": "208",
    "DATE": "2025-09-08",
    "TRADING CODE": "NCCBANK",
    "LTP*": "12.1",
    "HIGH": "12.2",
    "LOW": "12",
    "OPENP*": "12",
    "CLOSEP*": "12.1",
    "YCP": "11.9",
    "TRADE": "295",
    "VALUE (mn)": "19.708",
    "VOLUME": "1632606"
  },
  {
    "#": "207",
    "DATE": "2025-09-09",
    "TRADING CODE": "NCCBANK",
    "LTP*": "11.9",
    "HIGH": "12.2",
    "LOW": "11.9",
    "OPENP*": "12.2",
    "CLOSEP*": "11.9",
    "YCP": "12.1",
    "TRADE": "237",
    "VALUE (mn)": "14.709",
    "VOLUME": "1227622"
  },
  {
    "#": "206",
    "DATE": "2025-09-10",
    "TRADING CODE": "NCCBANK",
    "LTP*": "11.9",
    "HIGH": "12.1",
    "LOW": "11.8",
    "OPENP*": "11.9",
    "CLOSEP*": "11.9",
    "YCP": "11.9",
    "TRADE": "246",
    "VALUE (mn)": "15.842",
    "VOLUME": "1325185"
  },
  {
    "#": "205",
    "DATE": "2025-09-11",
    "TRADING CODE": "NCCBANK",
    "LTP*": "12",
    "HIGH": "12",
    "LOW": "11.8",
    "OPENP*": "11.9",
    "CLOSEP*": "12",
    "YCP": "11.9",
    "TRADE": "131",
    "VALUE (mn)": "5.001",
    "VOLUME": "419624"
  },
  {
    "#": "204",
    "DATE": "2025-09-14",
    "TRADING CODE": "NCCBANK",
    "LTP*": "12",
    "HIGH": "12.1",
    "LOW": "11.9",
    "OPENP*": "12",
    "CLOSEP*": "12",
    "YCP": "12",
    "TRADE": "206",
    "VALUE (mn)": "17.202",
    "VOLUME": "1436003"
  },
  {
    "#": "203",
    "DATE": "2025-09-15",
    "TRADING CODE": "NCCBANK",
    "LTP*": "12.4",
    "HIGH": "12.4",
    "LOW": "12",
    "OPENP*": "12.1",
    "CLOSEP*": "12.4",
    "YCP": "12",
    "TRADE": "515",
    "VALUE (mn)": "37.848",
    "VOLUME": "3081866"
  },
  {
    "#": "202",
    "DATE": "2025-09-16",
    "TRADING CODE": "NCCBANK",
    "LTP*": "13",
    "HIGH": "13.1",
    "LOW": "12.3",
    "OPENP*": "12.5",
    "CLOSEP*": "13",
    "YCP": "12.4",
    "TRADE": "1156",
    "VALUE (mn)": "75.428",
    "VOLUME": "5895555"
  },
  {
    "#": "201",
    "DATE": "2025-09-17",
    "TRADING CODE": "NCCBANK",
    "LTP*": "12.4",
    "HIGH": "13.3",
    "LOW": "12.3",
    "OPENP*": "13",
    "CLOSEP*": "12.4",
    "YCP": "13",
    "TRADE": "498",
    "VALUE (mn)": "34.365",
    "VOLUME": "2687297"
  },
  {
    "#": "200",
    "DATE": "2025-09-18",
    "TRADING CODE": "NCCBANK",
    "LTP*": "12.4",
    "HIGH": "12.7",
    "LOW": "12.3",
    "OPENP*": "12.4",
    "CLOSEP*": "12.4",
    "YCP": "12.4",
    "TRADE": "234",
    "VALUE (mn)": "12.088",
    "VOLUME": "968836"
  },
  {
    "#": "199",
    "DATE": "2025-09-21",
    "TRADING CODE": "NCCBANK",
    "LTP*": "12.3",
    "HIGH": "12.7",
    "LOW": "12.3",
    "OPENP*": "12.4",
    "CLOSEP*": "12.3",
    "YCP": "12.4",
    "TRADE": "202",
    "VALUE (mn)": "9.415",
    "VOLUME": "757009"
  },
  {
    "#": "198",
    "DATE": "2025-09-22",
    "TRADING CODE": "NCCBANK",
    "LTP*": "12.2",
    "HIGH": "12.4",
    "LOW": "12.2",
    "OPENP*": "12.2",
    "CLOSEP*": "12.2",
    "YCP": "12.3",
    "TRADE": "215",
    "VALUE (mn)": "12.952",
    "VOLUME": "1055348"
  },
  {
    "#": "197",
    "DATE": "2025-09-23",
    "TRADING CODE": "NCCBANK",
    "LTP*": "12",
    "HIGH": "12.4",
    "LOW": "11.9",
    "OPENP*": "12.4",
    "CLOSEP*": "12",
    "YCP": "12.2",
    "TRADE": "353",
    "VALUE (mn)": "30.599",
    "VOLUME": "2519039"
  },
  {
    "#": "196",
    "DATE": "2025-09-24",
    "TRADING CODE": "NCCBANK",
    "LTP*": "12.1",
    "HIGH": "12.2",
    "LOW": "12",
    "OPENP*": "12.1",
    "CLOSEP*": "12.1",
    "YCP": "12",
    "TRADE": "258",
    "VALUE (mn)": "18.046",
    "VOLUME": "1491279"
  },
  {
    "#": "195",
    "DATE": "2025-09-25",
    "TRADING CODE": "NCCBANK",
    "LTP*": "12.1",
    "HIGH": "12.3",
    "LOW": "12",
    "OPENP*": "12.2",
    "CLOSEP*": "12.1",
    "YCP": "12.1",
    "TRADE": "273",
    "VALUE (mn)": "17.281",
    "VOLUME": "1424704"
  },
  {
    "#": "194",
    "DATE": "2025-09-28",
    "TRADING CODE": "NCCBANK",
    "LTP*": "12",
    "HIGH": "12.2",
    "LOW": "11.9",
    "OPENP*": "12.1",
    "CLOSEP*": "12",
    "YCP": "12.1",
    "TRADE": "158",
    "VALUE (mn)": "8.428",
    "VOLUME": "700400"
  },
  {
    "#": "193",
    "DATE": "2025-09-29",
    "TRADING CODE": "NCCBANK",
    "LTP*": "12.1",
    "HIGH": "12.2",
    "LOW": "11.9",
    "OPENP*": "12",
    "CLOSEP*": "12.1",
    "YCP": "12",
    "TRADE": "179",
    "VALUE (mn)": "11.485",
    "VOLUME": "954082"
  },
  {
    "#": "192",
    "DATE": "2025-09-30",
    "TRADING CODE": "NCCBANK",
    "LTP*": "12.2",
    "HIGH": "12.3",
    "LOW": "12.1",
    "OPENP*": "12.2",
    "CLOSEP*": "12.2",
    "YCP": "12.1",
    "TRADE": "156",
    "VALUE (mn)": "9.342",
    "VOLUME": "766339"
  },
  {
    "#": "191",
    "DATE": "2025-10-05",
    "TRADING CODE": "NCCBANK",
    "LTP*": "12.3",
    "HIGH": "12.4",
    "LOW": "12.1",
    "OPENP*": "12.2",
    "CLOSEP*": "12.3",
    "YCP": "12.2",
    "TRADE": "188",
    "VALUE (mn)": "10.407",
    "VOLUME": "847870"
  },
  {
    "#": "190",
    "DATE": "2025-10-06",
    "TRADING CODE": "NCCBANK",
    "LTP*": "12.1",
    "HIGH": "12.5",
    "LOW": "12",
    "OPENP*": "12.4",
    "CLOSEP*": "12.1",
    "YCP": "12.3",
    "TRADE": "254",
    "VALUE (mn)": "19.601",
    "VOLUME": "1622895"
  },
  {
    "#": "189",
    "DATE": "2025-10-07",
    "TRADING CODE": "NCCBANK",
    "LTP*": "12",
    "HIGH": "12.2",
    "LOW": "11.9",
    "OPENP*": "12.1",
    "CLOSEP*": "12",
    "YCP": "12.1",
    "TRADE": "232",
    "VALUE (mn)": "16.058",
    "VOLUME": "1336009"
  },
  {
    "#": "188",
    "DATE": "2025-10-08",
    "TRADING CODE": "NCCBANK",
    "LTP*": "12",
    "HIGH": "12.1",
    "LOW": "11.9",
    "OPENP*": "12",
    "CLOSEP*": "12",
    "YCP": "12",
    "TRADE": "171",
    "VALUE (mn)": "13.666",
    "VOLUME": "1140168"
  },
  {
    "#": "187",
    "DATE": "2025-10-09",
    "TRADING CODE": "NCCBANK",
    "LTP*": "11.9",
    "HIGH": "12.1",
    "LOW": "11.9",
    "OPENP*": "12",
    "CLOSEP*": "11.9",
    "YCP": "12",
    "TRADE": "232",
    "VALUE (mn)": "14.16",
    "VOLUME": "1186066"
  },
  {
    "#": "186",
    "DATE": "2025-10-12",
    "TRADING CODE": "NCCBANK",
    "LTP*": "11.8",
    "HIGH": "11.9",
    "LOW": "11.8",
    "OPENP*": "11.9",
    "CLOSEP*": "11.8",
    "YCP": "11.9",
    "TRADE": "182",
    "VALUE (mn)": "10.23",
    "VOLUME": "863730"
  },
  {
    "#": "185",
    "DATE": "2025-10-13",
    "TRADING CODE": "NCCBANK",
    "LTP*": "12",
    "HIGH": "12",
    "LOW": "11.8",
    "OPENP*": "11.8",
    "CLOSEP*": "12",
    "YCP": "11.8",
    "TRADE": "97",
    "VALUE (mn)": "4.83",
    "VOLUME": "403593"
  },
  {
    "#": "184",
    "DATE": "2025-10-14",
    "TRADING CODE": "NCCBANK",
    "LTP*": "11.9",
    "HIGH": "12.1",
    "LOW": "11.9",
    "OPENP*": "12.1",
    "CLOSEP*": "11.9",
    "YCP": "12",
    "TRADE": "81",
    "VALUE (mn)": "4.2",
    "VOLUME": "350749"
  },
  {
    "#": "183",
    "DATE": "2025-10-15",
    "TRADING CODE": "NCCBANK",
    "LTP*": "11.7",
    "HIGH": "11.9",
    "LOW": "11.7",
    "OPENP*": "11.8",
    "CLOSEP*": "11.7",
    "YCP": "11.9",
    "TRADE": "195",
    "VALUE (mn)": "7.159",
    "VOLUME": "608363"
  },
  {
    "#": "182",
    "DATE": "2025-10-16",
    "TRADING CODE": "NCCBANK",
    "LTP*": "11.8",
    "HIGH": "11.9",
    "LOW": "11.7",
    "OPENP*": "11.7",
    "CLOSEP*": "11.8",
    "YCP": "11.7",
    "TRADE": "180",
    "VALUE (mn)": "7.802",
    "VOLUME": "661477"
  },
  {
    "#": "181",
    "DATE": "2025-10-19",
    "TRADING CODE": "NCCBANK",
    "LTP*": "11.6",
    "HIGH": "11.8",
    "LOW": "11.6",
    "OPENP*": "11.8",
    "CLOSEP*": "11.6",
    "YCP": "11.8",
    "TRADE": "270",
    "VALUE (mn)": "10.268",
    "VOLUME": "882332"
  },
  {
    "#": "180",
    "DATE": "2025-10-20",
    "TRADING CODE": "NCCBANK",
    "LTP*": "11.7",
    "HIGH": "11.7",
    "LOW": "11.5",
    "OPENP*": "11.6",
    "CLOSEP*": "11.7",
    "YCP": "11.6",
    "TRADE": "169",
    "VALUE (mn)": "7.686",
    "VOLUME": "659299"
  },
  {
    "#": "179",
    "DATE": "2025-10-21",
    "TRADING CODE": "NCCBANK",
    "LTP*": "11.5",
    "HIGH": "11.9",
    "LOW": "11.4",
    "OPENP*": "11.8",
    "CLOSEP*": "11.5",
    "YCP": "11.7",
    "TRADE": "233",
    "VALUE (mn)": "10.632",
    "VOLUME": "919496"
  },
  {
    "#": "178",
    "DATE": "2025-10-22",
    "TRADING CODE": "NCCBANK",
    "LTP*": "11.5",
    "HIGH": "11.6",
    "LOW": "11.4",
    "OPENP*": "11.6",
    "CLOSEP*": "11.5",
    "YCP": "11.5",
    "TRADE": "211",
    "VALUE (mn)": "8.993",
    "VOLUME": "784105"
  },
  {
    "#": "177",
    "DATE": "2025-10-23",
    "TRADING CODE": "NCCBANK",
    "LTP*": "11.6",
    "HIGH": "11.8",
    "LOW": "11.5",
    "OPENP*": "11.7",
    "CLOSEP*": "11.6",
    "YCP": "11.5",
    "TRADE": "199",
    "VALUE (mn)": "11.087",
    "VOLUME": "956548"
  },
  {
    "#": "176",
    "DATE": "2025-10-26",
    "TRADING CODE": "NCCBANK",
    "LTP*": "11.6",
    "HIGH": "11.7",
    "LOW": "11.4",
    "OPENP*": "11.6",
    "CLOSEP*": "11.6",
    "YCP": "11.6",
    "TRADE": "156",
    "VALUE (mn)": "9.176",
    "VOLUME": "794918"
  },
  {
    "#": "175",
    "DATE": "2025-10-27",
    "TRADING CODE": "NCCBANK",
    "LTP*": "11.4",
    "HIGH": "11.6",
    "LOW": "11.3",
    "OPENP*": "11.4",
    "CLOSEP*": "11.4",
    "YCP": "11.6",
    "TRADE": "266",
    "VALUE (mn)": "16.206",
    "VOLUME": "1417516"
  },
  {
    "#": "174",
    "DATE": "2025-10-28",
    "TRADING CODE": "NCCBANK",
    "LTP*": "11.3",
    "HIGH": "11.5",
    "LOW": "11.2",
    "OPENP*": "11.5",
    "CLOSEP*": "11.3",
    "YCP": "11.4",
    "TRADE": "265",
    "VALUE (mn)": "14.591",
    "VOLUME": "1285063"
  },
  {
    "#": "173",
    "DATE": "2025-10-29",
    "TRADING CODE": "NCCBANK",
    "LTP*": "11.4",
    "HIGH": "11.5",
    "LOW": "11.3",
    "OPENP*": "11.5",
    "CLOSEP*": "11.3",
    "YCP": "11.3",
    "TRADE": "234",
    "VALUE (mn)": "11.561",
    "VOLUME": "1016114"
  },
  {
    "#": "172",
    "DATE": "2025-10-30",
    "TRADING CODE": "NCCBANK",
    "LTP*": "11.1",
    "HIGH": "11.3",
    "LOW": "11",
    "OPENP*": "11.2",
    "CLOSEP*": "11.1",
    "YCP": "11.3",
    "TRADE": "418",
    "VALUE (mn)": "18.001",
    "VOLUME": "1622846"
  },
  {
    "#": "171",
    "DATE": "2025-11-02",
    "TRADING CODE": "NCCBANK",
    "LTP*": "11",
    "HIGH": "11.1",
    "LOW": "11",
    "OPENP*": "11.1",
    "CLOSEP*": "11",
    "YCP": "11.1",
    "TRADE": "256",
    "VALUE (mn)": "8.449",
    "VOLUME": "767070"
  },
  {
    "#": "170",
    "DATE": "2025-11-03",
    "TRADING CODE": "NCCBANK",
    "LTP*": "11",
    "HIGH": "11.2",
    "LOW": "10.9",
    "OPENP*": "11",
    "CLOSEP*": "11",
    "YCP": "11",
    "TRADE": "266",
    "VALUE (mn)": "6.49",
    "VOLUME": "589453"
  },
  {
    "#": "169",
    "DATE": "2025-11-04",
    "TRADING CODE": "NCCBANK",
    "LTP*": "10.9",
    "HIGH": "11.1",
    "LOW": "10.9",
    "OPENP*": "11",
    "CLOSEP*": "10.9",
    "YCP": "11",
    "TRADE": "233",
    "VALUE (mn)": "6.067",
    "VOLUME": "553808"
  },
  {
    "#": "168",
    "DATE": "2025-11-05",
    "TRADING CODE": "NCCBANK",
    "LTP*": "11",
    "HIGH": "11",
    "LOW": "10.9",
    "OPENP*": "10.9",
    "CLOSEP*": "11",
    "YCP": "10.9",
    "TRADE": "151",
    "VALUE (mn)": "5.404",
    "VOLUME": "494133"
  },
  {
    "#": "167",
    "DATE": "2025-11-06",
    "TRADING CODE": "NCCBANK",
    "LTP*": "10.9",
    "HIGH": "11",
    "LOW": "10.8",
    "OPENP*": "10.9",
    "CLOSEP*": "10.9",
    "YCP": "11",
    "TRADE": "222",
    "VALUE (mn)": "12.24",
    "VOLUME": "1127528"
  },
  {
    "#": "166",
    "DATE": "2025-11-09",
    "TRADING CODE": "NCCBANK",
    "LTP*": "10.9",
    "HIGH": "11",
    "LOW": "10.8",
    "OPENP*": "10.9",
    "CLOSEP*": "10.9",
    "YCP": "10.9",
    "TRADE": "136",
    "VALUE (mn)": "6.046",
    "VOLUME": "556115"
  },
  {
    "#": "165",
    "DATE": "2025-11-10",
    "TRADING CODE": "NCCBANK",
    "LTP*": "10.8",
    "HIGH": "10.9",
    "LOW": "10.8",
    "OPENP*": "10.9",
    "CLOSEP*": "10.8",
    "YCP": "10.9",
    "TRADE": "84",
    "VALUE (mn)": "3.265",
    "VOLUME": "300554"
  },
  {
    "#": "164",
    "DATE": "2025-11-11",
    "TRADING CODE": "NCCBANK",
    "LTP*": "10.9",
    "HIGH": "10.9",
    "LOW": "10.8",
    "OPENP*": "10.8",
    "CLOSEP*": "10.9",
    "YCP": "10.8",
    "TRADE": "90",
    "VALUE (mn)": "3.288",
    "VOLUME": "302678"
  },
  {
    "#": "163",
    "DATE": "2025-11-12",
    "TRADING CODE": "NCCBANK",
    "LTP*": "11",
    "HIGH": "11",
    "LOW": "10.9",
    "OPENP*": "10.9",
    "CLOSEP*": "11",
    "YCP": "10.9",
    "TRADE": "124",
    "VALUE (mn)": "4.536",
    "VOLUME": "415256"
  },
  {
    "#": "162",
    "DATE": "2025-11-13",
    "TRADING CODE": "NCCBANK",
    "LTP*": "10.6",
    "HIGH": "10.9",
    "LOW": "10.6",
    "OPENP*": "10.9",
    "CLOSEP*": "10.6",
    "YCP": "11",
    "TRADE": "198",
    "VALUE (mn)": "11.894",
    "VOLUME": "1112805"
  },
  {
    "#": "161",
    "DATE": "2025-11-16",
    "TRADING CODE": "NCCBANK",
    "LTP*": "10.7",
    "HIGH": "10.8",
    "LOW": "10.5",
    "OPENP*": "10.6",
    "CLOSEP*": "10.7",
    "YCP": "10.6",
    "TRADE": "93",
    "VALUE (mn)": "3.782",
    "VOLUME": "357051"
  },
  {
    "#": "160",
    "DATE": "2025-11-17",
    "TRADING CODE": "NCCBANK",
    "LTP*": "10.9",
    "HIGH": "11",
    "LOW": "10.7",
    "OPENP*": "11",
    "CLOSEP*": "10.9",
    "YCP": "10.7",
    "TRADE": "91",
    "VALUE (mn)": "3.008",
    "VOLUME": "277220"
  },
  {
    "#": "159",
    "DATE": "2025-11-18",
    "TRADING CODE": "NCCBANK",
    "LTP*": "11.2",
    "HIGH": "11.2",
    "LOW": "10.9",
    "OPENP*": "11",
    "CLOSEP*": "11.1",
    "YCP": "10.9",
    "TRADE": "128",
    "VALUE (mn)": "3.043",
    "VOLUME": "275116"
  },
  {
    "#": "158",
    "DATE": "2025-11-19",
    "TRADING CODE": "NCCBANK",
    "LTP*": "11.5",
    "HIGH": "11.6",
    "LOW": "11",
    "OPENP*": "11.2",
    "CLOSEP*": "11.5",
    "YCP": "11.1",
    "TRADE": "217",
    "VALUE (mn)": "4.579",
    "VOLUME": "406443"
  },
  {
    "#": "157",
    "DATE": "2025-11-20",
    "TRADING CODE": "NCCBANK",
    "LTP*": "11.4",
    "HIGH": "11.7",
    "LOW": "11.3",
    "OPENP*": "11.5",
    "CLOSEP*": "11.4",
    "YCP": "11.5",
    "TRADE": "157",
    "VALUE (mn)": "2.987",
    "VOLUME": "261119"
  },
  {
    "#": "156",
    "DATE": "2025-11-23",
    "TRADING CODE": "NCCBANK",
    "LTP*": "11.3",
    "HIGH": "11.4",
    "LOW": "11",
    "OPENP*": "11.2",
    "CLOSEP*": "11.3",
    "YCP": "11.4",
    "TRADE": "155",
    "VALUE (mn)": "3.075",
    "VOLUME": "273992"
  },
  {
    "#": "155",
    "DATE": "2025-11-24",
    "TRADING CODE": "NCCBANK",
    "LTP*": "11.6",
    "HIGH": "11.7",
    "LOW": "11.4",
    "OPENP*": "11.4",
    "CLOSEP*": "11.6",
    "YCP": "11.3",
    "TRADE": "172",
    "VALUE (mn)": "5.004",
    "VOLUME": "433752"
  },
  {
    "#": "154",
    "DATE": "2025-11-25",
    "TRADING CODE": "NCCBANK",
    "LTP*": "11.6",
    "HIGH": "11.8",
    "LOW": "11.5",
    "OPENP*": "11.6",
    "CLOSEP*": "11.6",
    "YCP": "11.6",
    "TRADE": "132",
    "VALUE (mn)": "5.563",
    "VOLUME": "477971"
  },
  {
    "#": "153",
    "DATE": "2025-11-26",
    "TRADING CODE": "NCCBANK",
    "LTP*": "11.6",
    "HIGH": "11.7",
    "LOW": "11.5",
    "OPENP*": "11.6",
    "CLOSEP*": "11.6",
    "YCP": "11.6",
    "TRADE": "125",
    "VALUE (mn)": "2.812",
    "VOLUME": "242024"
  },
  {
    "#": "152",
    "DATE": "2025-11-27",
    "TRADING CODE": "NCCBANK",
    "LTP*": "11.7",
    "HIGH": "11.8",
    "LOW": "11.6",
    "OPENP*": "11.7",
    "CLOSEP*": "11.7",
    "YCP": "11.6",
    "TRADE": "108",
    "VALUE (mn)": "3.208",
    "VOLUME": "273628"
  },
  {
    "#": "151",
    "DATE": "2025-11-30",
    "TRADING CODE": "NCCBANK",
    "LTP*": "11.6",
    "HIGH": "11.7",
    "LOW": "11.6",
    "OPENP*": "11.7",
    "CLOSEP*": "11.6",
    "YCP": "11.7",
    "TRADE": "129",
    "VALUE (mn)": "5.509",
    "VOLUME": "474358"
  },
  {
    "#": "150",
    "DATE": "2025-12-01",
    "TRADING CODE": "NCCBANK",
    "LTP*": "11.5",
    "HIGH": "11.6",
    "LOW": "11.5",
    "OPENP*": "11.6",
    "CLOSEP*": "11.5",
    "YCP": "11.6",
    "TRADE": "102",
    "VALUE (mn)": "4.223",
    "VOLUME": "366623"
  },
  {
    "#": "149",
    "DATE": "2025-12-02",
    "TRADING CODE": "NCCBANK",
    "LTP*": "11.6",
    "HIGH": "11.7",
    "LOW": "11.5",
    "OPENP*": "11.5",
    "CLOSEP*": "11.6",
    "YCP": "11.5",
    "TRADE": "60",
    "VALUE (mn)": "1.299",
    "VOLUME": "112143"
  },
  {
    "#": "148",
    "DATE": "2025-12-03",
    "TRADING CODE": "NCCBANK",
    "LTP*": "11.7",
    "HIGH": "11.8",
    "LOW": "11.6",
    "OPENP*": "11.8",
    "CLOSEP*": "11.7",
    "YCP": "11.6",
    "TRADE": "163",
    "VALUE (mn)": "4.344",
    "VOLUME": "371295"
  },
  {
    "#": "147",
    "DATE": "2025-12-04",
    "TRADING CODE": "NCCBANK",
    "LTP*": "11.7",
    "HIGH": "11.8",
    "LOW": "11.7",
    "OPENP*": "11.7",
    "CLOSEP*": "11.7",
    "YCP": "11.7",
    "TRADE": "140",
    "VALUE (mn)": "3.775",
    "VOLUME": "322615"
  },
  {
    "#": "146",
    "DATE": "2025-12-07",
    "TRADING CODE": "NCCBANK",
    "LTP*": "11.7",
    "HIGH": "11.8",
    "LOW": "11.7",
    "OPENP*": "11.8",
    "CLOSEP*": "11.7",
    "YCP": "11.7",
    "TRADE": "34",
    "VALUE (mn)": "0.875",
    "VOLUME": "74819"
  },
  {
    "#": "145",
    "DATE": "2025-12-08",
    "TRADING CODE": "NCCBANK",
    "LTP*": "11.8",
    "HIGH": "11.8",
    "LOW": "11.7",
    "OPENP*": "11.7",
    "CLOSEP*": "11.8",
    "YCP": "11.7",
    "TRADE": "75",
    "VALUE (mn)": "1.741",
    "VOLUME": "148466"
  },
  {
    "#": "144",
    "DATE": "2025-12-09",
    "TRADING CODE": "NCCBANK",
    "LTP*": "11.8",
    "HIGH": "11.9",
    "LOW": "11.8",
    "OPENP*": "11.8",
    "CLOSEP*": "11.8",
    "YCP": "11.8",
    "TRADE": "110",
    "VALUE (mn)": "2.157",
    "VOLUME": "182496"
  },
  {
    "#": "143",
    "DATE": "2025-12-10",
    "TRADING CODE": "NCCBANK",
    "LTP*": "11.7",
    "HIGH": "12",
    "LOW": "11.7",
    "OPENP*": "11.9",
    "CLOSEP*": "11.8",
    "YCP": "11.8",
    "TRADE": "74",
    "VALUE (mn)": "2.659",
    "VOLUME": "225550"
  },
  {
    "#": "142",
    "DATE": "2025-12-11",
    "TRADING CODE": "NCCBANK",
    "LTP*": "11.9",
    "HIGH": "12",
    "LOW": "11.7",
    "OPENP*": "11.8",
    "CLOSEP*": "11.9",
    "YCP": "11.8",
    "TRADE": "83",
    "VALUE (mn)": "3.125",
    "VOLUME": "263860"
  },
  {
    "#": "141",
    "DATE": "2025-12-14",
    "TRADING CODE": "NCCBANK",
    "LTP*": "11.8",
    "HIGH": "11.9",
    "LOW": "11.7",
    "OPENP*": "11.8",
    "CLOSEP*": "11.8",
    "YCP": "11.9",
    "TRADE": "48",
    "VALUE (mn)": "1.3",
    "VOLUME": "110159"
  },
  {
    "#": "140",
    "DATE": "2025-12-15",
    "TRADING CODE": "NCCBANK",
    "LTP*": "11.7",
    "HIGH": "11.8",
    "LOW": "11.7",
    "OPENP*": "11.8",
    "CLOSEP*": "11.7",
    "YCP": "11.8",
    "TRADE": "63",
    "VALUE (mn)": "2.207",
    "VOLUME": "188602"
  },
  {
    "#": "139",
    "DATE": "2025-12-17",
    "TRADING CODE": "NCCBANK",
    "LTP*": "11.7",
    "HIGH": "11.8",
    "LOW": "11.7",
    "OPENP*": "11.8",
    "CLOSEP*": "11.7",
    "YCP": "11.7",
    "TRADE": "56",
    "VALUE (mn)": "0.908",
    "VOLUME": "77358"
  },
  {
    "#": "138",
    "DATE": "2025-12-18",
    "TRADING CODE": "NCCBANK",
    "LTP*": "11.7",
    "HIGH": "11.8",
    "LOW": "11.7",
    "OPENP*": "11.7",
    "CLOSEP*": "11.7",
    "YCP": "11.7",
    "TRADE": "71",
    "VALUE (mn)": "3.035",
    "VOLUME": "259381"
  },
  {
    "#": "137",
    "DATE": "2025-12-21",
    "TRADING CODE": "NCCBANK",
    "LTP*": "11.8",
    "HIGH": "11.8",
    "LOW": "11.6",
    "OPENP*": "11.6",
    "CLOSEP*": "11.8",
    "YCP": "11.7",
    "TRADE": "51",
    "VALUE (mn)": "2.193",
    "VOLUME": "187229"
  },
  {
    "#": "136",
    "DATE": "2025-12-22",
    "TRADING CODE": "NCCBANK",
    "LTP*": "11.8",
    "HIGH": "11.9",
    "LOW": "11.7",
    "OPENP*": "11.9",
    "CLOSEP*": "11.8",
    "YCP": "11.8",
    "TRADE": "76",
    "VALUE (mn)": "2.116",
    "VOLUME": "179348"
  },
  {
    "#": "135",
    "DATE": "2025-12-23",
    "TRADING CODE": "NCCBANK",
    "LTP*": "11.8",
    "HIGH": "11.9",
    "LOW": "11.7",
    "OPENP*": "11.7",
    "CLOSEP*": "11.8",
    "YCP": "11.8",
    "TRADE": "35",
    "VALUE (mn)": "2.189",
    "VOLUME": "185475"
  },
  {
    "#": "134",
    "DATE": "2025-12-24",
    "TRADING CODE": "NCCBANK",
    "LTP*": "12",
    "HIGH": "12.1",
    "LOW": "11.8",
    "OPENP*": "11.8",
    "CLOSEP*": "12",
    "YCP": "11.8",
    "TRADE": "124",
    "VALUE (mn)": "6.147",
    "VOLUME": "512490"
  },
  {
    "#": "133",
    "DATE": "2025-12-28",
    "TRADING CODE": "NCCBANK",
    "LTP*": "12",
    "HIGH": "12.1",
    "LOW": "11.9",
    "OPENP*": "12.1",
    "CLOSEP*": "12.1",
    "YCP": "12",
    "TRADE": "78",
    "VALUE (mn)": "1.398",
    "VOLUME": "116157"
  },
  {
    "#": "132",
    "DATE": "2025-12-29",
    "TRADING CODE": "NCCBANK",
    "LTP*": "12.1",
    "HIGH": "12.1",
    "LOW": "11.9",
    "OPENP*": "12.1",
    "CLOSEP*": "12.1",
    "YCP": "12.1",
    "TRADE": "90",
    "VALUE (mn)": "2.387",
    "VOLUME": "197961"
  },
  {
    "#": "131",
    "DATE": "2025-12-30",
    "TRADING CODE": "NCCBANK",
    "LTP*": "12.2",
    "HIGH": "12.2",
    "LOW": "11.9",
    "OPENP*": "11.9",
    "CLOSEP*": "12.2",
    "YCP": "12.1",
    "TRADE": "105",
    "VALUE (mn)": "1.064",
    "VOLUME": "87793"
  },
  {
    "#": "130",
    "DATE": "2026-01-01",
    "TRADING CODE": "NCCBANK",
    "LTP*": "12.4",
    "HIGH": "12.5",
    "LOW": "12.1",
    "OPENP*": "12.2",
    "CLOSEP*": "12.4",
    "YCP": "12.2",
    "TRADE": "169",
    "VALUE (mn)": "6.447",
    "VOLUME": "524494"
  },
  {
    "#": "129",
    "DATE": "2026-01-04",
    "TRADING CODE": "NCCBANK",
    "LTP*": "12.6",
    "HIGH": "12.9",
    "LOW": "12.3",
    "OPENP*": "12.5",
    "CLOSEP*": "12.6",
    "YCP": "12.4",
    "TRADE": "436",
    "VALUE (mn)": "37.8",
    "VOLUME": "2986063"
  },
  {
    "#": "128",
    "DATE": "2026-01-05",
    "TRADING CODE": "NCCBANK",
    "LTP*": "12.4",
    "HIGH": "12.7",
    "LOW": "12.3",
    "OPENP*": "12.5",
    "CLOSEP*": "12.5",
    "YCP": "12.6",
    "TRADE": "276",
    "VALUE (mn)": "18.909",
    "VOLUME": "1511301"
  },
  {
    "#": "127",
    "DATE": "2026-01-06",
    "TRADING CODE": "NCCBANK",
    "LTP*": "12.4",
    "HIGH": "12.5",
    "LOW": "12.3",
    "OPENP*": "12.5",
    "CLOSEP*": "12.4",
    "YCP": "12.5",
    "TRADE": "168",
    "VALUE (mn)": "9.196",
    "VOLUME": "738679"
  },
  {
    "#": "126",
    "DATE": "2026-01-07",
    "TRADING CODE": "NCCBANK",
    "LTP*": "12.7",
    "HIGH": "12.8",
    "LOW": "12.4",
    "OPENP*": "12.6",
    "CLOSEP*": "12.7",
    "YCP": "12.4",
    "TRADE": "311",
    "VALUE (mn)": "17.661",
    "VOLUME": "1399623"
  },
  {
    "#": "125",
    "DATE": "2026-01-08",
    "TRADING CODE": "NCCBANK",
    "LTP*": "12.7",
    "HIGH": "12.8",
    "LOW": "12.5",
    "OPENP*": "12.7",
    "CLOSEP*": "12.7",
    "YCP": "12.7",
    "TRADE": "197",
    "VALUE (mn)": "12.944",
    "VOLUME": "1025022"
  },
  {
    "#": "124",
    "DATE": "2026-01-11",
    "TRADING CODE": "NCCBANK",
    "LTP*": "12.5",
    "HIGH": "12.7",
    "LOW": "12.3",
    "OPENP*": "12.7",
    "CLOSEP*": "12.5",
    "YCP": "12.7",
    "TRADE": "212",
    "VALUE (mn)": "9.584",
    "VOLUME": "768864"
  },
  {
    "#": "123",
    "DATE": "2026-01-12",
    "TRADING CODE": "NCCBANK",
    "LTP*": "12.4",
    "HIGH": "12.5",
    "LOW": "12.3",
    "OPENP*": "12.4",
    "CLOSEP*": "12.4",
    "YCP": "12.5",
    "TRADE": "162",
    "VALUE (mn)": "4.85",
    "VOLUME": "391064"
  },
  {
    "#": "122",
    "DATE": "2026-01-13",
    "TRADING CODE": "NCCBANK",
    "LTP*": "12.4",
    "HIGH": "12.5",
    "LOW": "12.4",
    "OPENP*": "12.4",
    "CLOSEP*": "12.4",
    "YCP": "12.4",
    "TRADE": "138",
    "VALUE (mn)": "3.755",
    "VOLUME": "302529"
  },
  {
    "#": "121",
    "DATE": "2026-01-14",
    "TRADING CODE": "NCCBANK",
    "LTP*": "12.5",
    "HIGH": "12.5",
    "LOW": "12.3",
    "OPENP*": "12.5",
    "CLOSEP*": "12.4",
    "YCP": "12.4",
    "TRADE": "107",
    "VALUE (mn)": "4.102",
    "VOLUME": "330965"
  },
  {
    "#": "120",
    "DATE": "2026-01-15",
    "TRADING CODE": "NCCBANK",
    "LTP*": "12.4",
    "HIGH": "12.4",
    "LOW": "12.3",
    "OPENP*": "12.3",
    "CLOSEP*": "12.4",
    "YCP": "12.4",
    "TRADE": "87",
    "VALUE (mn)": "2.967",
    "VOLUME": "239814"
  },
  {
    "#": "119",
    "DATE": "2026-01-18",
    "TRADING CODE": "NCCBANK",
    "LTP*": "12.6",
    "HIGH": "12.7",
    "LOW": "12.3",
    "OPENP*": "12.3",
    "CLOSEP*": "12.6",
    "YCP": "12.4",
    "TRADE": "140",
    "VALUE (mn)": "8.244",
    "VOLUME": "656103"
  },
  {
    "#": "118",
    "DATE": "2026-01-19",
    "TRADING CODE": "NCCBANK",
    "LTP*": "12.7",
    "HIGH": "12.7",
    "LOW": "12.5",
    "OPENP*": "12.6",
    "CLOSEP*": "12.7",
    "YCP": "12.6",
    "TRADE": "228",
    "VALUE (mn)": "13.002",
    "VOLUME": "1028654"
  },
  {
    "#": "117",
    "DATE": "2026-01-20",
    "TRADING CODE": "NCCBANK",
    "LTP*": "12.7",
    "HIGH": "12.7",
    "LOW": "12.5",
    "OPENP*": "12.6",
    "CLOSEP*": "12.7",
    "YCP": "12.7",
    "TRADE": "214",
    "VALUE (mn)": "8.152",
    "VOLUME": "645329"
  },
  {
    "#": "116",
    "DATE": "2026-01-21",
    "TRADING CODE": "NCCBANK",
    "LTP*": "12.6",
    "HIGH": "12.7",
    "LOW": "12.5",
    "OPENP*": "12.6",
    "CLOSEP*": "12.6",
    "YCP": "12.7",
    "TRADE": "115",
    "VALUE (mn)": "7.671",
    "VOLUME": "609367"
  },
  {
    "#": "115",
    "DATE": "2026-01-22",
    "TRADING CODE": "NCCBANK",
    "LTP*": "12.5",
    "HIGH": "12.7",
    "LOW": "12.4",
    "OPENP*": "12.4",
    "CLOSEP*": "12.5",
    "YCP": "12.6",
    "TRADE": "142",
    "VALUE (mn)": "5.669",
    "VOLUME": "452966"
  },
  {
    "#": "114",
    "DATE": "2026-01-25",
    "TRADING CODE": "NCCBANK",
    "LTP*": "12.5",
    "HIGH": "12.6",
    "LOW": "12.4",
    "OPENP*": "12.5",
    "CLOSEP*": "12.5",
    "YCP": "12.5",
    "TRADE": "79",
    "VALUE (mn)": "5.934",
    "VOLUME": "474930"
  },
  {
    "#": "113",
    "DATE": "2026-01-26",
    "TRADING CODE": "NCCBANK",
    "LTP*": "12.5",
    "HIGH": "12.6",
    "LOW": "12.4",
    "OPENP*": "12.5",
    "CLOSEP*": "12.5",
    "YCP": "12.5",
    "TRADE": "96",
    "VALUE (mn)": "4.173",
    "VOLUME": "334732"
  },
  {
    "#": "112",
    "DATE": "2026-01-27",
    "TRADING CODE": "NCCBANK",
    "LTP*": "12.5",
    "HIGH": "12.6",
    "LOW": "12.4",
    "OPENP*": "12.6",
    "CLOSEP*": "12.5",
    "YCP": "12.5",
    "TRADE": "232",
    "VALUE (mn)": "18.134",
    "VOLUME": "1446944"
  },
  {
    "#": "111",
    "DATE": "2026-01-28",
    "TRADING CODE": "NCCBANK",
    "LTP*": "12.7",
    "HIGH": "12.8",
    "LOW": "12.6",
    "OPENP*": "12.7",
    "CLOSEP*": "12.7",
    "YCP": "12.5",
    "TRADE": "284",
    "VALUE (mn)": "17.718",
    "VOLUME": "1393499"
  },
  {
    "#": "110",
    "DATE": "2026-01-29",
    "TRADING CODE": "NCCBANK",
    "LTP*": "12.8",
    "HIGH": "12.9",
    "LOW": "12.6",
    "OPENP*": "12.6",
    "CLOSEP*": "12.8",
    "YCP": "12.7",
    "TRADE": "277",
    "VALUE (mn)": "12.407",
    "VOLUME": "971476"
  },
  {
    "#": "109",
    "DATE": "2026-02-01",
    "TRADING CODE": "NCCBANK",
    "LTP*": "13",
    "HIGH": "13.1",
    "LOW": "12.8",
    "OPENP*": "12.8",
    "CLOSEP*": "13",
    "YCP": "12.8",
    "TRADE": "437",
    "VALUE (mn)": "38.594",
    "VOLUME": "2981108"
  },
  {
    "#": "108",
    "DATE": "2026-02-02",
    "TRADING CODE": "NCCBANK",
    "LTP*": "13.1",
    "HIGH": "13.2",
    "LOW": "12.8",
    "OPENP*": "13",
    "CLOSEP*": "13",
    "YCP": "13",
    "TRADE": "373",
    "VALUE (mn)": "27.944",
    "VOLUME": "2144768"
  },
  {
    "#": "107",
    "DATE": "2026-02-03",
    "TRADING CODE": "NCCBANK",
    "LTP*": "13",
    "HIGH": "13.1",
    "LOW": "12.9",
    "OPENP*": "13.1",
    "CLOSEP*": "13",
    "YCP": "13",
    "TRADE": "191",
    "VALUE (mn)": "17.383",
    "VOLUME": "1341645"
  },
  {
    "#": "106",
    "DATE": "2026-02-05",
    "TRADING CODE": "NCCBANK",
    "LTP*": "12.7",
    "HIGH": "13",
    "LOW": "12.7",
    "OPENP*": "12.9",
    "CLOSEP*": "12.7",
    "YCP": "13",
    "TRADE": "194",
    "VALUE (mn)": "11.859",
    "VOLUME": "924560"
  },
  {
    "#": "105",
    "DATE": "2026-02-08",
    "TRADING CODE": "NCCBANK",
    "LTP*": "12.9",
    "HIGH": "12.9",
    "LOW": "12.6",
    "OPENP*": "12.9",
    "CLOSEP*": "12.9",
    "YCP": "12.7",
    "TRADE": "115",
    "VALUE (mn)": "7.97",
    "VOLUME": "621225"
  },
  {
    "#": "104",
    "DATE": "2026-02-09",
    "TRADING CODE": "NCCBANK",
    "LTP*": "12.9",
    "HIGH": "13",
    "LOW": "12.8",
    "OPENP*": "12.9",
    "CLOSEP*": "12.9",
    "YCP": "12.9",
    "TRADE": "264",
    "VALUE (mn)": "15.48",
    "VOLUME": "1198466"
  },
  {
    "#": "103",
    "DATE": "2026-02-10",
    "TRADING CODE": "NCCBANK",
    "LTP*": "13",
    "HIGH": "13.1",
    "LOW": "12.9",
    "OPENP*": "13",
    "CLOSEP*": "13",
    "YCP": "12.9",
    "TRADE": "356",
    "VALUE (mn)": "21.247",
    "VOLUME": "1636041"
  },
  {
    "#": "102",
    "DATE": "2026-02-15",
    "TRADING CODE": "NCCBANK",
    "LTP*": "13.5",
    "HIGH": "13.7",
    "LOW": "13.1",
    "OPENP*": "13.1",
    "CLOSEP*": "13.5",
    "YCP": "13",
    "TRADE": "622",
    "VALUE (mn)": "44.95",
    "VOLUME": "3339748"
  },
  {
    "#": "101",
    "DATE": "2026-02-16",
    "TRADING CODE": "NCCBANK",
    "LTP*": "13.4",
    "HIGH": "13.6",
    "LOW": "13.2",
    "OPENP*": "13.6",
    "CLOSEP*": "13.4",
    "YCP": "13.5",
    "TRADE": "497",
    "VALUE (mn)": "21.489",
    "VOLUME": "1609335"
  },
  {
    "#": "100",
    "DATE": "2026-02-17",
    "TRADING CODE": "NCCBANK",
    "LTP*": "13.1",
    "HIGH": "13.3",
    "LOW": "13",
    "OPENP*": "13.3",
    "CLOSEP*": "13.1",
    "YCP": "13.4",
    "TRADE": "398",
    "VALUE (mn)": "16.242",
    "VOLUME": "1232950"
  },
  {
    "#": "99",
    "DATE": "2026-02-18",
    "TRADING CODE": "NCCBANK",
    "LTP*": "12.9",
    "HIGH": "13.3",
    "LOW": "12.9",
    "OPENP*": "13.3",
    "CLOSEP*": "12.9",
    "YCP": "13.1",
    "TRADE": "319",
    "VALUE (mn)": "13.656",
    "VOLUME": "1051896"
  },
  {
    "#": "98",
    "DATE": "2026-02-19",
    "TRADING CODE": "NCCBANK",
    "LTP*": "12.8",
    "HIGH": "13",
    "LOW": "12.8",
    "OPENP*": "12.9",
    "CLOSEP*": "12.8",
    "YCP": "12.9",
    "TRADE": "204",
    "VALUE (mn)": "7.906",
    "VOLUME": "614273"
  },
  {
    "#": "97",
    "DATE": "2026-02-22",
    "TRADING CODE": "NCCBANK",
    "LTP*": "12.9",
    "HIGH": "13",
    "LOW": "12.8",
    "OPENP*": "12.8",
    "CLOSEP*": "12.9",
    "YCP": "12.8",
    "TRADE": "164",
    "VALUE (mn)": "4.378",
    "VOLUME": "340666"
  },
  {
    "#": "96",
    "DATE": "2026-02-23",
    "TRADING CODE": "NCCBANK",
    "LTP*": "13.1",
    "HIGH": "13.1",
    "LOW": "12.9",
    "OPENP*": "13",
    "CLOSEP*": "13.1",
    "YCP": "12.9",
    "TRADE": "209",
    "VALUE (mn)": "11.988",
    "VOLUME": "919493"
  },
  {
    "#": "95",
    "DATE": "2026-02-24",
    "TRADING CODE": "NCCBANK",
    "LTP*": "12.9",
    "HIGH": "13.3",
    "LOW": "12.9",
    "OPENP*": "13.2",
    "CLOSEP*": "12.9",
    "YCP": "13.1",
    "TRADE": "248",
    "VALUE (mn)": "9.34",
    "VOLUME": "717147"
  },
  {
    "#": "94",
    "DATE": "2026-02-25",
    "TRADING CODE": "NCCBANK",
    "LTP*": "12.9",
    "HIGH": "13",
    "LOW": "12.8",
    "OPENP*": "12.9",
    "CLOSEP*": "12.9",
    "YCP": "12.9",
    "TRADE": "133",
    "VALUE (mn)": "7.065",
    "VOLUME": "547468"
  },
  {
    "#": "93",
    "DATE": "2026-02-26",
    "TRADING CODE": "NCCBANK",
    "LTP*": "13.3",
    "HIGH": "13.4",
    "LOW": "12.9",
    "OPENP*": "13",
    "CLOSEP*": "13.3",
    "YCP": "12.9",
    "TRADE": "432",
    "VALUE (mn)": "24.717",
    "VOLUME": "1872632"
  },
  {
    "#": "92",
    "DATE": "2026-03-01",
    "TRADING CODE": "NCCBANK",
    "LTP*": "13",
    "HIGH": "13.2",
    "LOW": "12.8",
    "OPENP*": "13.2",
    "CLOSEP*": "13",
    "YCP": "13.3",
    "TRADE": "286",
    "VALUE (mn)": "15.85",
    "VOLUME": "1224859"
  },
  {
    "#": "91",
    "DATE": "2026-03-02",
    "TRADING CODE": "NCCBANK",
    "LTP*": "13.1",
    "HIGH": "13.2",
    "LOW": "12.9",
    "OPENP*": "13",
    "CLOSEP*": "13.1",
    "YCP": "13",
    "TRADE": "186",
    "VALUE (mn)": "8.893",
    "VOLUME": "679993"
  },
  {
    "#": "90",
    "DATE": "2026-03-03",
    "TRADING CODE": "NCCBANK",
    "LTP*": "12.6",
    "HIGH": "13",
    "LOW": "12.5",
    "OPENP*": "13",
    "CLOSEP*": "12.6",
    "YCP": "13.1",
    "TRADE": "472",
    "VALUE (mn)": "37.397",
    "VOLUME": "2946336"
  },
  {
    "#": "89",
    "DATE": "2026-03-04",
    "TRADING CODE": "NCCBANK",
    "LTP*": "12.7",
    "HIGH": "12.8",
    "LOW": "12.4",
    "OPENP*": "12.5",
    "CLOSEP*": "12.7",
    "YCP": "12.6",
    "TRADE": "208",
    "VALUE (mn)": "9.827",
    "VOLUME": "785950"
  },
  {
    "#": "88",
    "DATE": "2026-03-05",
    "TRADING CODE": "NCCBANK",
    "LTP*": "12.6",
    "HIGH": "12.7",
    "LOW": "12.5",
    "OPENP*": "12.7",
    "CLOSEP*": "12.6",
    "YCP": "12.7",
    "TRADE": "156",
    "VALUE (mn)": "6.827",
    "VOLUME": "543449"
  },
  {
    "#": "87",
    "DATE": "2026-03-08",
    "TRADING CODE": "NCCBANK",
    "LTP*": "12.4",
    "HIGH": "12.6",
    "LOW": "12.3",
    "OPENP*": "12.6",
    "CLOSEP*": "12.4",
    "YCP": "12.6",
    "TRADE": "371",
    "VALUE (mn)": "17.367",
    "VOLUME": "1401131"
  },
  {
    "#": "86",
    "DATE": "2026-03-09",
    "TRADING CODE": "NCCBANK",
    "LTP*": "12.6",
    "HIGH": "12.7",
    "LOW": "12.2",
    "OPENP*": "12.5",
    "CLOSEP*": "12.6",
    "YCP": "12.4",
    "TRADE": "214",
    "VALUE (mn)": "5.973",
    "VOLUME": "481069"
  },
  {
    "#": "85",
    "DATE": "2026-03-10",
    "TRADING CODE": "NCCBANK",
    "LTP*": "12.9",
    "HIGH": "12.9",
    "LOW": "12.6",
    "OPENP*": "12.6",
    "CLOSEP*": "12.8",
    "YCP": "12.6",
    "TRADE": "205",
    "VALUE (mn)": "8.702",
    "VOLUME": "683658"
  },
  {
    "#": "84",
    "DATE": "2026-03-11",
    "TRADING CODE": "NCCBANK",
    "LTP*": "12.8",
    "HIGH": "13",
    "LOW": "12.7",
    "OPENP*": "12.8",
    "CLOSEP*": "12.8",
    "YCP": "12.8",
    "TRADE": "118",
    "VALUE (mn)": "4.801",
    "VOLUME": "375401"
  },
  {
    "#": "83",
    "DATE": "2026-03-12",
    "TRADING CODE": "NCCBANK",
    "LTP*": "13",
    "HIGH": "13.1",
    "LOW": "12.7",
    "OPENP*": "12.8",
    "CLOSEP*": "13",
    "YCP": "12.8",
    "TRADE": "162",
    "VALUE (mn)": "7.386",
    "VOLUME": "569625"
  },
  {
    "#": "82",
    "DATE": "2026-03-15",
    "TRADING CODE": "NCCBANK",
    "LTP*": "13",
    "HIGH": "13",
    "LOW": "12.8",
    "OPENP*": "12.9",
    "CLOSEP*": "13",
    "YCP": "13",
    "TRADE": "105",
    "VALUE (mn)": "4.755",
    "VOLUME": "367946"
  },
  {
    "#": "81",
    "DATE": "2026-03-16",
    "TRADING CODE": "NCCBANK",
    "LTP*": "13",
    "HIGH": "13",
    "LOW": "12.9",
    "OPENP*": "13",
    "CLOSEP*": "13",
    "YCP": "13",
    "TRADE": "132",
    "VALUE (mn)": "7.421",
    "VOLUME": "571876"
  },
  {
    "#": "80",
    "DATE": "2026-03-24",
    "TRADING CODE": "NCCBANK",
    "LTP*": "12.9",
    "HIGH": "13",
    "LOW": "12.8",
    "OPENP*": "13",
    "CLOSEP*": "12.9",
    "YCP": "13",
    "TRADE": "152",
    "VALUE (mn)": "9.957",
    "VOLUME": "772015"
  },
  {
    "#": "79",
    "DATE": "2026-03-25",
    "TRADING CODE": "NCCBANK",
    "LTP*": "13",
    "HIGH": "13",
    "LOW": "12.9",
    "OPENP*": "12.9",
    "CLOSEP*": "13",
    "YCP": "12.9",
    "TRADE": "142",
    "VALUE (mn)": "10.529",
    "VOLUME": "812790"
  },
  {
    "#": "78",
    "DATE": "2026-03-29",
    "TRADING CODE": "NCCBANK",
    "LTP*": "12.9",
    "HIGH": "13",
    "LOW": "12.9",
    "OPENP*": "12.9",
    "CLOSEP*": "12.9",
    "YCP": "13",
    "TRADE": "108",
    "VALUE (mn)": "5.639",
    "VOLUME": "436882"
  },
  {
    "#": "77",
    "DATE": "2026-03-30",
    "TRADING CODE": "NCCBANK",
    "LTP*": "12.9",
    "HIGH": "13",
    "LOW": "12.8",
    "OPENP*": "12.9",
    "CLOSEP*": "12.9",
    "YCP": "12.9",
    "TRADE": "156",
    "VALUE (mn)": "9.367",
    "VOLUME": "726580"
  },
  {
    "#": "76",
    "DATE": "2026-03-31",
    "TRADING CODE": "NCCBANK",
    "LTP*": "12.8",
    "HIGH": "13",
    "LOW": "12.7",
    "OPENP*": "13",
    "CLOSEP*": "12.8",
    "YCP": "12.9",
    "TRADE": "189",
    "VALUE (mn)": "9.457",
    "VOLUME": "738775"
  },
  {
    "#": "75",
    "DATE": "2026-04-01",
    "TRADING CODE": "NCCBANK",
    "LTP*": "12.9",
    "HIGH": "13",
    "LOW": "12.8",
    "OPENP*": "12.8",
    "CLOSEP*": "12.9",
    "YCP": "12.8",
    "TRADE": "96",
    "VALUE (mn)": "4.977",
    "VOLUME": "386179"
  },
  {
    "#": "74",
    "DATE": "2026-04-02",
    "TRADING CODE": "NCCBANK",
    "LTP*": "12.8",
    "HIGH": "13",
    "LOW": "12.8",
    "OPENP*": "13",
    "CLOSEP*": "12.8",
    "YCP": "12.9",
    "TRADE": "126",
    "VALUE (mn)": "7.666",
    "VOLUME": "598151"
  },
  {
    "#": "73",
    "DATE": "2026-04-05",
    "TRADING CODE": "NCCBANK",
    "LTP*": "12.7",
    "HIGH": "12.8",
    "LOW": "12.7",
    "OPENP*": "12.8",
    "CLOSEP*": "12.7",
    "YCP": "12.8",
    "TRADE": "154",
    "VALUE (mn)": "6.038",
    "VOLUME": "474539"
  },
  {
    "#": "72",
    "DATE": "2026-04-06",
    "TRADING CODE": "NCCBANK",
    "LTP*": "12.7",
    "HIGH": "12.9",
    "LOW": "12.7",
    "OPENP*": "12.8",
    "CLOSEP*": "12.7",
    "YCP": "12.7",
    "TRADE": "73",
    "VALUE (mn)": "1.887",
    "VOLUME": "147803"
  },
  {
    "#": "71",
    "DATE": "2026-04-07",
    "TRADING CODE": "NCCBANK",
    "LTP*": "12.7",
    "HIGH": "12.9",
    "LOW": "12.7",
    "OPENP*": "12.9",
    "CLOSEP*": "12.7",
    "YCP": "12.7",
    "TRADE": "101",
    "VALUE (mn)": "5.608",
    "VOLUME": "438423"
  },
  {
    "#": "70",
    "DATE": "2026-04-08",
    "TRADING CODE": "NCCBANK",
    "LTP*": "13",
    "HIGH": "13.1",
    "LOW": "12.8",
    "OPENP*": "12.8",
    "CLOSEP*": "13",
    "YCP": "12.7",
    "TRADE": "581",
    "VALUE (mn)": "14.133",
    "VOLUME": "1089445"
  },
  {
    "#": "69",
    "DATE": "2026-04-09",
    "TRADING CODE": "NCCBANK",
    "LTP*": "12.9",
    "HIGH": "13",
    "LOW": "12.8",
    "OPENP*": "13",
    "CLOSEP*": "12.9",
    "YCP": "13",
    "TRADE": "128",
    "VALUE (mn)": "7.049",
    "VOLUME": "546334"
  },
  {
    "#": "68",
    "DATE": "2026-04-12",
    "TRADING CODE": "NCCBANK",
    "LTP*": "13.1",
    "HIGH": "13.1",
    "LOW": "12.9",
    "OPENP*": "13",
    "CLOSEP*": "13.1",
    "YCP": "12.9",
    "TRADE": "182",
    "VALUE (mn)": "8.755",
    "VOLUME": "673927"
  },
  {
    "#": "67",
    "DATE": "2026-04-13",
    "TRADING CODE": "NCCBANK",
    "LTP*": "13.1",
    "HIGH": "13.2",
    "LOW": "13",
    "OPENP*": "13.1",
    "CLOSEP*": "13.1",
    "YCP": "13.1",
    "TRADE": "146",
    "VALUE (mn)": "8.413",
    "VOLUME": "643234"
  },
  {
    "#": "66",
    "DATE": "2026-04-15",
    "TRADING CODE": "NCCBANK",
    "LTP*": "13",
    "HIGH": "13.2",
    "LOW": "13",
    "OPENP*": "13.2",
    "CLOSEP*": "13",
    "YCP": "13.1",
    "TRADE": "96",
    "VALUE (mn)": "4.89",
    "VOLUME": "374019"
  },
  {
    "#": "65",
    "DATE": "2026-04-16",
    "TRADING CODE": "NCCBANK",
    "LTP*": "13.1",
    "HIGH": "13.2",
    "LOW": "13",
    "OPENP*": "13",
    "CLOSEP*": "13.1",
    "YCP": "13",
    "TRADE": "131",
    "VALUE (mn)": "6.474",
    "VOLUME": "494592"
  },
  {
    "#": "64",
    "DATE": "2026-04-19",
    "TRADING CODE": "NCCBANK",
    "LTP*": "13",
    "HIGH": "13.1",
    "LOW": "13",
    "OPENP*": "13",
    "CLOSEP*": "13",
    "YCP": "13.1",
    "TRADE": "119",
    "VALUE (mn)": "8.473",
    "VOLUME": "651481"
  },
  {
    "#": "63",
    "DATE": "2026-04-20",
    "TRADING CODE": "NCCBANK",
    "LTP*": "13.2",
    "HIGH": "13.2",
    "LOW": "13",
    "OPENP*": "13.1",
    "CLOSEP*": "13.2",
    "YCP": "13",
    "TRADE": "173",
    "VALUE (mn)": "8.405",
    "VOLUME": "641997"
  },
  {
    "#": "62",
    "DATE": "2026-04-21",
    "TRADING CODE": "NCCBANK",
    "LTP*": "13.3",
    "HIGH": "13.4",
    "LOW": "13.2",
    "OPENP*": "13.2",
    "CLOSEP*": "13.3",
    "YCP": "13.2",
    "TRADE": "277",
    "VALUE (mn)": "7.972",
    "VOLUME": "600124"
  },
  {
    "#": "61",
    "DATE": "2026-04-22",
    "TRADING CODE": "NCCBANK",
    "LTP*": "13.6",
    "HIGH": "13.6",
    "LOW": "13.3",
    "OPENP*": "13.4",
    "CLOSEP*": "13.6",
    "YCP": "13.3",
    "TRADE": "499",
    "VALUE (mn)": "30.632",
    "VOLUME": "2266788"
  },
  {
    "#": "60",
    "DATE": "2026-04-23",
    "TRADING CODE": "NCCBANK",
    "LTP*": "13.5",
    "HIGH": "13.7",
    "LOW": "13.4",
    "OPENP*": "13.7",
    "CLOSEP*": "13.5",
    "YCP": "13.6",
    "TRADE": "259",
    "VALUE (mn)": "12.904",
    "VOLUME": "956788"
  },
  {
    "#": "59",
    "DATE": "2026-04-26",
    "TRADING CODE": "NCCBANK",
    "LTP*": "14.1",
    "HIGH": "14.2",
    "LOW": "13.4",
    "OPENP*": "13.5",
    "CLOSEP*": "14.1",
    "YCP": "13.5",
    "TRADE": "725",
    "VALUE (mn)": "89.389",
    "VOLUME": "6476924"
  },
  {
    "#": "58",
    "DATE": "2026-04-27",
    "TRADING CODE": "NCCBANK",
    "LTP*": "14.3",
    "HIGH": "14.6",
    "LOW": "14.1",
    "OPENP*": "14.2",
    "CLOSEP*": "14.3",
    "YCP": "14.1",
    "TRADE": "804",
    "VALUE (mn)": "79.205",
    "VOLUME": "5515161"
  },
  {
    "#": "57",
    "DATE": "2026-04-28",
    "TRADING CODE": "NCCBANK",
    "LTP*": "17.3",
    "HIGH": "17.7",
    "LOW": "15.2",
    "OPENP*": "15.4",
    "CLOSEP*": "17.3",
    "YCP": "14.3",
    "TRADE": "5423",
    "VALUE (mn)": "837.313",
    "VOLUME": "50935968"
  },
  {
    "#": "56",
    "DATE": "2026-04-29",
    "TRADING CODE": "NCCBANK",
    "LTP*": "16.7",
    "HIGH": "17.7",
    "LOW": "16.4",
    "OPENP*": "17.4",
    "CLOSEP*": "16.7",
    "YCP": "17.3",
    "TRADE": "2561",
    "VALUE (mn)": "255.529",
    "VOLUME": "15096366"
  },
  {
    "#": "55",
    "DATE": "2026-04-30",
    "TRADING CODE": "NCCBANK",
    "LTP*": "16.9",
    "HIGH": "17.4",
    "LOW": "15.9",
    "OPENP*": "16.7",
    "CLOSEP*": "16.9",
    "YCP": "16.7",
    "TRADE": "2976",
    "VALUE (mn)": "385.785",
    "VOLUME": "22854409"
  },
  {
    "#": "54",
    "DATE": "2026-05-03",
    "TRADING CODE": "NCCBANK",
    "LTP*": "16.1",
    "HIGH": "17",
    "LOW": "15.9",
    "OPENP*": "17",
    "CLOSEP*": "16.1",
    "YCP": "16.9",
    "TRADE": "2895",
    "VALUE (mn)": "354.205",
    "VOLUME": "21558501"
  },
  {
    "#": "53",
    "DATE": "2026-05-04",
    "TRADING CODE": "NCCBANK",
    "LTP*": "17.1",
    "HIGH": "17.4",
    "LOW": "16.2",
    "OPENP*": "16.3",
    "CLOSEP*": "17.1",
    "YCP": "16.1",
    "TRADE": "2215",
    "VALUE (mn)": "397.373",
    "VOLUME": "23574297"
  },
  {
    "#": "52",
    "DATE": "2026-05-05",
    "TRADING CODE": "NCCBANK",
    "LTP*": "16.8",
    "HIGH": "17.2",
    "LOW": "16.7",
    "OPENP*": "17.1",
    "CLOSEP*": "16.8",
    "YCP": "17.1",
    "TRADE": "1746",
    "VALUE (mn)": "191.645",
    "VOLUME": "11305414"
  },
  {
    "#": "51",
    "DATE": "2026-05-06",
    "TRADING CODE": "NCCBANK",
    "LTP*": "16.5",
    "HIGH": "17.1",
    "LOW": "16.5",
    "OPENP*": "16.9",
    "CLOSEP*": "16.5",
    "YCP": "16.8",
    "TRADE": "1273",
    "VALUE (mn)": "100.585",
    "VOLUME": "6016250"
  },
  {
    "#": "50",
    "DATE": "2026-05-07",
    "TRADING CODE": "NCCBANK",
    "LTP*": "16.5",
    "HIGH": "16.8",
    "LOW": "16.3",
    "OPENP*": "16.6",
    "CLOSEP*": "16.5",
    "YCP": "16.5",
    "TRADE": "1109",
    "VALUE (mn)": "97.352",
    "VOLUME": "5903858"
  },
  {
    "#": "49",
    "DATE": "2026-05-10",
    "TRADING CODE": "NCCBANK",
    "LTP*": "16.4",
    "HIGH": "16.6",
    "LOW": "16.3",
    "OPENP*": "16.6",
    "CLOSEP*": "16.4",
    "YCP": "16.5",
    "TRADE": "930",
    "VALUE (mn)": "59.556",
    "VOLUME": "3616416"
  },
  {
    "#": "48",
    "DATE": "2026-05-11",
    "TRADING CODE": "NCCBANK",
    "LTP*": "16.1",
    "HIGH": "16.5",
    "LOW": "16",
    "OPENP*": "16.5",
    "CLOSEP*": "16.1",
    "YCP": "16.4",
    "TRADE": "1238",
    "VALUE (mn)": "83.873",
    "VOLUME": "5176073"
  },
  {
    "#": "47",
    "DATE": "2026-05-12",
    "TRADING CODE": "NCCBANK",
    "LTP*": "16.5",
    "HIGH": "16.7",
    "LOW": "16.1",
    "OPENP*": "16.4",
    "CLOSEP*": "16.5",
    "YCP": "16.1",
    "TRADE": "1008",
    "VALUE (mn)": "159.145",
    "VOLUME": "9669192"
  },
  {
    "#": "46",
    "DATE": "2026-05-13",
    "TRADING CODE": "NCCBANK",
    "LTP*": "16.7",
    "HIGH": "16.9",
    "LOW": "16.3",
    "OPENP*": "16.5",
    "CLOSEP*": "16.7",
    "YCP": "16.5",
    "TRADE": "984",
    "VALUE (mn)": "152.535",
    "VOLUME": "9207462"
  },
  {
    "#": "45",
    "DATE": "2026-05-14",
    "TRADING CODE": "NCCBANK",
    "LTP*": "16.8",
    "HIGH": "17.3",
    "LOW": "16.6",
    "OPENP*": "16.7",
    "CLOSEP*": "16.8",
    "YCP": "16.7",
    "TRADE": "1935",
    "VALUE (mn)": "371.656",
    "VOLUME": "21860697"
  },
  {
    "#": "44",
    "DATE": "2026-05-17",
    "TRADING CODE": "NCCBANK",
    "LTP*": "16.2",
    "HIGH": "17.2",
    "LOW": "16.1",
    "OPENP*": "17.2",
    "CLOSEP*": "16.2",
    "YCP": "16.8",
    "TRADE": "2005",
    "VALUE (mn)": "256.866",
    "VOLUME": "15612500"
  },
  {
    "#": "43",
    "DATE": "2026-05-18",
    "TRADING CODE": "NCCBANK",
    "LTP*": "16.1",
    "HIGH": "16.4",
    "LOW": "16",
    "OPENP*": "16.4",
    "CLOSEP*": "16.1",
    "YCP": "16.2",
    "TRADE": "1345",
    "VALUE (mn)": "116.091",
    "VOLUME": "7193470"
  },
  {
    "#": "42",
    "DATE": "2026-05-19",
    "TRADING CODE": "NCCBANK",
    "LTP*": "16.2",
    "HIGH": "16.3",
    "LOW": "16",
    "OPENP*": "16.1",
    "CLOSEP*": "16.2",
    "YCP": "16.1",
    "TRADE": "1069",
    "VALUE (mn)": "230.681",
    "VOLUME": "14319146"
  },
  {
    "#": "41",
    "DATE": "2026-05-20",
    "TRADING CODE": "NCCBANK",
    "LTP*": "15.9",
    "HIGH": "16.4",
    "LOW": "15.8",
    "OPENP*": "16.2",
    "CLOSEP*": "15.9",
    "YCP": "16.2",
    "TRADE": "2261",
    "VALUE (mn)": "423.586",
    "VOLUME": "26364569"
  },
  {
    "#": "40",
    "DATE": "2026-05-21",
    "TRADING CODE": "NCCBANK",
    "LTP*": "0",
    "HIGH": "0",
    "LOW": "0",
    "OPENP*": "0",
    "CLOSEP*": "15.9",
    "YCP": "15.9",
    "TRADE": "0",
    "VALUE (mn)": "0",
    "VOLUME": "0"
  },
  {
    "#": "39",
    "DATE": "2026-05-23",
    "TRADING CODE": "NCCBANK",
    "LTP*": "15",
    "HIGH": "15.1",
    "LOW": "14.1",
    "OPENP*": "14.5",
    "CLOSEP*": "15",
    "YCP": "15.9",
    "TRADE": "2527",
    "VALUE (mn)": "327.751",
    "VOLUME": "22021348"
  },
  {
    "#": "38",
    "DATE": "2026-05-24",
    "TRADING CODE": "NCCBANK",
    "LTP*": "14.6",
    "HIGH": "15.1",
    "LOW": "14.5",
    "OPENP*": "14.9",
    "CLOSEP*": "14.6",
    "YCP": "15",
    "TRADE": "1216",
    "VALUE (mn)": "117.007",
    "VOLUME": "7965283"
  },
  {
    "#": "37",
    "DATE": "2026-06-01",
    "TRADING CODE": "NCCBANK",
    "LTP*": "15.7",
    "HIGH": "15.8",
    "LOW": "14.6",
    "OPENP*": "14.6",
    "CLOSEP*": "15.7",
    "YCP": "14.6",
    "TRADE": "2591",
    "VALUE (mn)": "440.753",
    "VOLUME": "28595363"
  },
  {
    "#": "36",
    "DATE": "2026-06-02",
    "TRADING CODE": "NCCBANK",
    "LTP*": "15.6",
    "HIGH": "15.8",
    "LOW": "15.5",
    "OPENP*": "15.8",
    "CLOSEP*": "15.6",
    "YCP": "15.7",
    "TRADE": "1225",
    "VALUE (mn)": "116.511",
    "VOLUME": "7444115"
  },
  {
    "#": "35",
    "DATE": "2026-06-03",
    "TRADING CODE": "NCCBANK",
    "LTP*": "15.4",
    "HIGH": "15.9",
    "LOW": "15.2",
    "OPENP*": "15.7",
    "CLOSEP*": "15.4",
    "YCP": "15.6",
    "TRADE": "1509",
    "VALUE (mn)": "202.45",
    "VOLUME": "13020844"
  },
  {
    "#": "34",
    "DATE": "2026-06-04",
    "TRADING CODE": "NCCBANK",
    "LTP*": "15.5",
    "HIGH": "15.7",
    "LOW": "15.2",
    "OPENP*": "15.4",
    "CLOSEP*": "15.5",
    "YCP": "15.4",
    "TRADE": "1068",
    "VALUE (mn)": "339.879",
    "VOLUME": "21982432"
  },
  {
    "#": "33",
    "DATE": "2026-06-07",
    "TRADING CODE": "NCCBANK",
    "LTP*": "15.6",
    "HIGH": "15.8",
    "LOW": "15.5",
    "OPENP*": "15.6",
    "CLOSEP*": "15.6",
    "YCP": "15.5",
    "TRADE": "1170",
    "VALUE (mn)": "156.907",
    "VOLUME": "10033356"
  },
  {
    "#": "32",
    "DATE": "2026-06-08",
    "TRADING CODE": "NCCBANK",
    "LTP*": "16.1",
    "HIGH": "16.5",
    "LOW": "15.5",
    "OPENP*": "15.8",
    "CLOSEP*": "16.1",
    "YCP": "15.6",
    "TRADE": "2130",
    "VALUE (mn)": "251.867",
    "VOLUME": "15718417"
  },
  {
    "#": "31",
    "DATE": "2026-06-09",
    "TRADING CODE": "NCCBANK",
    "LTP*": "16.8",
    "HIGH": "17.6",
    "LOW": "16",
    "OPENP*": "16",
    "CLOSEP*": "16.8",
    "YCP": "16.1",
    "TRADE": "3542",
    "VALUE (mn)": "495.205",
    "VOLUME": "29331501"
  },
  {
    "#": "30",
    "DATE": "2026-06-10",
    "TRADING CODE": "NCCBANK",
    "LTP*": "16.8",
    "HIGH": "17.4",
    "LOW": "16.7",
    "OPENP*": "16.9",
    "CLOSEP*": "16.8",
    "YCP": "16.8",
    "TRADE": "1732",
    "VALUE (mn)": "236.123",
    "VOLUME": "13915253"
  },
  {
    "#": "29",
    "DATE": "2026-06-11",
    "TRADING CODE": "NCCBANK",
    "LTP*": "16.3",
    "HIGH": "17.1",
    "LOW": "16.1",
    "OPENP*": "16.8",
    "CLOSEP*": "16.3",
    "YCP": "16.8",
    "TRADE": "1800",
    "VALUE (mn)": "234.447",
    "VOLUME": "14166069"
  },
  {
    "#": "28",
    "DATE": "2026-06-14",
    "TRADING CODE": "NCCBANK",
    "LTP*": "16.6",
    "HIGH": "16.8",
    "LOW": "16.2",
    "OPENP*": "16.5",
    "CLOSEP*": "16.6",
    "YCP": "16.3",
    "TRADE": "1874",
    "VALUE (mn)": "220.047",
    "VOLUME": "13369939"
  },
  {
    "#": "27",
    "DATE": "2026-06-15",
    "TRADING CODE": "NCCBANK",
    "LTP*": "16.8",
    "HIGH": "17.2",
    "LOW": "16.6",
    "OPENP*": "16.7",
    "CLOSEP*": "16.8",
    "YCP": "16.6",
    "TRADE": "2707",
    "VALUE (mn)": "542.486",
    "VOLUME": "31951812"
  },
  {
    "#": "26",
    "DATE": "2026-06-16",
    "TRADING CODE": "NCCBANK",
    "LTP*": "16.6",
    "HIGH": "17.3",
    "LOW": "16.5",
    "OPENP*": "16.8",
    "CLOSEP*": "16.6",
    "YCP": "16.8",
    "TRADE": "2977",
    "VALUE (mn)": "522.975",
    "VOLUME": "30863601"
  },
  {
    "#": "25",
    "DATE": "2026-06-17",
    "TRADING CODE": "NCCBANK",
    "LTP*": "16.6",
    "HIGH": "16.8",
    "LOW": "16.4",
    "OPENP*": "16.6",
    "CLOSEP*": "16.6",
    "YCP": "16.6",
    "TRADE": "1581",
    "VALUE (mn)": "171.527",
    "VOLUME": "10360637"
  },
  {
    "#": "24",
    "DATE": "2026-06-18",
    "TRADING CODE": "NCCBANK",
    "LTP*": "16.2",
    "HIGH": "16.8",
    "LOW": "16.1",
    "OPENP*": "16.6",
    "CLOSEP*": "16.2",
    "YCP": "16.6",
    "TRADE": "2889",
    "VALUE (mn)": "342.488",
    "VOLUME": "20861891"
  },
  {
    "#": "23",
    "DATE": "2026-06-21",
    "TRADING CODE": "NCCBANK",
    "LTP*": "16",
    "HIGH": "16.5",
    "LOW": "15.9",
    "OPENP*": "16.4",
    "CLOSEP*": "16",
    "YCP": "16.2",
    "TRADE": "1904",
    "VALUE (mn)": "221.607",
    "VOLUME": "13674442"
  },
  {
    "#": "22",
    "DATE": "2026-06-22",
    "TRADING CODE": "NCCBANK",
    "LTP*": "15.6",
    "HIGH": "16",
    "LOW": "15.5",
    "OPENP*": "16",
    "CLOSEP*": "15.6",
    "YCP": "16",
    "TRADE": "1690",
    "VALUE (mn)": "131.374",
    "VOLUME": "8324097"
  },
  {
    "#": "21",
    "DATE": "2026-06-23",
    "TRADING CODE": "NCCBANK",
    "LTP*": "15.9",
    "HIGH": "16.1",
    "LOW": "15.6",
    "OPENP*": "15.6",
    "CLOSEP*": "15.9",
    "YCP": "15.6",
    "TRADE": "1152",
    "VALUE (mn)": "118.96",
    "VOLUME": "7517624"
  },
  {
    "#": "20",
    "DATE": "2026-06-24",
    "TRADING CODE": "NCCBANK",
    "LTP*": "15.9",
    "HIGH": "16.1",
    "LOW": "15.8",
    "OPENP*": "16",
    "CLOSEP*": "15.9",
    "YCP": "15.9",
    "TRADE": "1074",
    "VALUE (mn)": "152.601",
    "VOLUME": "9571030"
  },
  {
    "#": "19",
    "DATE": "2026-06-25",
    "TRADING CODE": "NCCBANK",
    "LTP*": "16",
    "HIGH": "16.2",
    "LOW": "15.8",
    "OPENP*": "16",
    "CLOSEP*": "16",
    "YCP": "15.9",
    "TRADE": "1275",
    "VALUE (mn)": "197.362",
    "VOLUME": "12328954"
  },
  {
    "#": "18",
    "DATE": "2026-06-28",
    "TRADING CODE": "NCCBANK",
    "LTP*": "16.1",
    "HIGH": "16.6",
    "LOW": "16",
    "OPENP*": "16.2",
    "CLOSEP*": "16.1",
    "YCP": "16",
    "TRADE": "2659",
    "VALUE (mn)": "488.724",
    "VOLUME": "29885459"
  },
  {
    "#": "17",
    "DATE": "2026-06-29",
    "TRADING CODE": "NCCBANK",
    "LTP*": "16",
    "HIGH": "16.4",
    "LOW": "15.9",
    "OPENP*": "16.2",
    "CLOSEP*": "16",
    "YCP": "16.1",
    "TRADE": "2179",
    "VALUE (mn)": "301.928",
    "VOLUME": "18689907"
  },
  {
    "#": "16",
    "DATE": "2026-06-30",
    "TRADING CODE": "NCCBANK",
    "LTP*": "16",
    "HIGH": "16.2",
    "LOW": "15.9",
    "OPENP*": "16",
    "CLOSEP*": "16",
    "YCP": "16",
    "TRADE": "2217",
    "VALUE (mn)": "224.175",
    "VOLUME": "14003882"
  },
  {
    "#": "15",
    "DATE": "2026-07-02",
    "TRADING CODE": "NCCBANK",
    "LTP*": "15.8",
    "HIGH": "16.1",
    "LOW": "15.7",
    "OPENP*": "16.1",
    "CLOSEP*": "15.8",
    "YCP": "16",
    "TRADE": "1946",
    "VALUE (mn)": "132.384",
    "VOLUME": "8362497"
  },
  {
    "#": "14",
    "DATE": "2026-07-05",
    "TRADING CODE": "NCCBANK",
    "LTP*": "15.9",
    "HIGH": "16.2",
    "LOW": "15.7",
    "OPENP*": "15.8",
    "CLOSEP*": "15.9",
    "YCP": "15.8",
    "TRADE": "1631",
    "VALUE (mn)": "220.165",
    "VOLUME": "13775179"
  },
  {
    "#": "13",
    "DATE": "2026-07-06",
    "TRADING CODE": "NCCBANK",
    "LTP*": "15.6",
    "HIGH": "16",
    "LOW": "15.5",
    "OPENP*": "16",
    "CLOSEP*": "15.6",
    "YCP": "15.9",
    "TRADE": "2437",
    "VALUE (mn)": "159.305",
    "VOLUME": "10182896"
  },
  {
    "#": "12",
    "DATE": "2026-07-07",
    "TRADING CODE": "NCCBANK",
    "LTP*": "15.5",
    "HIGH": "15.9",
    "LOW": "15.4",
    "OPENP*": "15.9",
    "CLOSEP*": "15.5",
    "YCP": "15.6",
    "TRADE": "1447",
    "VALUE (mn)": "72.833",
    "VOLUME": "4699468"
  },
  {
    "#": "11",
    "DATE": "2026-07-08",
    "TRADING CODE": "NCCBANK",
    "LTP*": "15.1",
    "HIGH": "15.6",
    "LOW": "15",
    "OPENP*": "15.5",
    "CLOSEP*": "15.1",
    "YCP": "15.5",
    "TRADE": "2289",
    "VALUE (mn)": "146.135",
    "VOLUME": "9604102"
  },
  {
    "#": "10",
    "DATE": "2026-07-09",
    "TRADING CODE": "NCCBANK",
    "LTP*": "14.9",
    "HIGH": "15.2",
    "LOW": "14.8",
    "OPENP*": "15.2",
    "CLOSEP*": "14.9",
    "YCP": "15.1",
    "TRADE": "1878",
    "VALUE (mn)": "118.042",
    "VOLUME": "7872997"
  },
  {
    "#": "9",
    "DATE": "2026-07-12",
    "TRADING CODE": "NCCBANK",
    "LTP*": "15.1",
    "HIGH": "15.3",
    "LOW": "14.8",
    "OPENP*": "14.9",
    "CLOSEP*": "15.1",
    "YCP": "14.9",
    "TRADE": "1381",
    "VALUE (mn)": "99.913",
    "VOLUME": "6653663"
  },
  {
    "#": "8",
    "DATE": "2026-07-13",
    "TRADING CODE": "NCCBANK",
    "LTP*": "15.6",
    "HIGH": "15.7",
    "LOW": "15.2",
    "OPENP*": "15.2",
    "CLOSEP*": "15.6",
    "YCP": "15.1",
    "TRADE": "1912",
    "VALUE (mn)": "117.694",
    "VOLUME": "7591449"
  },
  {
    "#": "7",
    "DATE": "2026-07-14",
    "TRADING CODE": "NCCBANK",
    "LTP*": "15.5",
    "HIGH": "15.8",
    "LOW": "15.4",
    "OPENP*": "15.6",
    "CLOSEP*": "15.5",
    "YCP": "15.6",
    "TRADE": "1472",
    "VALUE (mn)": "102.293",
    "VOLUME": "6568291"
  },
  {
    "#": "6",
    "DATE": "2026-07-15",
    "TRADING CODE": "NCCBANK",
    "LTP*": "15.6",
    "HIGH": "15.9",
    "LOW": "15.4",
    "OPENP*": "15.4",
    "CLOSEP*": "15.6",
    "YCP": "15.5",
    "TRADE": "1353",
    "VALUE (mn)": "91.974",
    "VOLUME": "5862084"
  },
  {
    "#": "5",
    "DATE": "2026-07-16",
    "TRADING CODE": "NCCBANK",
    "LTP*": "15.6",
    "HIGH": "15.8",
    "LOW": "15.5",
    "OPENP*": "15.6",
    "CLOSEP*": "15.6",
    "YCP": "15.6",
    "TRADE": "758",
    "VALUE (mn)": "43.77",
    "VOLUME": "2804361"
  },
  {
    "#": "4",
    "DATE": "2026-07-19",
    "TRADING CODE": "NCCBANK",
    "LTP*": "15.5",
    "HIGH": "15.6",
    "LOW": "15.4",
    "OPENP*": "15.6",
    "CLOSEP*": "15.5",
    "YCP": "15.6",
    "TRADE": "944",
    "VALUE (mn)": "54.983",
    "VOLUME": "3550816"
  },
  {
    "#": "3",
    "DATE": "2026-07-20",
    "TRADING CODE": "NCCBANK",
    "LTP*": "15.8",
    "HIGH": "15.9",
    "LOW": "15.5",
    "OPENP*": "15.5",
    "CLOSEP*": "15.8",
    "YCP": "15.5",
    "TRADE": "1389",
    "VALUE (mn)": "94.006",
    "VOLUME": "6004388"
  },
  {
    "#": "2",
    "DATE": "2026-07-21",
    "TRADING CODE": "NCCBANK",
    "LTP*": "16",
    "HIGH": "16.2",
    "LOW": "15.8",
    "OPENP*": "15.9",
    "CLOSEP*": "16",
    "YCP": "15.8",
    "TRADE": "1935",
    "VALUE (mn)": "178.34",
    "VOLUME": "11134694"
  },
  {
    "#": "1",
    "DATE": "2026-07-22",
    "TRADING CODE": "NCCBANK",
    "LTP*": "15.9",
    "HIGH": "16.2",
    "LOW": "15.8",
    "OPENP*": "16.1",
    "CLOSEP*": "15.9",
    "YCP": "16",
    "TRADE": "1314",
    "VALUE (mn)": "107.956",
    "VOLUME": "6747550"
  }
]