[
  {
    "#": "1",
    "TRADING CODE": "1JANATAMF",
    "LTP*": "3.4",
    "HIGH": "3.5",
    "LOW": "3.3",
    "CLOSEP*": "3.4",
    "YCP*": "3.4",
    "CHANGE": "0",
    "TRADE": "244",
    "VALUE (mn)": "9.256",
    "VOLUME": "2718802"
  },
  {
    "#": "2",
    "TRADING CODE": "1STPRIMFMF",
    "LTP*": "24.7",
    "HIGH": "25.3",
    "LOW": "24.4",
    "CLOSEP*": "24.7",
    "YCP*": "24.8",
    "CHANGE": "-0.1",
    "TRADE": "644",
    "VALUE (mn)": "19.398",
    "VOLUME": "781006"
  },
  {
    "#": "3",
    "TRADING CODE": "AAMRANET",
    "LTP*": "21.2",
    "HIGH": "21.6",
    "LOW": "21",
    "CLOSEP*": "21.2",
    "YCP*": "21.5",
    "CHANGE": "-0.3",
    "TRADE": "603",
    "VALUE (mn)": "11.006",
    "VOLUME": "518235"
  },
  {
    "#": "4",
    "TRADING CODE": "AAMRATECH",
    "LTP*": "17.5",
    "HIGH": "17.9",
    "LOW": "17.3",
    "CLOSEP*": "17.5",
    "YCP*": "17.8",
    "CHANGE": "-0.3",
    "TRADE": "263",
    "VALUE (mn)": "4.175",
    "VOLUME": "238093"
  },
  {
    "#": "5",
    "TRADING CODE": "ABB1STMF",
    "LTP*": "3.6",
    "HIGH": "3.7",
    "LOW": "3.5",
    "CLOSEP*": "3.6",
    "YCP*": "3.6",
    "CHANGE": "0",
    "TRADE": "346",
    "VALUE (mn)": "16.819",
    "VOLUME": "4660966"
  },
  {
    "#": "6",
    "TRADING CODE": "ABBANK",
    "LTP*": "5",
    "HIGH": "5",
    "LOW": "4.9",
    "CLOSEP*": "4.9",
    "YCP*": "4.9",
    "CHANGE": "0.1",
    "TRADE": "206",
    "VALUE (mn)": "4.36",
    "VOLUME": "877325"
  },
  {
    "#": "7",
    "TRADING CODE": "ACFL",
    "LTP*": "24.2",
    "HIGH": "24.4",
    "LOW": "24",
    "CLOSEP*": "24.2",
    "YCP*": "23.6",
    "CHANGE": "0.6",
    "TRADE": "204",
    "VALUE (mn)": "4.97",
    "VOLUME": "205719"
  },
  {
    "#": "8",
    "TRADING CODE": "ACI",
    "LTP*": "203.2",
    "HIGH": "204",
    "LOW": "201.1",
    "CLOSEP*": "203.2",
    "YCP*": "203.7",
    "CHANGE": "-0.5",
    "TRADE": "393",
    "VALUE (mn)": "11.778",
    "VOLUME": "57904"
  },
  {
    "#": "9",
    "TRADING CODE": "ACIFORMULA",
    "LTP*": "157.6",
    "HIGH": "158.1",
    "LOW": "153.2",
    "CLOSEP*": "157.6",
    "YCP*": "153.9",
    "CHANGE": "3.7",
    "TRADE": "760",
    "VALUE (mn)": "29.163",
    "VOLUME": "186855"
  },
  {
    "#": "10",
    "TRADING CODE": "ACMELAB",
    "LTP*": "86.8",
    "HIGH": "87.5",
    "LOW": "86",
    "CLOSEP*": "86.8",
    "YCP*": "86.9",
    "CHANGE": "-0.1",
    "TRADE": "1647",
    "VALUE (mn)": "113.636",
    "VOLUME": "1312285"
  },
  {
    "#": "11",
    "TRADING CODE": "ACMEPL",
    "LTP*": "23.3",
    "HIGH": "23.4",
    "LOW": "23",
    "CLOSEP*": "23.3",
    "YCP*": "22.9",
    "CHANGE": "0.4",
    "TRADE": "948",
    "VALUE (mn)": "30.478",
    "VOLUME": "1311088"
  },
  {
    "#": "12",
    "TRADING CODE": "ACTIVEFINE",
    "LTP*": "6.9",
    "HIGH": "7",
    "LOW": "6.9",
    "CLOSEP*": "6.9",
    "YCP*": "7",
    "CHANGE": "-0.1",
    "TRADE": "143",
    "VALUE (mn)": "2.663",
    "VOLUME": "384337"
  },
  {
    "#": "13",
    "TRADING CODE": "ADNTEL",
    "LTP*": "70.6",
    "HIGH": "71.8",
    "LOW": "70.3",
    "CLOSEP*": "70.6",
    "YCP*": "70.9",
    "CHANGE": "-0.3",
    "TRADE": "1196",
    "VALUE (mn)": "48.742",
    "VOLUME": "687376"
  },
  {
    "#": "14",
    "TRADING CODE": "ADVENT",
    "LTP*": "16",
    "HIGH": "16.2",
    "LOW": "16",
    "CLOSEP*": "16",
    "YCP*": "16.1",
    "CHANGE": "-0.1",
    "TRADE": "127",
    "VALUE (mn)": "3.257",
    "VOLUME": "202888"
  },
  {
    "#": "15",
    "TRADING CODE": "AFCAGRO",
    "LTP*": "7.3",
    "HIGH": "7.4",
    "LOW": "7.2",
    "CLOSEP*": "7.3",
    "YCP*": "7.2",
    "CHANGE": "0.1",
    "TRADE": "76",
    "VALUE (mn)": "0.544",
    "VOLUME": "74537"
  },
  {
    "#": "16",
    "TRADING CODE": "AFTABAUTO",
    "LTP*": "31.9",
    "HIGH": "32",
    "LOW": "31",
    "CLOSEP*": "31.9",
    "YCP*": "31.5",
    "CHANGE": "0.4",
    "TRADE": "645",
    "VALUE (mn)": "16.811",
    "VOLUME": "528057"
  },
  {
    "#": "17",
    "TRADING CODE": "AGNISYSL",
    "LTP*": "32.7",
    "HIGH": "33.5",
    "LOW": "31.8",
    "CLOSEP*": "32.7",
    "YCP*": "31.7",
    "CHANGE": "1",
    "TRADE": "2293",
    "VALUE (mn)": "155.789",
    "VOLUME": "4756464"
  },
  {
    "#": "18",
    "TRADING CODE": "AGRANINS",
    "LTP*": "31.9",
    "HIGH": "32.9",
    "LOW": "31.6",
    "CLOSEP*": "31.9",
    "YCP*": "32.6",
    "CHANGE": "-0.7",
    "TRADE": "1026",
    "VALUE (mn)": "36.449",
    "VOLUME": "1127479"
  },
  {
    "#": "19",
    "TRADING CODE": "AIBL1STIMF",
    "LTP*": "5.5",
    "HIGH": "5.7",
    "LOW": "5.3",
    "CLOSEP*": "5.5",
    "YCP*": "5.6",
    "CHANGE": "-0.1",
    "TRADE": "527",
    "VALUE (mn)": "23.515",
    "VOLUME": "4301099"
  },
  {
    "#": "20",
    "TRADING CODE": "AIL",
    "LTP*": "39.5",
    "HIGH": "40.5",
    "LOW": "39.2",
    "CLOSEP*": "39.3",
    "YCP*": "39.1",
    "CHANGE": "0.4",
    "TRADE": "750",
    "VALUE (mn)": "20.649",
    "VOLUME": "523053"
  },
  {
    "#": "21",
    "TRADING CODE": "AL-HAJTEX",
    "LTP*": "112.7",
    "HIGH": "113.9",
    "LOW": "106.8",
    "CLOSEP*": "112.7",
    "YCP*": "106.2",
    "CHANGE": "6.5",
    "TRADE": "3750",
    "VALUE (mn)": "118.659",
    "VOLUME": "1070763"
  },
  {
    "#": "22",
    "TRADING CODE": "ALARABANK",
    "LTP*": "16.1",
    "HIGH": "16.2",
    "LOW": "16",
    "CLOSEP*": "16",
    "YCP*": "16",
    "CHANGE": "0.1",
    "TRADE": "34",
    "VALUE (mn)": "0.161",
    "VOLUME": "10060"
  },
  {
    "#": "23",
    "TRADING CODE": "ALIF",
    "LTP*": "5.6",
    "HIGH": "5.7",
    "LOW": "5.5",
    "CLOSEP*": "5.6",
    "YCP*": "5.5",
    "CHANGE": "0.1",
    "TRADE": "192",
    "VALUE (mn)": "2.41",
    "VOLUME": "430877"
  },
  {
    "#": "24",
    "TRADING CODE": "ALLTEX",
    "LTP*": "18.1",
    "HIGH": "18.4",
    "LOW": "18",
    "CLOSEP*": "18.1",
    "YCP*": "18",
    "CHANGE": "0.1",
    "TRADE": "303",
    "VALUE (mn)": "6.208",
    "VOLUME": "342188"
  },
  {
    "#": "25",
    "TRADING CODE": "AMANFEED",
    "LTP*": "37.5",
    "HIGH": "37.5",
    "LOW": "34.3",
    "CLOSEP*": "37.5",
    "YCP*": "34.1",
    "CHANGE": "3.4",
    "TRADE": "1498",
    "VALUE (mn)": "140.478",
    "VOLUME": "3816650"
  },
  {
    "#": "26",
    "TRADING CODE": "AMBEEPHA",
    "LTP*": "771.6",
    "HIGH": "778",
    "LOW": "767.3",
    "CLOSEP*": "771.6",
    "YCP*": "768.7",
    "CHANGE": "2.9",
    "TRADE": "111",
    "VALUE (mn)": "1.302",
    "VOLUME": "1683"
  },
  {
    "#": "27",
    "TRADING CODE": "AMCL(PRAN)",
    "LTP*": "230.3",
    "HIGH": "230.3",
    "LOW": "227.7",
    "CLOSEP*": "229.4",
    "YCP*": "227.6",
    "CHANGE": "2.7",
    "TRADE": "160",
    "VALUE (mn)": "4.667",
    "VOLUME": "20354"
  },
  {
    "#": "28",
    "TRADING CODE": "ANLIMAYARN",
    "LTP*": "36.2",
    "HIGH": "36.7",
    "LOW": "35.4",
    "CLOSEP*": "36.2",
    "YCP*": "36.2",
    "CHANGE": "0",
    "TRADE": "106",
    "VALUE (mn)": "0.991",
    "VOLUME": "27364"
  },
  {
    "#": "29",
    "TRADING CODE": "ANWARGALV",
    "LTP*": "119.5",
    "HIGH": "122.4",
    "LOW": "118.8",
    "CLOSEP*": "119.5",
    "YCP*": "120.7",
    "CHANGE": "-1.2",
    "TRADE": "1998",
    "VALUE (mn)": "57.539",
    "VOLUME": "477067"
  },
  {
    "#": "30",
    "TRADING CODE": "AOL",
    "LTP*": "17.4",
    "HIGH": "17.6",
    "LOW": "17.3",
    "CLOSEP*": "17.4",
    "YCP*": "17.4",
    "CHANGE": "0",
    "TRADE": "307",
    "VALUE (mn)": "8.384",
    "VOLUME": "481635"
  },
  {
    "#": "31",
    "TRADING CODE": "APEXFOODS",
    "LTP*": "305.4",
    "HIGH": "312.9",
    "LOW": "303.9",
    "CLOSEP*": "305.4",
    "YCP*": "304.9",
    "CHANGE": "0.5",
    "TRADE": "1182",
    "VALUE (mn)": "26.904",
    "VOLUME": "87239"
  },
  {
    "#": "32",
    "TRADING CODE": "APEXFOOT",
    "LTP*": "221.4",
    "HIGH": "223.6",
    "LOW": "218.9",
    "CLOSEP*": "221.4",
    "YCP*": "219.4",
    "CHANGE": "2",
    "TRADE": "1867",
    "VALUE (mn)": "64.089",
    "VOLUME": "289717"
  },
  {
    "#": "33",
    "TRADING CODE": "APEXSPINN",
    "LTP*": "398",
    "HIGH": "412",
    "LOW": "395",
    "CLOSEP*": "398",
    "YCP*": "409.3",
    "CHANGE": "-11.3",
    "TRADE": "861",
    "VALUE (mn)": "66.646",
    "VOLUME": "164843"
  },
  {
    "#": "34",
    "TRADING CODE": "APEXTANRY",
    "LTP*": "113.8",
    "HIGH": "114.4",
    "LOW": "105",
    "CLOSEP*": "113.8",
    "YCP*": "104",
    "CHANGE": "9.8",
    "TRADE": "2300",
    "VALUE (mn)": "72.093",
    "VOLUME": "646846"
  },
  {
    "#": "35",
    "TRADING CODE": "APOLOISPAT",
    "LTP*": "3.1",
    "HIGH": "3.2",
    "LOW": "3",
    "CLOSEP*": "3.1",
    "YCP*": "3.1",
    "CHANGE": "0",
    "TRADE": "153",
    "VALUE (mn)": "1.771",
    "VOLUME": "585749"
  },
  {
    "#": "36",
    "TRADING CODE": "ARAMIT",
    "LTP*": "209.9",
    "HIGH": "219",
    "LOW": "208.1",
    "CLOSEP*": "209.9",
    "YCP*": "214.1",
    "CHANGE": "-4.2",
    "TRADE": "361",
    "VALUE (mn)": "6.875",
    "VOLUME": "32581"
  },
  {
    "#": "37",
    "TRADING CODE": "ARAMITCEM",
    "LTP*": "11.9",
    "HIGH": "12",
    "LOW": "11.6",
    "CLOSEP*": "11.9",
    "YCP*": "11.8",
    "CHANGE": "0.1",
    "TRADE": "103",
    "VALUE (mn)": "0.589",
    "VOLUME": "49872"
  },
  {
    "#": "38",
    "TRADING CODE": "ARGONDENIM",
    "LTP*": "21.8",
    "HIGH": "22.1",
    "LOW": "21.5",
    "CLOSEP*": "21.8",
    "YCP*": "21.4",
    "CHANGE": "0.4",
    "TRADE": "1218",
    "VALUE (mn)": "64.773",
    "VOLUME": "2971336"
  },
  {
    "#": "39",
    "TRADING CODE": "ASIAINS",
    "LTP*": "46",
    "HIGH": "47.6",
    "LOW": "45.6",
    "CLOSEP*": "46",
    "YCP*": "45.6",
    "CHANGE": "0.4",
    "TRADE": "1954",
    "VALUE (mn)": "90.315",
    "VOLUME": "1933222"
  },
  {
    "#": "40",
    "TRADING CODE": "ASIAPACINS",
    "LTP*": "48.5",
    "HIGH": "50.4",
    "LOW": "48.1",
    "CLOSEP*": "48.5",
    "YCP*": "49.5",
    "CHANGE": "-1",
    "TRADE": "778",
    "VALUE (mn)": "31.923",
    "VOLUME": "650379"
  },
  {
    "#": "41",
    "TRADING CODE": "ASIATICLAB",
    "LTP*": "142.8",
    "HIGH": "144.8",
    "LOW": "139",
    "CLOSEP*": "142.8",
    "YCP*": "142.2",
    "CHANGE": "0.6",
    "TRADE": "1560",
    "VALUE (mn)": "271.186",
    "VOLUME": "1900944"
  },
  {
    "#": "42",
    "TRADING CODE": "ATLASBANG",
    "LTP*": "98.1",
    "HIGH": "102",
    "LOW": "96.4",
    "CLOSEP*": "98.1",
    "YCP*": "98.3",
    "CHANGE": "-0.2",
    "TRADE": "407",
    "VALUE (mn)": "6.612",
    "VOLUME": "66192"
  },
  {
    "#": "43",
    "TRADING CODE": "AZIZPIPES",
    "LTP*": "78.5",
    "HIGH": "80.6",
    "LOW": "74.8",
    "CLOSEP*": "78.5",
    "YCP*": "75.8",
    "CHANGE": "2.7",
    "TRADE": "291",
    "VALUE (mn)": "5.195",
    "VOLUME": "67497"
  },
  {
    "#": "44",
    "TRADING CODE": "BANGAS",
    "LTP*": "143.4",
    "HIGH": "146.9",
    "LOW": "142.7",
    "CLOSEP*": "143.4",
    "YCP*": "142.7",
    "CHANGE": "0.7",
    "TRADE": "1547",
    "VALUE (mn)": "40.808",
    "VOLUME": "282785"
  },
  {
    "#": "45",
    "TRADING CODE": "BANKASIA",
    "LTP*": "18.7",
    "HIGH": "18.7",
    "LOW": "18.3",
    "CLOSEP*": "18.7",
    "YCP*": "18.4",
    "CHANGE": "0.3",
    "TRADE": "243",
    "VALUE (mn)": "10.844",
    "VOLUME": "584547"
  },
  {
    "#": "46",
    "TRADING CODE": "BARKAPOWER",
    "LTP*": "8.2",
    "HIGH": "8.3",
    "LOW": "8.1",
    "CLOSEP*": "8.2",
    "YCP*": "8.2",
    "CHANGE": "0",
    "TRADE": "128",
    "VALUE (mn)": "2.009",
    "VOLUME": "246163"
  },
  {
    "#": "47",
    "TRADING CODE": "BATASHOE",
    "LTP*": "875.5",
    "HIGH": "881.9",
    "LOW": "875",
    "CLOSEP*": "879.1",
    "YCP*": "877.6",
    "CHANGE": "-2.1",
    "TRADE": "19",
    "VALUE (mn)": "0.254",
    "VOLUME": "289"
  },
  {
    "#": "48",
    "TRADING CODE": "BATBC",
    "LTP*": "224.8",
    "HIGH": "226.5",
    "LOW": "224",
    "CLOSEP*": "224.8",
    "YCP*": "224",
    "CHANGE": "0.8",
    "TRADE": "2334",
    "VALUE (mn)": "63.544",
    "VOLUME": "282028"
  },
  {
    "#": "49",
    "TRADING CODE": "BAYLEASING",
    "LTP*": "4.5",
    "HIGH": "4.6",
    "LOW": "4.4",
    "CLOSEP*": "4.5",
    "YCP*": "4.5",
    "CHANGE": "0",
    "TRADE": "237",
    "VALUE (mn)": "3.212",
    "VOLUME": "723773"
  },
  {
    "#": "50",
    "TRADING CODE": "BBS",
    "LTP*": "15.5",
    "HIGH": "15.7",
    "LOW": "15.4",
    "CLOSEP*": "15.5",
    "YCP*": "15.4",
    "CHANGE": "0.1",
    "TRADE": "770",
    "VALUE (mn)": "21.671",
    "VOLUME": "1393461"
  },
  {
    "#": "51",
    "TRADING CODE": "BBSCABLES",
    "LTP*": "23.3",
    "HIGH": "23.5",
    "LOW": "23.1",
    "CLOSEP*": "23.3",
    "YCP*": "23.2",
    "CHANGE": "0.1",
    "TRADE": "897",
    "VALUE (mn)": "45.654",
    "VOLUME": "1957156"
  },
  {
    "#": "52",
    "TRADING CODE": "BDAUTOCA",
    "LTP*": "219.6",
    "HIGH": "223.8",
    "LOW": "211.8",
    "CLOSEP*": "219.6",
    "YCP*": "210.8",
    "CHANGE": "8.8",
    "TRADE": "2624",
    "VALUE (mn)": "71.429",
    "VOLUME": "324757"
  },
  {
    "#": "53",
    "TRADING CODE": "BDCOM",
    "LTP*": "34",
    "HIGH": "34.6",
    "LOW": "33.8",
    "CLOSEP*": "34",
    "YCP*": "33.9",
    "CHANGE": "0.1",
    "TRADE": "1558",
    "VALUE (mn)": "70.802",
    "VOLUME": "2073513"
  },
  {
    "#": "54",
    "TRADING CODE": "BDFINANCE",
    "LTP*": "12.8",
    "HIGH": "13",
    "LOW": "12.7",
    "CLOSEP*": "12.8",
    "YCP*": "12.8",
    "CHANGE": "0",
    "TRADE": "138",
    "VALUE (mn)": "2.044",
    "VOLUME": "159584"
  },
  {
    "#": "55",
    "TRADING CODE": "BDLAMPS",
    "LTP*": "190.6",
    "HIGH": "193.9",
    "LOW": "185.9",
    "CLOSEP*": "190.6",
    "YCP*": "185.4",
    "CHANGE": "5.2",
    "TRADE": "1065",
    "VALUE (mn)": "37.221",
    "VOLUME": "195727"
  },
  {
    "#": "56",
    "TRADING CODE": "BDSERVICE",
    "LTP*": "0",
    "HIGH": "0",
    "LOW": "0",
    "CLOSEP*": "5.2",
    "YCP*": "5.2",
    "CHANGE": "--",
    "TRADE": "0",
    "VALUE (mn)": "0",
    "VOLUME": "0"
  },
  {
    "#": "57",
    "TRADING CODE": "BDTHAI",
    "LTP*": "19.6",
    "HIGH": "20.6",
    "LOW": "19.5",
    "CLOSEP*": "19.6",
    "YCP*": "20.2",
    "CHANGE": "-0.6",
    "TRADE": "2730",
    "VALUE (mn)": "85.603",
    "VOLUME": "4303407"
  },
  {
    "#": "58",
    "TRADING CODE": "BDTHAIFOOD",
    "LTP*": "24.1",
    "HIGH": "24.7",
    "LOW": "24",
    "CLOSEP*": "24.1",
    "YCP*": "24.3",
    "CHANGE": "-0.2",
    "TRADE": "1501",
    "VALUE (mn)": "50.692",
    "VOLUME": "2082806"
  },
  {
    "#": "59",
    "TRADING CODE": "BDWELDING",
    "LTP*": "14",
    "HIGH": "14.4",
    "LOW": "13.9",
    "CLOSEP*": "14",
    "YCP*": "13.9",
    "CHANGE": "0.1",
    "TRADE": "279",
    "VALUE (mn)": "2.935",
    "VOLUME": "208385"
  },
  {
    "#": "60",
    "TRADING CODE": "BEACHHATCH",
    "LTP*": "35.7",
    "HIGH": "36.8",
    "LOW": "34.4",
    "CLOSEP*": "35.7",
    "YCP*": "34.2",
    "CHANGE": "1.5",
    "TRADE": "1749",
    "VALUE (mn)": "44.66",
    "VOLUME": "1234990"
  },
  {
    "#": "61",
    "TRADING CODE": "BEACONPHAR",
    "LTP*": "114.8",
    "HIGH": "115.7",
    "LOW": "114.5",
    "CLOSEP*": "114.8",
    "YCP*": "114.5",
    "CHANGE": "0.3",
    "TRADE": "1341",
    "VALUE (mn)": "64.815",
    "VOLUME": "563891"
  },
  {
    "#": "62",
    "TRADING CODE": "BENGALWTL",
    "LTP*": "25.6",
    "HIGH": "25.8",
    "LOW": "24.9",
    "CLOSEP*": "25.6",
    "YCP*": "24.8",
    "CHANGE": "0.8",
    "TRADE": "574",
    "VALUE (mn)": "21.803",
    "VOLUME": "857338"
  },
  {
    "#": "63",
    "TRADING CODE": "BERGERPBL",
    "LTP*": "1408.2",
    "HIGH": "1410.2",
    "LOW": "1402",
    "CLOSEP*": "1408.2",
    "YCP*": "1400",
    "CHANGE": "8.2",
    "TRADE": "229",
    "VALUE (mn)": "4.455",
    "VOLUME": "3165"
  },
  {
    "#": "64",
    "TRADING CODE": "BESTHLDNG",
    "LTP*": "16",
    "HIGH": "16.2",
    "LOW": "15.9",
    "CLOSEP*": "16",
    "YCP*": "16",
    "CHANGE": "0",
    "TRADE": "467",
    "VALUE (mn)": "9.072",
    "VOLUME": "567193"
  },
  {
    "#": "65",
    "TRADING CODE": "BEXIMCO",
    "LTP*": "26.4",
    "HIGH": "27.5",
    "LOW": "26.2",
    "CLOSEP*": "26.4",
    "YCP*": "27.1",
    "CHANGE": "-0.7",
    "TRADE": "7753",
    "VALUE (mn)": "175.156",
    "VOLUME": "6558173"
  },
  {
    "#": "66",
    "TRADING CODE": "BGIC",
    "LTP*": "44.3",
    "HIGH": "45.9",
    "LOW": "43.9",
    "CLOSEP*": "44.3",
    "YCP*": "45",
    "CHANGE": "-0.7",
    "TRADE": "502",
    "VALUE (mn)": "13.374",
    "VOLUME": "298559"
  },
  {
    "#": "67",
    "TRADING CODE": "BIFC",
    "LTP*": "4.3",
    "HIGH": "4.5",
    "LOW": "4.3",
    "CLOSEP*": "4.4",
    "YCP*": "4.3",
    "CHANGE": "0",
    "TRADE": "29",
    "VALUE (mn)": "0.141",
    "VOLUME": "32036"
  },
  {
    "#": "68",
    "TRADING CODE": "BNICL",
    "LTP*": "114",
    "HIGH": "117.2",
    "LOW": "112.8",
    "CLOSEP*": "113.4",
    "YCP*": "114.6",
    "CHANGE": "-0.6",
    "TRADE": "842",
    "VALUE (mn)": "21.898",
    "VOLUME": "192859"
  },
  {
    "#": "69",
    "TRADING CODE": "BPML",
    "LTP*": "28.5",
    "HIGH": "28.9",
    "LOW": "28.5",
    "CLOSEP*": "28.6",
    "YCP*": "28.4",
    "CHANGE": "0.1",
    "TRADE": "177",
    "VALUE (mn)": "2.369",
    "VOLUME": "82679"
  },
  {
    "#": "70",
    "TRADING CODE": "BPPL",
    "LTP*": "20.9",
    "HIGH": "21.3",
    "LOW": "20.8",
    "CLOSEP*": "20.9",
    "YCP*": "20.8",
    "CHANGE": "0.1",
    "TRADE": "1071",
    "VALUE (mn)": "46.74",
    "VOLUME": "2229098"
  },
  {
    "#": "71",
    "TRADING CODE": "BRACBANK",
    "LTP*": "64.8",
    "HIGH": "64.9",
    "LOW": "63.5",
    "CLOSEP*": "64.8",
    "YCP*": "63.7",
    "CHANGE": "1.1",
    "TRADE": "3169",
    "VALUE (mn)": "281.088",
    "VOLUME": "4372740"
  },
  {
    "#": "72",
    "TRADING CODE": "BSC",
    "LTP*": "127.8",
    "HIGH": "129",
    "LOW": "123",
    "CLOSEP*": "127.8",
    "YCP*": "123.6",
    "CHANGE": "4.2",
    "TRADE": "6071",
    "VALUE (mn)": "492.564",
    "VOLUME": "3882122"
  },
  {
    "#": "73",
    "TRADING CODE": "BSCPLC",
    "LTP*": "163.1",
    "HIGH": "164.5",
    "LOW": "162.4",
    "CLOSEP*": "163.1",
    "YCP*": "162.8",
    "CHANGE": "0.3",
    "TRADE": "1060",
    "VALUE (mn)": "45.987",
    "VOLUME": "281402"
  },
  {
    "#": "74",
    "TRADING CODE": "BSRMLTD",
    "LTP*": "107.7",
    "HIGH": "109.4",
    "LOW": "105.7",
    "CLOSEP*": "107.7",
    "YCP*": "106.9",
    "CHANGE": "0.8",
    "TRADE": "2140",
    "VALUE (mn)": "137.575",
    "VOLUME": "1275642"
  },
  {
    "#": "75",
    "TRADING CODE": "BSRMSTEEL",
    "LTP*": "98.5",
    "HIGH": "99",
    "LOW": "92.5",
    "CLOSEP*": "98.5",
    "YCP*": "93.5",
    "CHANGE": "5",
    "TRADE": "2852",
    "VALUE (mn)": "268.23",
    "VOLUME": "2787935"
  },
  {
    "#": "76",
    "TRADING CODE": "BXPHARMA",
    "LTP*": "155.4",
    "HIGH": "156.4",
    "LOW": "153.6",
    "CLOSEP*": "155.4",
    "YCP*": "153.2",
    "CHANGE": "2.2",
    "TRADE": "1795",
    "VALUE (mn)": "191.65",
    "VOLUME": "1234420"
  },
  {
    "#": "77",
    "TRADING CODE": "CAPITECGBF",
    "LTP*": "8.2",
    "HIGH": "8.3",
    "LOW": "8.1",
    "CLOSEP*": "8.2",
    "YCP*": "8.2",
    "CHANGE": "0",
    "TRADE": "444",
    "VALUE (mn)": "20.324",
    "VOLUME": "2476827"
  },
  {
    "#": "78",
    "TRADING CODE": "CAPMBDBLMF",
    "LTP*": "10.2",
    "HIGH": "10.4",
    "LOW": "10",
    "CLOSEP*": "10.1",
    "YCP*": "10.3",
    "CHANGE": "-0.1",
    "TRADE": "493",
    "VALUE (mn)": "20.841",
    "VOLUME": "2046309"
  },
  {
    "#": "79",
    "TRADING CODE": "CAPMIBBLMF",
    "LTP*": "15.2",
    "HIGH": "15.6",
    "LOW": "14.9",
    "CLOSEP*": "15.2",
    "YCP*": "15.5",
    "CHANGE": "-0.3",
    "TRADE": "476",
    "VALUE (mn)": "17.733",
    "VOLUME": "1165300"
  },
  {
    "#": "80",
    "TRADING CODE": "CENTRALINS",
    "LTP*": "45.3",
    "HIGH": "46.9",
    "LOW": "44.8",
    "CLOSEP*": "45.3",
    "YCP*": "45.7",
    "CHANGE": "-0.4",
    "TRADE": "1161",
    "VALUE (mn)": "40.42",
    "VOLUME": "878067"
  },
  {
    "#": "81",
    "TRADING CODE": "CENTRALPHL",
    "LTP*": "10.7",
    "HIGH": "11",
    "LOW": "10.6",
    "CLOSEP*": "10.7",
    "YCP*": "10.8",
    "CHANGE": "-0.1",
    "TRADE": "376",
    "VALUE (mn)": "9.226",
    "VOLUME": "859561"
  },
  {
    "#": "82",
    "TRADING CODE": "CITYBANK",
    "LTP*": "31.4",
    "HIGH": "31.5",
    "LOW": "30.8",
    "CLOSEP*": "31.4",
    "YCP*": "31.1",
    "CHANGE": "0.3",
    "TRADE": "1709",
    "VALUE (mn)": "198.005",
    "VOLUME": "6329624"
  },
  {
    "#": "83",
    "TRADING CODE": "CITYGENINS",
    "LTP*": "107.2",
    "HIGH": "107.5",
    "LOW": "107",
    "CLOSEP*": "107.2",
    "YCP*": "107.1",
    "CHANGE": "0.1",
    "TRADE": "257",
    "VALUE (mn)": "15.778",
    "VOLUME": "147249"
  },
  {
    "#": "84",
    "TRADING CODE": "CLICL",
    "LTP*": "56.3",
    "HIGH": "61.8",
    "LOW": "56.1",
    "CLOSEP*": "56.3",
    "YCP*": "56.2",
    "CHANGE": "0.1",
    "TRADE": "1037",
    "VALUE (mn)": "29.267",
    "VOLUME": "518453"
  },
  {
    "#": "85",
    "TRADING CODE": "CNATEX",
    "LTP*": "3.1",
    "HIGH": "3.1",
    "LOW": "3",
    "CLOSEP*": "3.1",
    "YCP*": "3",
    "CHANGE": "0.1",
    "TRADE": "159",
    "VALUE (mn)": "1.673",
    "VOLUME": "555323"
  },
  {
    "#": "86",
    "TRADING CODE": "CONFIDCEM",
    "LTP*": "72.3",
    "HIGH": "72.7",
    "LOW": "70.7",
    "CLOSEP*": "72.1",
    "YCP*": "71.6",
    "CHANGE": "0.7",
    "TRADE": "1326",
    "VALUE (mn)": "58.623",
    "VOLUME": "813460"
  },
  {
    "#": "87",
    "TRADING CODE": "CONTININS",
    "LTP*": "36.9",
    "HIGH": "38.8",
    "LOW": "36.2",
    "CLOSEP*": "36.9",
    "YCP*": "38.1",
    "CHANGE": "-1.2",
    "TRADE": "1591",
    "VALUE (mn)": "55.293",
    "VOLUME": "1472540"
  },
  {
    "#": "88",
    "TRADING CODE": "COPPERTECH",
    "LTP*": "27.5",
    "HIGH": "27.7",
    "LOW": "27.2",
    "CLOSEP*": "27.5",
    "YCP*": "27.2",
    "CHANGE": "0.3",
    "TRADE": "429",
    "VALUE (mn)": "21.36",
    "VOLUME": "777038"
  },
  {
    "#": "89",
    "TRADING CODE": "CROWNCEMNT",
    "LTP*": "68",
    "HIGH": "68",
    "LOW": "67",
    "CLOSEP*": "67.2",
    "YCP*": "67.3",
    "CHANGE": "0.7",
    "TRADE": "211",
    "VALUE (mn)": "3.182",
    "VOLUME": "47388"
  },
  {
    "#": "90",
    "TRADING CODE": "CRYSTALINS",
    "LTP*": "71.4",
    "HIGH": "72.9",
    "LOW": "71.3",
    "CLOSEP*": "71.4",
    "YCP*": "71.9",
    "CHANGE": "-0.5",
    "TRADE": "1122",
    "VALUE (mn)": "29.161",
    "VOLUME": "406261"
  },
  {
    "#": "91",
    "TRADING CODE": "CVOPRL",
    "LTP*": "180.8",
    "HIGH": "181.9",
    "LOW": "176.2",
    "CLOSEP*": "180.8",
    "YCP*": "175.6",
    "CHANGE": "5.2",
    "TRADE": "2714",
    "VALUE (mn)": "110.724",
    "VOLUME": "618512"
  },
  {
    "#": "92",
    "TRADING CODE": "DACCADYE",
    "LTP*": "16.8",
    "HIGH": "17.1",
    "LOW": "16.6",
    "CLOSEP*": "16.8",
    "YCP*": "16.9",
    "CHANGE": "-0.1",
    "TRADE": "252",
    "VALUE (mn)": "4.458",
    "VOLUME": "265388"
  },
  {
    "#": "93",
    "TRADING CODE": "DAFODILCOM",
    "LTP*": "162.2",
    "HIGH": "163",
    "LOW": "157",
    "CLOSEP*": "162.2",
    "YCP*": "163.8",
    "CHANGE": "-1.6",
    "TRADE": "908",
    "VALUE (mn)": "31.363",
    "VOLUME": "194948"
  },
  {
    "#": "94",
    "TRADING CODE": "DBH",
    "LTP*": "42.2",
    "HIGH": "42.5",
    "LOW": "41.7",
    "CLOSEP*": "42.2",
    "YCP*": "42.4",
    "CHANGE": "-0.2",
    "TRADE": "421",
    "VALUE (mn)": "16.372",
    "VOLUME": "389765"
  },
  {
    "#": "95",
    "TRADING CODE": "DBH1STMF",
    "LTP*": "5.1",
    "HIGH": "5.3",
    "LOW": "5",
    "CLOSEP*": "5",
    "YCP*": "5.2",
    "CHANGE": "-0.1",
    "TRADE": "225",
    "VALUE (mn)": "5.975",
    "VOLUME": "1174094"
  },
  {
    "#": "96",
    "TRADING CODE": "DELTALIFE",
    "LTP*": "86.4",
    "HIGH": "87.5",
    "LOW": "86",
    "CLOSEP*": "86.4",
    "YCP*": "87",
    "CHANGE": "-0.6",
    "TRADE": "731",
    "VALUE (mn)": "23.824",
    "VOLUME": "275277"
  },
  {
    "#": "97",
    "TRADING CODE": "DELTASPINN",
    "LTP*": "7.2",
    "HIGH": "7.4",
    "LOW": "7.1",
    "CLOSEP*": "7.2",
    "YCP*": "7.1",
    "CHANGE": "0.1",
    "TRADE": "295",
    "VALUE (mn)": "7.694",
    "VOLUME": "1054913"
  },
  {
    "#": "98",
    "TRADING CODE": "DESCO",
    "LTP*": "26.9",
    "HIGH": "27.4",
    "LOW": "26.6",
    "CLOSEP*": "26.9",
    "YCP*": "27",
    "CHANGE": "-0.1",
    "TRADE": "126",
    "VALUE (mn)": "2.017",
    "VOLUME": "75116"
  },
  {
    "#": "99",
    "TRADING CODE": "DESHBANDHU",
    "LTP*": "22.1",
    "HIGH": "22.4",
    "LOW": "21.3",
    "CLOSEP*": "22.1",
    "YCP*": "21.1",
    "CHANGE": "1",
    "TRADE": "1515",
    "VALUE (mn)": "54.49",
    "VOLUME": "2474074"
  },
  {
    "#": "100",
    "TRADING CODE": "DGIC",
    "LTP*": "36.8",
    "HIGH": "37.3",
    "LOW": "34.7",
    "CLOSEP*": "36.8",
    "YCP*": "35.1",
    "CHANGE": "1.7",
    "TRADE": "1228",
    "VALUE (mn)": "55.155",
    "VOLUME": "1518422"
  },
  {
    "#": "101",
    "TRADING CODE": "DHAKABANK",
    "LTP*": "12.4",
    "HIGH": "12.5",
    "LOW": "12.3",
    "CLOSEP*": "12.4",
    "YCP*": "12.3",
    "CHANGE": "0.1",
    "TRADE": "523",
    "VALUE (mn)": "19.887",
    "VOLUME": "1603498"
  },
  {
    "#": "102",
    "TRADING CODE": "DHAKAINS",
    "LTP*": "46.9",
    "HIGH": "48.5",
    "LOW": "46.6",
    "CLOSEP*": "46.9",
    "YCP*": "45.9",
    "CHANGE": "1",
    "TRADE": "844",
    "VALUE (mn)": "25.921",
    "VOLUME": "546066"
  },
  {
    "#": "103",
    "TRADING CODE": "DOMINAGE",
    "LTP*": "77.6",
    "HIGH": "78.4",
    "LOW": "76.5",
    "CLOSEP*": "77.6",
    "YCP*": "77",
    "CHANGE": "0.6",
    "TRADE": "1295",
    "VALUE (mn)": "75.918",
    "VOLUME": "982156"
  },
  {
    "#": "104",
    "TRADING CODE": "DOREENPWR",
    "LTP*": "32.4",
    "HIGH": "32.6",
    "LOW": "31.6",
    "CLOSEP*": "32.4",
    "YCP*": "32",
    "CHANGE": "0.4",
    "TRADE": "904",
    "VALUE (mn)": "32.885",
    "VOLUME": "1023171"
  },
  {
    "#": "105",
    "TRADING CODE": "DSHGARME",
    "LTP*": "169.3",
    "HIGH": "180.5",
    "LOW": "165.4",
    "CLOSEP*": "169.3",
    "YCP*": "164.1",
    "CHANGE": "5.2",
    "TRADE": "2071",
    "VALUE (mn)": "87.761",
    "VOLUME": "496809"
  },
  {
    "#": "106",
    "TRADING CODE": "DSSL",
    "LTP*": "13.3",
    "HIGH": "13.7",
    "LOW": "13.1",
    "CLOSEP*": "13.3",
    "YCP*": "13.2",
    "CHANGE": "0.1",
    "TRADE": "2240",
    "VALUE (mn)": "105.028",
    "VOLUME": "7847103"
  },
  {
    "#": "107",
    "TRADING CODE": "DULAMIACOT",
    "LTP*": "187.3",
    "HIGH": "195",
    "LOW": "185",
    "CLOSEP*": "187.3",
    "YCP*": "188",
    "CHANGE": "-0.7",
    "TRADE": "294",
    "VALUE (mn)": "7.629",
    "VOLUME": "40634"
  },
  {
    "#": "108",
    "TRADING CODE": "DUTCHBANGL",
    "LTP*": "48.3",
    "HIGH": "48.9",
    "LOW": "46.7",
    "CLOSEP*": "48.3",
    "YCP*": "46.9",
    "CHANGE": "1.4",
    "TRADE": "966",
    "VALUE (mn)": "73.928",
    "VOLUME": "1548164"
  },
  {
    "#": "109",
    "TRADING CODE": "EASTERNINS",
    "LTP*": "62.4",
    "HIGH": "63.7",
    "LOW": "61.9",
    "CLOSEP*": "62.4",
    "YCP*": "61.7",
    "CHANGE": "0.7",
    "TRADE": "804",
    "VALUE (mn)": "27.076",
    "VOLUME": "431117"
  },
  {
    "#": "110",
    "TRADING CODE": "EASTLAND",
    "LTP*": "30.8",
    "HIGH": "31.8",
    "LOW": "30.7",
    "CLOSEP*": "30.8",
    "YCP*": "31.5",
    "CHANGE": "-0.7",
    "TRADE": "1118",
    "VALUE (mn)": "36.632",
    "VOLUME": "1179837"
  },
  {
    "#": "111",
    "TRADING CODE": "EASTRNLUB",
    "LTP*": "1977.4",
    "HIGH": "2005",
    "LOW": "1972",
    "CLOSEP*": "1977.4",
    "YCP*": "1981.2",
    "CHANGE": "-3.8",
    "TRADE": "1510",
    "VALUE (mn)": "46.446",
    "VOLUME": "23364"
  },
  {
    "#": "112",
    "TRADING CODE": "EBL",
    "LTP*": "24.5",
    "HIGH": "24.6",
    "LOW": "24.4",
    "CLOSEP*": "24.5",
    "YCP*": "24.5",
    "CHANGE": "0",
    "TRADE": "1458",
    "VALUE (mn)": "80.679",
    "VOLUME": "3297223"
  },
  {
    "#": "113",
    "TRADING CODE": "EBL1STMF",
    "LTP*": "4.5",
    "HIGH": "4.6",
    "LOW": "4.4",
    "CLOSEP*": "4.5",
    "YCP*": "4.5",
    "CHANGE": "0",
    "TRADE": "74",
    "VALUE (mn)": "1.423",
    "VOLUME": "316686"
  },
  {
    "#": "114",
    "TRADING CODE": "EBLNRBMF",
    "LTP*": "3.3",
    "HIGH": "3.4",
    "LOW": "3.3",
    "CLOSEP*": "3.3",
    "YCP*": "3.4",
    "CHANGE": "-0.1",
    "TRADE": "70",
    "VALUE (mn)": "2.152",
    "VOLUME": "643173"
  },
  {
    "#": "115",
    "TRADING CODE": "ECABLES",
    "LTP*": "151.6",
    "HIGH": "157",
    "LOW": "150.2",
    "CLOSEP*": "151.6",
    "YCP*": "153.3",
    "CHANGE": "-1.7",
    "TRADE": "545",
    "VALUE (mn)": "9.957",
    "VOLUME": "64468"
  },
  {
    "#": "116",
    "TRADING CODE": "EGEN",
    "LTP*": "27.5",
    "HIGH": "28",
    "LOW": "27.4",
    "CLOSEP*": "27.5",
    "YCP*": "27.4",
    "CHANGE": "0.1",
    "TRADE": "1004",
    "VALUE (mn)": "39.35",
    "VOLUME": "1420758"
  },
  {
    "#": "117",
    "TRADING CODE": "EHL",
    "LTP*": "100.1",
    "HIGH": "102.8",
    "LOW": "98.4",
    "CLOSEP*": "100.1",
    "YCP*": "99.3",
    "CHANGE": "0.8",
    "TRADE": "3524",
    "VALUE (mn)": "212.135",
    "VOLUME": "2099986"
  },
  {
    "#": "118",
    "TRADING CODE": "EIL",
    "LTP*": "34.1",
    "HIGH": "35.5",
    "LOW": "33.8",
    "CLOSEP*": "34.1",
    "YCP*": "34.4",
    "CHANGE": "-0.3",
    "TRADE": "1626",
    "VALUE (mn)": "79.104",
    "VOLUME": "2285610"
  },
  {
    "#": "119",
    "TRADING CODE": "EMERALDOIL",
    "LTP*": "29.1",
    "HIGH": "31.7",
    "LOW": "28.9",
    "CLOSEP*": "29.1",
    "YCP*": "28.9",
    "CHANGE": "0.2",
    "TRADE": "1607",
    "VALUE (mn)": "64.047",
    "VOLUME": "2136455"
  },
  {
    "#": "120",
    "TRADING CODE": "ENVOYTEX",
    "LTP*": "59",
    "HIGH": "59.8",
    "LOW": "58.5",
    "CLOSEP*": "59",
    "YCP*": "59",
    "CHANGE": "0",
    "TRADE": "840",
    "VALUE (mn)": "35.488",
    "VOLUME": "601462"
  },
  {
    "#": "121",
    "TRADING CODE": "EPGL",
    "LTP*": "20.5",
    "HIGH": "20.8",
    "LOW": "20.3",
    "CLOSEP*": "20.5",
    "YCP*": "20.7",
    "CHANGE": "-0.2",
    "TRADE": "636",
    "VALUE (mn)": "13.42",
    "VOLUME": "653344"
  },
  {
    "#": "122",
    "TRADING CODE": "ESQUIRENIT",
    "LTP*": "26.7",
    "HIGH": "27.4",
    "LOW": "26.6",
    "CLOSEP*": "26.7",
    "YCP*": "26.6",
    "CHANGE": "0.1",
    "TRADE": "341",
    "VALUE (mn)": "8.476",
    "VOLUME": "314013"
  },
  {
    "#": "123",
    "TRADING CODE": "ETL",
    "LTP*": "14.4",
    "HIGH": "14.7",
    "LOW": "13.9",
    "CLOSEP*": "14.4",
    "YCP*": "13.9",
    "CHANGE": "0.5",
    "TRADE": "2849",
    "VALUE (mn)": "127.723",
    "VOLUME": "8877648"
  },
  {
    "#": "124",
    "TRADING CODE": "EXIM1STMF",
    "LTP*": "4.1",
    "HIGH": "4.1",
    "LOW": "3.9",
    "CLOSEP*": "4.1",
    "YCP*": "4",
    "CHANGE": "0.1",
    "TRADE": "362",
    "VALUE (mn)": "11.75",
    "VOLUME": "2924148"
  },
  {
    "#": "125",
    "TRADING CODE": "EXIMBANK",
    "LTP*": "0",
    "HIGH": "0",
    "LOW": "0",
    "CLOSEP*": "3",
    "YCP*": "3",
    "CHANGE": "--",
    "TRADE": "0",
    "VALUE (mn)": "0",
    "VOLUME": "0"
  },
  {
    "#": "126",
    "TRADING CODE": "FAMILYTEX",
    "LTP*": "2.4",
    "HIGH": "2.4",
    "LOW": "2.2",
    "CLOSEP*": "2.4",
    "YCP*": "2.2",
    "CHANGE": "0.2",
    "TRADE": "276",
    "VALUE (mn)": "2.039",
    "VOLUME": "881095"
  },
  {
    "#": "127",
    "TRADING CODE": "FARCHEM",
    "LTP*": "21.7",
    "HIGH": "21.8",
    "LOW": "19.7",
    "CLOSEP*": "21.7",
    "YCP*": "19.9",
    "CHANGE": "1.8",
    "TRADE": "1262",
    "VALUE (mn)": "44.136",
    "VOLUME": "2062072"
  },
  {
    "#": "128",
    "TRADING CODE": "FAREASTFIN",
    "LTP*": "1.2",
    "HIGH": "1.2",
    "LOW": "1.2",
    "CLOSEP*": "1.2",
    "YCP*": "1.1",
    "CHANGE": "0.1",
    "TRADE": "90",
    "VALUE (mn)": "1.038",
    "VOLUME": "864761"
  },
  {
    "#": "129",
    "TRADING CODE": "FAREASTLIF",
    "LTP*": "23.1",
    "HIGH": "23.9",
    "LOW": "22.6",
    "CLOSEP*": "23.1",
    "YCP*": "23.5",
    "CHANGE": "-0.4",
    "TRADE": "110",
    "VALUE (mn)": "1.992",
    "VOLUME": "85687"
  },
  {
    "#": "130",
    "TRADING CODE": "FASFIN",
    "LTP*": "1.3",
    "HIGH": "1.4",
    "LOW": "1.2",
    "CLOSEP*": "1.3",
    "YCP*": "1.3",
    "CHANGE": "0",
    "TRADE": "83",
    "VALUE (mn)": "0.706",
    "VOLUME": "533154"
  },
  {
    "#": "131",
    "TRADING CODE": "FBFIF",
    "LTP*": "3.4",
    "HIGH": "3.5",
    "LOW": "3.3",
    "CLOSEP*": "3.4",
    "YCP*": "3.4",
    "CHANGE": "0",
    "TRADE": "120",
    "VALUE (mn)": "3.277",
    "VOLUME": "963854"
  },
  {
    "#": "132",
    "TRADING CODE": "FEDERALINS",
    "LTP*": "30.1",
    "HIGH": "30.9",
    "LOW": "29.8",
    "CLOSEP*": "30.1",
    "YCP*": "29.8",
    "CHANGE": "0.3",
    "TRADE": "2156",
    "VALUE (mn)": "106.939",
    "VOLUME": "3514558"
  },
  {
    "#": "133",
    "TRADING CODE": "FEKDIL",
    "LTP*": "24.7",
    "HIGH": "25.3",
    "LOW": "24.3",
    "CLOSEP*": "24.7",
    "YCP*": "24.2",
    "CHANGE": "0.5",
    "TRADE": "2525",
    "VALUE (mn)": "171.857",
    "VOLUME": "6920904"
  },
  {
    "#": "134",
    "TRADING CODE": "FINEFOODS",
    "LTP*": "504",
    "HIGH": "507.8",
    "LOW": "499.7",
    "CLOSEP*": "504",
    "YCP*": "497.3",
    "CHANGE": "6.7",
    "TRADE": "717",
    "VALUE (mn)": "102.687",
    "VOLUME": "203811"
  },
  {
    "#": "135",
    "TRADING CODE": "FIRSTFIN",
    "LTP*": "4",
    "HIGH": "4.1",
    "LOW": "3.9",
    "CLOSEP*": "4",
    "YCP*": "4.1",
    "CHANGE": "-0.1",
    "TRADE": "36",
    "VALUE (mn)": "0.466",
    "VOLUME": "117358"
  },
  {
    "#": "136",
    "TRADING CODE": "FIRSTSBANK",
    "LTP*": "0",
    "HIGH": "0",
    "LOW": "0",
    "CLOSEP*": "1.9",
    "YCP*": "1.9",
    "CHANGE": "--",
    "TRADE": "0",
    "VALUE (mn)": "0",
    "VOLUME": "0"
  },
  {
    "#": "137",
    "TRADING CODE": "FORTUNE",
    "LTP*": "20.7",
    "HIGH": "21",
    "LOW": "18.9",
    "CLOSEP*": "20.7",
    "YCP*": "19.5",
    "CHANGE": "1.2",
    "TRADE": "1739",
    "VALUE (mn)": "46.845",
    "VOLUME": "2354734"
  },
  {
    "#": "138",
    "TRADING CODE": "FUWANGCER",
    "LTP*": "16.2",
    "HIGH": "16.4",
    "LOW": "15.4",
    "CLOSEP*": "16.2",
    "YCP*": "15.4",
    "CHANGE": "0.8",
    "TRADE": "2234",
    "VALUE (mn)": "99.604",
    "VOLUME": "6203686"
  },
  {
    "#": "139",
    "TRADING CODE": "FUWANGFOOD",
    "LTP*": "12.5",
    "HIGH": "12.7",
    "LOW": "12.1",
    "CLOSEP*": "12.5",
    "YCP*": "12.1",
    "CHANGE": "0.4",
    "TRADE": "454",
    "VALUE (mn)": "12.613",
    "VOLUME": "1016948"
  },
  {
    "#": "140",
    "TRADING CODE": "GBBPOWER",
    "LTP*": "8.2",
    "HIGH": "8.4",
    "LOW": "8.2",
    "CLOSEP*": "8.2",
    "YCP*": "8.3",
    "CHANGE": "-0.1",
    "TRADE": "112",
    "VALUE (mn)": "1.272",
    "VOLUME": "153643"
  },
  {
    "#": "141",
    "TRADING CODE": "GEMINISEA",
    "LTP*": "132.7",
    "HIGH": "134.1",
    "LOW": "129.7",
    "CLOSEP*": "132.7",
    "YCP*": "127.9",
    "CHANGE": "4.8",
    "TRADE": "1099",
    "VALUE (mn)": "18.714",
    "VOLUME": "140891"
  },
  {
    "#": "142",
    "TRADING CODE": "GENEXIL",
    "LTP*": "41.1",
    "HIGH": "42.1",
    "LOW": "40.5",
    "CLOSEP*": "41.1",
    "YCP*": "40.8",
    "CHANGE": "0.3",
    "TRADE": "2568",
    "VALUE (mn)": "135.577",
    "VOLUME": "3275261"
  },
  {
    "#": "143",
    "TRADING CODE": "GENNEXT",
    "LTP*": "2.9",
    "HIGH": "3",
    "LOW": "2.8",
    "CLOSEP*": "2.9",
    "YCP*": "2.8",
    "CHANGE": "0.1",
    "TRADE": "215",
    "VALUE (mn)": "3.706",
    "VOLUME": "1289117"
  },
  {
    "#": "144",
    "TRADING CODE": "GHAIL",
    "LTP*": "15.7",
    "HIGH": "15.9",
    "LOW": "15.5",
    "CLOSEP*": "15.7",
    "YCP*": "15.5",
    "CHANGE": "0.2",
    "TRADE": "959",
    "VALUE (mn)": "40.128",
    "VOLUME": "2548226"
  },
  {
    "#": "145",
    "TRADING CODE": "GHCL",
    "LTP*": "20.5",
    "HIGH": "20.8",
    "LOW": "20.5",
    "CLOSEP*": "20.6",
    "YCP*": "20.5",
    "CHANGE": "0",
    "TRADE": "135",
    "VALUE (mn)": "2.423",
    "VOLUME": "117817"
  },
  {
    "#": "146",
    "TRADING CODE": "GIB",
    "LTP*": "0",
    "HIGH": "0",
    "LOW": "0",
    "CLOSEP*": "1.7",
    "YCP*": "1.7",
    "CHANGE": "--",
    "TRADE": "0",
    "VALUE (mn)": "0",
    "VOLUME": "0"
  },
  {
    "#": "147",
    "TRADING CODE": "GLDNJMF",
    "LTP*": "7.7",
    "HIGH": "7.9",
    "LOW": "7.5",
    "CLOSEP*": "7.7",
    "YCP*": "7.7",
    "CHANGE": "0",
    "TRADE": "360",
    "VALUE (mn)": "9.721",
    "VOLUME": "1267136"
  },
  {
    "#": "148",
    "TRADING CODE": "GLOBALINS",
    "LTP*": "46.3",
    "HIGH": "48",
    "LOW": "46",
    "CLOSEP*": "46.3",
    "YCP*": "47.5",
    "CHANGE": "-1.2",
    "TRADE": "1605",
    "VALUE (mn)": "65.872",
    "VOLUME": "1406038"
  },
  {
    "#": "149",
    "TRADING CODE": "GOLDENSON",
    "LTP*": "16.8",
    "HIGH": "17",
    "LOW": "16.7",
    "CLOSEP*": "16.8",
    "YCP*": "16.8",
    "CHANGE": "0",
    "TRADE": "1071",
    "VALUE (mn)": "48.328",
    "VOLUME": "2871510"
  },
  {
    "#": "150",
    "TRADING CODE": "GP",
    "LTP*": "258.6",
    "HIGH": "259.8",
    "LOW": "258",
    "CLOSEP*": "258.6",
    "YCP*": "258.2",
    "CHANGE": "0.4",
    "TRADE": "1356",
    "VALUE (mn)": "39.305",
    "VOLUME": "151914"
  },
  {
    "#": "151",
    "TRADING CODE": "GPHISPAT",
    "LTP*": "20.3",
    "HIGH": "20.4",
    "LOW": "19.4",
    "CLOSEP*": "20.3",
    "YCP*": "19.5",
    "CHANGE": "0.8",
    "TRADE": "1643",
    "VALUE (mn)": "83.073",
    "VOLUME": "4161999"
  },
  {
    "#": "152",
    "TRADING CODE": "GQBALLPEN",
    "LTP*": "634.8",
    "HIGH": "634.8",
    "LOW": "585",
    "CLOSEP*": "634.8",
    "YCP*": "590.6",
    "CHANGE": "44.2",
    "TRADE": "1787",
    "VALUE (mn)": "101.081",
    "VOLUME": "163043"
  },
  {
    "#": "153",
    "TRADING CODE": "GRAMEENS2",
    "LTP*": "12.8",
    "HIGH": "13.2",
    "LOW": "12.8",
    "CLOSEP*": "12.8",
    "YCP*": "13",
    "CHANGE": "-0.2",
    "TRADE": "483",
    "VALUE (mn)": "17.775",
    "VOLUME": "1380533"
  },
  {
    "#": "154",
    "TRADING CODE": "GREENDELMF",
    "LTP*": "4",
    "HIGH": "4.2",
    "LOW": "4",
    "CLOSEP*": "4",
    "YCP*": "4.1",
    "CHANGE": "-0.1",
    "TRADE": "149",
    "VALUE (mn)": "3.456",
    "VOLUME": "853531"
  },
  {
    "#": "155",
    "TRADING CODE": "GREENDELT",
    "LTP*": "70.6",
    "HIGH": "71.9",
    "LOW": "69.9",
    "CLOSEP*": "70.6",
    "YCP*": "70.2",
    "CHANGE": "0.4",
    "TRADE": "954",
    "VALUE (mn)": "40.536",
    "VOLUME": "572344"
  },
  {
    "#": "156",
    "TRADING CODE": "GSPFINANCE",
    "LTP*": "3.5",
    "HIGH": "3.7",
    "LOW": "3.5",
    "CLOSEP*": "3.5",
    "YCP*": "3.6",
    "CHANGE": "-0.1",
    "TRADE": "95",
    "VALUE (mn)": "0.773",
    "VOLUME": "219126"
  },
  {
    "#": "157",
    "TRADING CODE": "HAKKANIPUL",
    "LTP*": "85.4",
    "HIGH": "87.5",
    "LOW": "85.2",
    "CLOSEP*": "85.4",
    "YCP*": "86.6",
    "CHANGE": "-1.2",
    "TRADE": "1866",
    "VALUE (mn)": "66.599",
    "VOLUME": "775411"
  },
  {
    "#": "158",
    "TRADING CODE": "HAMI",
    "LTP*": "150.5",
    "HIGH": "151",
    "LOW": "147.1",
    "CLOSEP*": "150.5",
    "YCP*": "147.6",
    "CHANGE": "2.9",
    "TRADE": "339",
    "VALUE (mn)": "4.011",
    "VOLUME": "26687"
  },
  {
    "#": "159",
    "TRADING CODE": "HEIDELBCEM",
    "LTP*": "240.4",
    "HIGH": "245",
    "LOW": "231",
    "CLOSEP*": "240.4",
    "YCP*": "232.9",
    "CHANGE": "7.5",
    "TRADE": "775",
    "VALUE (mn)": "20.871",
    "VOLUME": "87231"
  },
  {
    "#": "160",
    "TRADING CODE": "HFL",
    "LTP*": "14.6",
    "HIGH": "14.6",
    "LOW": "13.9",
    "CLOSEP*": "14.4",
    "YCP*": "14.2",
    "CHANGE": "0.4",
    "TRADE": "198",
    "VALUE (mn)": "1.196",
    "VOLUME": "83020"
  },
  {
    "#": "161",
    "TRADING CODE": "HRTEX",
    "LTP*": "21.8",
    "HIGH": "21.8",
    "LOW": "21.5",
    "CLOSEP*": "21.8",
    "YCP*": "21.7",
    "CHANGE": "0.1",
    "TRADE": "149",
    "VALUE (mn)": "2.468",
    "VOLUME": "113619"
  },
  {
    "#": "162",
    "TRADING CODE": "HWAWELLTEX",
    "LTP*": "48.5",
    "HIGH": "48.9",
    "LOW": "47.8",
    "CLOSEP*": "48.5",
    "YCP*": "47.8",
    "CHANGE": "0.7",
    "TRADE": "539",
    "VALUE (mn)": "21.694",
    "VOLUME": "448025"
  },
  {
    "#": "163",
    "TRADING CODE": "IBNSINA",
    "LTP*": "328.3",
    "HIGH": "329.2",
    "LOW": "324.3",
    "CLOSEP*": "328.3",
    "YCP*": "326.5",
    "CHANGE": "1.8",
    "TRADE": "409",
    "VALUE (mn)": "14.667",
    "VOLUME": "44885"
  },
  {
    "#": "164",
    "TRADING CODE": "IBP",
    "LTP*": "18.5",
    "HIGH": "18.8",
    "LOW": "18",
    "CLOSEP*": "18.5",
    "YCP*": "18",
    "CHANGE": "0.5",
    "TRADE": "1636",
    "VALUE (mn)": "93.799",
    "VOLUME": "5077648"
  },
  {
    "#": "165",
    "TRADING CODE": "ICB",
    "LTP*": "47.8",
    "HIGH": "48.6",
    "LOW": "47.3",
    "CLOSEP*": "47.8",
    "YCP*": "47.2",
    "CHANGE": "0.6",
    "TRADE": "674",
    "VALUE (mn)": "21.257",
    "VOLUME": "444661"
  },
  {
    "#": "166",
    "TRADING CODE": "ICB3RDNRB",
    "LTP*": "5.5",
    "HIGH": "5.7",
    "LOW": "5.5",
    "CLOSEP*": "5.5",
    "YCP*": "5.6",
    "CHANGE": "-0.1",
    "TRADE": "129",
    "VALUE (mn)": "2.451",
    "VOLUME": "442130"
  },
  {
    "#": "167",
    "TRADING CODE": "ICBAGRANI1",
    "LTP*": "8.9",
    "HIGH": "9.2",
    "LOW": "8.6",
    "CLOSEP*": "8.9",
    "YCP*": "8.9",
    "CHANGE": "0",
    "TRADE": "346",
    "VALUE (mn)": "15.138",
    "VOLUME": "1679357"
  },
  {
    "#": "168",
    "TRADING CODE": "ICBAMCL2ND",
    "LTP*": "7.4",
    "HIGH": "7.5",
    "LOW": "7.2",
    "CLOSEP*": "7.4",
    "YCP*": "7.3",
    "CHANGE": "0.1",
    "TRADE": "89",
    "VALUE (mn)": "1.578",
    "VOLUME": "214004"
  },
  {
    "#": "169",
    "TRADING CODE": "ICBEPMF1S1",
    "LTP*": "6.3",
    "HIGH": "6.6",
    "LOW": "6.3",
    "CLOSEP*": "6.3",
    "YCP*": "6.5",
    "CHANGE": "-0.2",
    "TRADE": "169",
    "VALUE (mn)": "3.965",
    "VOLUME": "622850"
  },
  {
    "#": "170",
    "TRADING CODE": "ICBIBANK",
    "LTP*": "2.8",
    "HIGH": "2.8",
    "LOW": "2.7",
    "CLOSEP*": "2.8",
    "YCP*": "2.7",
    "CHANGE": "0.1",
    "TRADE": "44",
    "VALUE (mn)": "0.923",
    "VOLUME": "339747"
  },
  {
    "#": "171",
    "TRADING CODE": "ICBSONALI1",
    "LTP*": "6.3",
    "HIGH": "6.5",
    "LOW": "6.2",
    "CLOSEP*": "6.3",
    "YCP*": "6.4",
    "CHANGE": "-0.1",
    "TRADE": "626",
    "VALUE (mn)": "22.16",
    "VOLUME": "3492898"
  },
  {
    "#": "172",
    "TRADING CODE": "ICICL",
    "LTP*": "32.3",
    "HIGH": "33.6",
    "LOW": "32.2",
    "CLOSEP*": "32.3",
    "YCP*": "32.7",
    "CHANGE": "-0.4",
    "TRADE": "1186",
    "VALUE (mn)": "44.157",
    "VOLUME": "1342412"
  },
  {
    "#": "173",
    "TRADING CODE": "IDLC",
    "LTP*": "44.1",
    "HIGH": "44.7",
    "LOW": "43.5",
    "CLOSEP*": "44.1",
    "YCP*": "44.3",
    "CHANGE": "-0.2",
    "TRADE": "739",
    "VALUE (mn)": "29.047",
    "VOLUME": "661473"
  },
  {
    "#": "174",
    "TRADING CODE": "IFADAUTOS",
    "LTP*": "26.7",
    "HIGH": "27.1",
    "LOW": "26.6",
    "CLOSEP*": "26.7",
    "YCP*": "26.9",
    "CHANGE": "-0.2",
    "TRADE": "756",
    "VALUE (mn)": "24.467",
    "VOLUME": "913589"
  },
  {
    "#": "175",
    "TRADING CODE": "IFIC",
    "LTP*": "5",
    "HIGH": "5.1",
    "LOW": "4.9",
    "CLOSEP*": "5",
    "YCP*": "4.9",
    "CHANGE": "0.1",
    "TRADE": "421",
    "VALUE (mn)": "13.688",
    "VOLUME": "2736101"
  },
  {
    "#": "176",
    "TRADING CODE": "IFIC1STMF",
    "LTP*": "3.8",
    "HIGH": "4",
    "LOW": "3.8",
    "CLOSEP*": "3.8",
    "YCP*": "3.9",
    "CHANGE": "-0.1",
    "TRADE": "223",
    "VALUE (mn)": "8.892",
    "VOLUME": "2298829"
  },
  {
    "#": "177",
    "TRADING CODE": "IFILISLMF1",
    "LTP*": "5",
    "HIGH": "5.1",
    "LOW": "4.9",
    "CLOSEP*": "5",
    "YCP*": "4.9",
    "CHANGE": "0.1",
    "TRADE": "111",
    "VALUE (mn)": "3.812",
    "VOLUME": "762886"
  },
  {
    "#": "178",
    "TRADING CODE": "ILFSL",
    "LTP*": "1.1",
    "HIGH": "1.2",
    "LOW": "1.1",
    "CLOSEP*": "1.1",
    "YCP*": "1.2",
    "CHANGE": "-0.1",
    "TRADE": "63",
    "VALUE (mn)": "0.58",
    "VOLUME": "509434"
  },
  {
    "#": "179",
    "TRADING CODE": "INDEXAGRO",
    "LTP*": "77.9",
    "HIGH": "79.1",
    "LOW": "77.1",
    "CLOSEP*": "77.9",
    "YCP*": "77.2",
    "CHANGE": "0.7",
    "TRADE": "914",
    "VALUE (mn)": "39.321",
    "VOLUME": "502267"
  },
  {
    "#": "180",
    "TRADING CODE": "INTECH",
    "LTP*": "27.7",
    "HIGH": "28.2",
    "LOW": "27.2",
    "CLOSEP*": "27.7",
    "YCP*": "28.2",
    "CHANGE": "-0.5",
    "TRADE": "626",
    "VALUE (mn)": "11.199",
    "VOLUME": "404610"
  },
  {
    "#": "181",
    "TRADING CODE": "INTRACO",
    "LTP*": "21.8",
    "HIGH": "22.3",
    "LOW": "21.6",
    "CLOSEP*": "21.8",
    "YCP*": "22",
    "CHANGE": "-0.2",
    "TRADE": "381",
    "VALUE (mn)": "8.484",
    "VOLUME": "387798"
  },
  {
    "#": "182",
    "TRADING CODE": "IPDC",
    "LTP*": "33.3",
    "HIGH": "33.9",
    "LOW": "32",
    "CLOSEP*": "33.3",
    "YCP*": "32.6",
    "CHANGE": "0.7",
    "TRADE": "3687",
    "VALUE (mn)": "296.217",
    "VOLUME": "8866053"
  },
  {
    "#": "183",
    "TRADING CODE": "ISLAMIBANK",
    "LTP*": "32.5",
    "HIGH": "32.8",
    "LOW": "32.3",
    "CLOSEP*": "32.5",
    "YCP*": "32.2",
    "CHANGE": "0.3",
    "TRADE": "393",
    "VALUE (mn)": "5.662",
    "VOLUME": "174402"
  },
  {
    "#": "184",
    "TRADING CODE": "ISLAMICFIN",
    "LTP*": "11.1",
    "HIGH": "11.2",
    "LOW": "11",
    "CLOSEP*": "11.1",
    "YCP*": "11.2",
    "CHANGE": "-0.1",
    "TRADE": "148",
    "VALUE (mn)": "2.45",
    "VOLUME": "220652"
  },
  {
    "#": "185",
    "TRADING CODE": "ISLAMIINS",
    "LTP*": "65.4",
    "HIGH": "66",
    "LOW": "63.7",
    "CLOSEP*": "65.4",
    "YCP*": "64.1",
    "CHANGE": "1.3",
    "TRADE": "531",
    "VALUE (mn)": "32.271",
    "VOLUME": "494560"
  },
  {
    "#": "186",
    "TRADING CODE": "ISNLTD",
    "LTP*": "62.4",
    "HIGH": "63.4",
    "LOW": "61",
    "CLOSEP*": "62.4",
    "YCP*": "60.9",
    "CHANGE": "1.5",
    "TRADE": "1100",
    "VALUE (mn)": "22.888",
    "VOLUME": "366414"
  },
  {
    "#": "187",
    "TRADING CODE": "ITC",
    "LTP*": "50.4",
    "HIGH": "51.8",
    "LOW": "50",
    "CLOSEP*": "50.4",
    "YCP*": "51.2",
    "CHANGE": "-0.8",
    "TRADE": "2673",
    "VALUE (mn)": "177.632",
    "VOLUME": "3483455"
  },
  {
    "#": "188",
    "TRADING CODE": "JAMUNABANK",
    "LTP*": "23.8",
    "HIGH": "23.9",
    "LOW": "23.5",
    "CLOSEP*": "23.8",
    "YCP*": "23.5",
    "CHANGE": "0.3",
    "TRADE": "442",
    "VALUE (mn)": "39.911",
    "VOLUME": "1682020"
  },
  {
    "#": "189",
    "TRADING CODE": "JAMUNAOIL",
    "LTP*": "184.7",
    "HIGH": "185.1",
    "LOW": "182.8",
    "CLOSEP*": "184.7",
    "YCP*": "184.4",
    "CHANGE": "0.3",
    "TRADE": "294",
    "VALUE (mn)": "7.159",
    "VOLUME": "38807"
  },
  {
    "#": "190",
    "TRADING CODE": "JANATAINS",
    "LTP*": "36.6",
    "HIGH": "37.9",
    "LOW": "36.6",
    "CLOSEP*": "36.6",
    "YCP*": "37.4",
    "CHANGE": "-0.8",
    "TRADE": "1256",
    "VALUE (mn)": "41.449",
    "VOLUME": "1118592"
  },
  {
    "#": "191",
    "TRADING CODE": "JHRML",
    "LTP*": "53",
    "HIGH": "53.4",
    "LOW": "52.6",
    "CLOSEP*": "53",
    "YCP*": "53",
    "CHANGE": "0",
    "TRADE": "581",
    "VALUE (mn)": "16.009",
    "VOLUME": "301979"
  },
  {
    "#": "192",
    "TRADING CODE": "JMISMDL",
    "LTP*": "153.1",
    "HIGH": "156.8",
    "LOW": "150",
    "CLOSEP*": "153.1",
    "YCP*": "156.7",
    "CHANGE": "-3.6",
    "TRADE": "631",
    "VALUE (mn)": "12.476",
    "VOLUME": "80891"
  },
  {
    "#": "193",
    "TRADING CODE": "JUTESPINN",
    "LTP*": "239",
    "HIGH": "246.9",
    "LOW": "239",
    "CLOSEP*": "246.4",
    "YCP*": "227.1",
    "CHANGE": "11.9",
    "TRADE": "231",
    "VALUE (mn)": "5.423",
    "VOLUME": "22009"
  },
  {
    "#": "194",
    "TRADING CODE": "KARNAPHULI",
    "LTP*": "46.8",
    "HIGH": "49.7",
    "LOW": "46.3",
    "CLOSEP*": "46.8",
    "YCP*": "47.8",
    "CHANGE": "-1",
    "TRADE": "2141",
    "VALUE (mn)": "146.264",
    "VOLUME": "3043604"
  },
  {
    "#": "195",
    "TRADING CODE": "KAY&QUE",
    "LTP*": "434.1",
    "HIGH": "443.3",
    "LOW": "432.1",
    "CLOSEP*": "434.1",
    "YCP*": "437.2",
    "CHANGE": "-3.1",
    "TRADE": "1261",
    "VALUE (mn)": "31.055",
    "VOLUME": "71171"
  },
  {
    "#": "196",
    "TRADING CODE": "KBPPWBIL",
    "LTP*": "41.6",
    "HIGH": "41.8",
    "LOW": "39.2",
    "CLOSEP*": "41.6",
    "YCP*": "39.2",
    "CHANGE": "2.4",
    "TRADE": "4213",
    "VALUE (mn)": "101.402",
    "VOLUME": "2476179"
  },
  {
    "#": "197",
    "TRADING CODE": "KDSALTD",
    "LTP*": "53.5",
    "HIGH": "54",
    "LOW": "53.2",
    "CLOSEP*": "53.5",
    "YCP*": "53.2",
    "CHANGE": "0.3",
    "TRADE": "760",
    "VALUE (mn)": "37.826",
    "VOLUME": "705186"
  },
  {
    "#": "198",
    "TRADING CODE": "KEYACOSMET",
    "LTP*": "5.1",
    "HIGH": "5.2",
    "LOW": "5.1",
    "CLOSEP*": "5.1",
    "YCP*": "5.1",
    "CHANGE": "0",
    "TRADE": "240",
    "VALUE (mn)": "4.374",
    "VOLUME": "851600"
  },
  {
    "#": "199",
    "TRADING CODE": "KOHINOOR",
    "LTP*": "512.8",
    "HIGH": "513.1",
    "LOW": "509.5",
    "CLOSEP*": "512.8",
    "YCP*": "509.7",
    "CHANGE": "3.1",
    "TRADE": "277",
    "VALUE (mn)": "5.89",
    "VOLUME": "11500"
  },
  {
    "#": "200",
    "TRADING CODE": "KPCL",
    "LTP*": "10.4",
    "HIGH": "10.5",
    "LOW": "10.3",
    "CLOSEP*": "10.4",
    "YCP*": "10.4",
    "CHANGE": "0",
    "TRADE": "141",
    "VALUE (mn)": "1.325",
    "VOLUME": "127366"
  },
  {
    "#": "201",
    "TRADING CODE": "KPPL",
    "LTP*": "14.9",
    "HIGH": "15.2",
    "LOW": "14.8",
    "CLOSEP*": "14.9",
    "YCP*": "14.9",
    "CHANGE": "0",
    "TRADE": "239",
    "VALUE (mn)": "2.962",
    "VOLUME": "198399"
  },
  {
    "#": "202",
    "TRADING CODE": "KTL",
    "LTP*": "10.7",
    "HIGH": "10.8",
    "LOW": "10.6",
    "CLOSEP*": "10.7",
    "YCP*": "10.6",
    "CHANGE": "0.1",
    "TRADE": "186",
    "VALUE (mn)": "3.116",
    "VOLUME": "291497"
  },
  {
    "#": "203",
    "TRADING CODE": "LANKABAFIN",
    "LTP*": "16.7",
    "HIGH": "16.9",
    "LOW": "16.6",
    "CLOSEP*": "16.7",
    "YCP*": "16.7",
    "CHANGE": "0",
    "TRADE": "899",
    "VALUE (mn)": "44.8",
    "VOLUME": "2680133"
  },
  {
    "#": "204",
    "TRADING CODE": "LEGACYFOOT",
    "LTP*": "72.3",
    "HIGH": "74.2",
    "LOW": "71.9",
    "CLOSEP*": "72.3",
    "YCP*": "72.3",
    "CHANGE": "0",
    "TRADE": "1503",
    "VALUE (mn)": "41.76",
    "VOLUME": "572340"
  },
  {
    "#": "205",
    "TRADING CODE": "LHB",
    "LTP*": "60.1",
    "HIGH": "61.2",
    "LOW": "57.2",
    "CLOSEP*": "60.1",
    "YCP*": "57.4",
    "CHANGE": "2.7",
    "TRADE": "4346",
    "VALUE (mn)": "311.572",
    "VOLUME": "5271673"
  },
  {
    "#": "206",
    "TRADING CODE": "LIBRAINFU",
    "LTP*": "640.7",
    "HIGH": "644.9",
    "LOW": "638.3",
    "CLOSEP*": "640.2",
    "YCP*": "638.1",
    "CHANGE": "2.6",
    "TRADE": "313",
    "VALUE (mn)": "4.936",
    "VOLUME": "7709"
  },
  {
    "#": "207",
    "TRADING CODE": "LINDEBD",
    "LTP*": "750",
    "HIGH": "755",
    "LOW": "737",
    "CLOSEP*": "750",
    "YCP*": "748.3",
    "CHANGE": "1.7",
    "TRADE": "658",
    "VALUE (mn)": "9.962",
    "VOLUME": "13324"
  },
  {
    "#": "208",
    "TRADING CODE": "LOVELLO",
    "LTP*": "76.7",
    "HIGH": "79.8",
    "LOW": "75.5",
    "CLOSEP*": "76.7",
    "YCP*": "75.7",
    "CHANGE": "1",
    "TRADE": "9907",
    "VALUE (mn)": "749.678",
    "VOLUME": "9662043"
  },
  {
    "#": "209",
    "TRADING CODE": "LRBDL",
    "LTP*": "15.2",
    "HIGH": "15.6",
    "LOW": "15",
    "CLOSEP*": "15.2",
    "YCP*": "15.5",
    "CHANGE": "-0.3",
    "TRADE": "616",
    "VALUE (mn)": "13.772",
    "VOLUME": "896222"
  },
  {
    "#": "210",
    "TRADING CODE": "LRGLOBMF1",
    "LTP*": "3.8",
    "HIGH": "3.9",
    "LOW": "3.8",
    "CLOSEP*": "3.8",
    "YCP*": "3.8",
    "CHANGE": "0",
    "TRADE": "116",
    "VALUE (mn)": "3.047",
    "VOLUME": "795247"
  },
  {
    "#": "211",
    "TRADING CODE": "MAGURAPLEX",
    "LTP*": "96.4",
    "HIGH": "98.6",
    "LOW": "96.1",
    "CLOSEP*": "96.4",
    "YCP*": "97.6",
    "CHANGE": "-1.2",
    "TRADE": "1229",
    "VALUE (mn)": "32.448",
    "VOLUME": "334166"
  },
  {
    "#": "212",
    "TRADING CODE": "MAKSONSPIN",
    "LTP*": "5.8",
    "HIGH": "6",
    "LOW": "5.7",
    "CLOSEP*": "5.8",
    "YCP*": "5.8",
    "CHANGE": "0",
    "TRADE": "136",
    "VALUE (mn)": "2.932",
    "VOLUME": "502737"
  },
  {
    "#": "213",
    "TRADING CODE": "MALEKSPIN",
    "LTP*": "45.5",
    "HIGH": "46.8",
    "LOW": "43.7",
    "CLOSEP*": "45.5",
    "YCP*": "45.5",
    "CHANGE": "0",
    "TRADE": "3441",
    "VALUE (mn)": "365.515",
    "VOLUME": "7913340"
  },
  {
    "#": "214",
    "TRADING CODE": "MARICO",
    "LTP*": "2740.1",
    "HIGH": "2745",
    "LOW": "2732.5",
    "CLOSEP*": "2740.1",
    "YCP*": "2732.4",
    "CHANGE": "7.7",
    "TRADE": "348",
    "VALUE (mn)": "23.788",
    "VOLUME": "8688"
  },
  {
    "#": "215",
    "TRADING CODE": "MATINSPINN",
    "LTP*": "59",
    "HIGH": "60",
    "LOW": "58.9",
    "CLOSEP*": "59",
    "YCP*": "59",
    "CHANGE": "0",
    "TRADE": "289",
    "VALUE (mn)": "8.252",
    "VOLUME": "139349"
  },
  {
    "#": "216",
    "TRADING CODE": "MBL1STMF",
    "LTP*": "4.5",
    "HIGH": "4.6",
    "LOW": "4.4",
    "CLOSEP*": "4.5",
    "YCP*": "4.5",
    "CHANGE": "0",
    "TRADE": "125",
    "VALUE (mn)": "3.485",
    "VOLUME": "774332"
  },
  {
    "#": "217",
    "TRADING CODE": "MEGCONMILK",
    "LTP*": "36.8",
    "HIGH": "39",
    "LOW": "35.9",
    "CLOSEP*": "36.8",
    "YCP*": "37.9",
    "CHANGE": "-1.1",
    "TRADE": "617",
    "VALUE (mn)": "10.366",
    "VOLUME": "279530"
  },
  {
    "#": "218",
    "TRADING CODE": "MEGHNACEM",
    "LTP*": "33.6",
    "HIGH": "33.7",
    "LOW": "32",
    "CLOSEP*": "33.2",
    "YCP*": "32",
    "CHANGE": "1.6",
    "TRADE": "186",
    "VALUE (mn)": "1.972",
    "VOLUME": "60165"
  },
  {
    "#": "219",
    "TRADING CODE": "MEGHNAINS",
    "LTP*": "42.6",
    "HIGH": "45.1",
    "LOW": "41.9",
    "CLOSEP*": "42.6",
    "YCP*": "44.8",
    "CHANGE": "-2.2",
    "TRADE": "3042",
    "VALUE (mn)": "150.761",
    "VOLUME": "3459728"
  },
  {
    "#": "220",
    "TRADING CODE": "MEGHNALIFE",
    "LTP*": "66.8",
    "HIGH": "67.5",
    "LOW": "65.6",
    "CLOSEP*": "66.8",
    "YCP*": "67",
    "CHANGE": "-0.2",
    "TRADE": "1084",
    "VALUE (mn)": "47.837",
    "VOLUME": "716835"
  },
  {
    "#": "221",
    "TRADING CODE": "MEGHNAPET",
    "LTP*": "83.8",
    "HIGH": "87.8",
    "LOW": "82.4",
    "CLOSEP*": "83.8",
    "YCP*": "84.3",
    "CHANGE": "-0.5",
    "TRADE": "426",
    "VALUE (mn)": "15.925",
    "VOLUME": "187022"
  },
  {
    "#": "222",
    "TRADING CODE": "MERCANBANK",
    "LTP*": "7.6",
    "HIGH": "7.7",
    "LOW": "7.5",
    "CLOSEP*": "7.6",
    "YCP*": "7.6",
    "CHANGE": "0",
    "TRADE": "149",
    "VALUE (mn)": "2.076",
    "VOLUME": "272892"
  },
  {
    "#": "223",
    "TRADING CODE": "MERCINS",
    "LTP*": "46",
    "HIGH": "46.3",
    "LOW": "44.9",
    "CLOSEP*": "46",
    "YCP*": "45.4",
    "CHANGE": "0.6",
    "TRADE": "973",
    "VALUE (mn)": "50.452",
    "VOLUME": "1101378"
  },
  {
    "#": "224",
    "TRADING CODE": "METROSPIN",
    "LTP*": "9.3",
    "HIGH": "9.6",
    "LOW": "9.3",
    "CLOSEP*": "9.3",
    "YCP*": "9.3",
    "CHANGE": "0",
    "TRADE": "63",
    "VALUE (mn)": "0.405",
    "VOLUME": "43337"
  },
  {
    "#": "225",
    "TRADING CODE": "MHSML",
    "LTP*": "23.5",
    "HIGH": "23.8",
    "LOW": "23.1",
    "CLOSEP*": "23.5",
    "YCP*": "23.1",
    "CHANGE": "0.4",
    "TRADE": "1407",
    "VALUE (mn)": "58.148",
    "VOLUME": "2472211"
  },
  {
    "#": "226",
    "TRADING CODE": "MIDASFIN",
    "LTP*": "5.9",
    "HIGH": "6",
    "LOW": "5.7",
    "CLOSEP*": "5.9",
    "YCP*": "5.9",
    "CHANGE": "0",
    "TRADE": "80",
    "VALUE (mn)": "1.163",
    "VOLUME": "199660"
  },
  {
    "#": "227",
    "TRADING CODE": "MIDLANDBNK",
    "LTP*": "17.9",
    "HIGH": "18.1",
    "LOW": "17.3",
    "CLOSEP*": "17.9",
    "YCP*": "17.6",
    "CHANGE": "0.3",
    "TRADE": "1762",
    "VALUE (mn)": "88.944",
    "VOLUME": "4967336"
  },
  {
    "#": "228",
    "TRADING CODE": "MIRACLEIND",
    "LTP*": "28.5",
    "HIGH": "28.8",
    "LOW": "28.3",
    "CLOSEP*": "28.5",
    "YCP*": "28.4",
    "CHANGE": "0.1",
    "TRADE": "280",
    "VALUE (mn)": "5.059",
    "VOLUME": "177502"
  },
  {
    "#": "229",
    "TRADING CODE": "MIRAKHTER",
    "LTP*": "41.1",
    "HIGH": "42",
    "LOW": "40.6",
    "CLOSEP*": "41.1",
    "YCP*": "41.2",
    "CHANGE": "-0.1",
    "TRADE": "1022",
    "VALUE (mn)": "34.242",
    "VOLUME": "830750"
  },
  {
    "#": "230",
    "TRADING CODE": "MITHUNKNIT",
    "LTP*": "14.6",
    "HIGH": "14.8",
    "LOW": "14.3",
    "CLOSEP*": "14.6",
    "YCP*": "14.2",
    "CHANGE": "0.4",
    "TRADE": "71",
    "VALUE (mn)": "0.445",
    "VOLUME": "30636"
  },
  {
    "#": "231",
    "TRADING CODE": "MJLBD",
    "LTP*": "95.9",
    "HIGH": "96.3",
    "LOW": "95.5",
    "CLOSEP*": "95.9",
    "YCP*": "96",
    "CHANGE": "-0.1",
    "TRADE": "429",
    "VALUE (mn)": "10.808",
    "VOLUME": "112725"
  },
  {
    "#": "232",
    "TRADING CODE": "MLDYEING",
    "LTP*": "13.1",
    "HIGH": "13.5",
    "LOW": "12.5",
    "CLOSEP*": "13.1",
    "YCP*": "12.8",
    "CHANGE": "0.3",
    "TRADE": "1566",
    "VALUE (mn)": "56.01",
    "VOLUME": "4257820"
  },
  {
    "#": "233",
    "TRADING CODE": "MONNOAGML",
    "LTP*": "359.1",
    "HIGH": "362.9",
    "LOW": "358.2",
    "CLOSEP*": "359.1",
    "YCP*": "357.9",
    "CHANGE": "1.2",
    "TRADE": "430",
    "VALUE (mn)": "8.254",
    "VOLUME": "22941"
  },
  {
    "#": "234",
    "TRADING CODE": "MONNOCERA",
    "LTP*": "99.8",
    "HIGH": "102.1",
    "LOW": "99.2",
    "CLOSEP*": "99.8",
    "YCP*": "100.2",
    "CHANGE": "-0.4",
    "TRADE": "2450",
    "VALUE (mn)": "98.534",
    "VOLUME": "982620"
  },
  {
    "#": "235",
    "TRADING CODE": "MONNOFABR",
    "LTP*": "22.8",
    "HIGH": "23.1",
    "LOW": "22.7",
    "CLOSEP*": "22.8",
    "YCP*": "22.8",
    "CHANGE": "0",
    "TRADE": "887",
    "VALUE (mn)": "45.045",
    "VOLUME": "1965050"
  },
  {
    "#": "236",
    "TRADING CODE": "MONOSPOOL",
    "LTP*": "123",
    "HIGH": "125",
    "LOW": "122.9",
    "CLOSEP*": "123",
    "YCP*": "123.1",
    "CHANGE": "-0.1",
    "TRADE": "1742",
    "VALUE (mn)": "66.776",
    "VOLUME": "540927"
  },
  {
    "#": "237",
    "TRADING CODE": "MPETROLEUM",
    "LTP*": "215.5",
    "HIGH": "216.2",
    "LOW": "214.7",
    "CLOSEP*": "215.5",
    "YCP*": "215.5",
    "CHANGE": "0",
    "TRADE": "269",
    "VALUE (mn)": "10.296",
    "VOLUME": "47773"
  },
  {
    "#": "238",
    "TRADING CODE": "MTB",
    "LTP*": "14",
    "HIGH": "14.3",
    "LOW": "13.9",
    "CLOSEP*": "14",
    "YCP*": "14",
    "CHANGE": "0",
    "TRADE": "239",
    "VALUE (mn)": "19.953",
    "VOLUME": "1418597"
  },
  {
    "#": "239",
    "TRADING CODE": "NAHEEACP",
    "LTP*": "39.8",
    "HIGH": "41.1",
    "LOW": "39.4",
    "CLOSEP*": "39.8",
    "YCP*": "41.1",
    "CHANGE": "-1.3",
    "TRADE": "1555",
    "VALUE (mn)": "73.085",
    "VOLUME": "1825866"
  },
  {
    "#": "240",
    "TRADING CODE": "NATLIFEINS",
    "LTP*": "110.2",
    "HIGH": "113.4",
    "LOW": "108.3",
    "CLOSEP*": "110.2",
    "YCP*": "110.2",
    "CHANGE": "0",
    "TRADE": "624",
    "VALUE (mn)": "22.62",
    "VOLUME": "204469"
  },
  {
    "#": "241",
    "TRADING CODE": "NAVANACNG",
    "LTP*": "23",
    "HIGH": "23.2",
    "LOW": "22.9",
    "CLOSEP*": "23",
    "YCP*": "23",
    "CHANGE": "0",
    "TRADE": "93",
    "VALUE (mn)": "1.696",
    "VOLUME": "73653"
  },
  {
    "#": "242",
    "TRADING CODE": "NAVANAPHAR",
    "LTP*": "72.8",
    "HIGH": "73.5",
    "LOW": "72.6",
    "CLOSEP*": "72.8",
    "YCP*": "72.9",
    "CHANGE": "-0.1",
    "TRADE": "1017",
    "VALUE (mn)": "39.545",
    "VOLUME": "541685"
  },
  {
    "#": "243",
    "TRADING CODE": "NBL",
    "LTP*": "3.8",
    "HIGH": "3.9",
    "LOW": "3.7",
    "CLOSEP*": "3.8",
    "YCP*": "3.8",
    "CHANGE": "0",
    "TRADE": "324",
    "VALUE (mn)": "6.979",
    "VOLUME": "1838176"
  },
  {
    "#": "244",
    "TRADING CODE": "NCCBANK",
    "LTP*": "15.5",
    "HIGH": "15.8",
    "LOW": "15.4",
    "CLOSEP*": "15.5",
    "YCP*": "15.6",
    "CHANGE": "-0.1",
    "TRADE": "1472",
    "VALUE (mn)": "102.293",
    "VOLUME": "6568291"
  },
  {
    "#": "245",
    "TRADING CODE": "NCCBLMF1",
    "LTP*": "5.5",
    "HIGH": "5.6",
    "LOW": "5.4",
    "CLOSEP*": "5.5",
    "YCP*": "5.7",
    "CHANGE": "-0.2",
    "TRADE": "129",
    "VALUE (mn)": "2.295",
    "VOLUME": "418993"
  },
  {
    "#": "246",
    "TRADING CODE": "NEWLINE",
    "LTP*": "5.4",
    "HIGH": "5.5",
    "LOW": "5.2",
    "CLOSEP*": "5.4",
    "YCP*": "5.2",
    "CHANGE": "0.2",
    "TRADE": "85",
    "VALUE (mn)": "1.08",
    "VOLUME": "198996"
  },
  {
    "#": "247",
    "TRADING CODE": "NFML",
    "LTP*": "21.7",
    "HIGH": "22.1",
    "LOW": "20",
    "CLOSEP*": "21.7",
    "YCP*": "20.9",
    "CHANGE": "0.8",
    "TRADE": "3107",
    "VALUE (mn)": "126.673",
    "VOLUME": "5853453"
  },
  {
    "#": "248",
    "TRADING CODE": "NHFIL",
    "LTP*": "31.9",
    "HIGH": "32.4",
    "LOW": "31.7",
    "CLOSEP*": "31.9",
    "YCP*": "31.8",
    "CHANGE": "0.1",
    "TRADE": "906",
    "VALUE (mn)": "42.993",
    "VOLUME": "1344641"
  },
  {
    "#": "249",
    "TRADING CODE": "NITOLINS",
    "LTP*": "38.8",
    "HIGH": "39.7",
    "LOW": "38.6",
    "CLOSEP*": "38.8",
    "YCP*": "38.1",
    "CHANGE": "0.7",
    "TRADE": "471",
    "VALUE (mn)": "16.599",
    "VOLUME": "422485"
  },
  {
    "#": "250",
    "TRADING CODE": "NORTHERN",
    "LTP*": "123.8",
    "HIGH": "123.8",
    "LOW": "114.5",
    "CLOSEP*": "123.8",
    "YCP*": "112.6",
    "CHANGE": "11.2",
    "TRADE": "479",
    "VALUE (mn)": "6.759",
    "VOLUME": "55500"
  },
  {
    "#": "251",
    "TRADING CODE": "NORTHRNINS",
    "LTP*": "42.7",
    "HIGH": "44.1",
    "LOW": "42.4",
    "CLOSEP*": "42.7",
    "YCP*": "43.4",
    "CHANGE": "-0.7",
    "TRADE": "995",
    "VALUE (mn)": "30.362",
    "VOLUME": "701109"
  },
  {
    "#": "252",
    "TRADING CODE": "NPOLYMER",
    "LTP*": "34.6",
    "HIGH": "35",
    "LOW": "34.5",
    "CLOSEP*": "34.6",
    "YCP*": "34.5",
    "CHANGE": "0.1",
    "TRADE": "387",
    "VALUE (mn)": "12.899",
    "VOLUME": "371519"
  },
  {
    "#": "253",
    "TRADING CODE": "NRBBANK",
    "LTP*": "6",
    "HIGH": "6.1",
    "LOW": "6",
    "CLOSEP*": "6",
    "YCP*": "6",
    "CHANGE": "0",
    "TRADE": "83",
    "VALUE (mn)": "1.955",
    "VOLUME": "325703"
  },
  {
    "#": "254",
    "TRADING CODE": "NRBCBANK",
    "LTP*": "7.3",
    "HIGH": "7.4",
    "LOW": "7.3",
    "CLOSEP*": "7.3",
    "YCP*": "7.3",
    "CHANGE": "0",
    "TRADE": "23",
    "VALUE (mn)": "0.436",
    "VOLUME": "59497"
  },
  {
    "#": "255",
    "TRADING CODE": "NTC",
    "LTP*": "183.2",
    "HIGH": "183.2",
    "LOW": "165",
    "CLOSEP*": "183.2",
    "YCP*": "166.6",
    "CHANGE": "16.6",
    "TRADE": "616",
    "VALUE (mn)": "10.41",
    "VOLUME": "58163"
  },
  {
    "#": "256",
    "TRADING CODE": "NTLTUBES",
    "LTP*": "73.8",
    "HIGH": "75.3",
    "LOW": "73.3",
    "CLOSEP*": "73.8",
    "YCP*": "74.3",
    "CHANGE": "-0.5",
    "TRADE": "1298",
    "VALUE (mn)": "29.907",
    "VOLUME": "402409"
  },
  {
    "#": "257",
    "TRADING CODE": "NURANI",
    "LTP*": "2.8",
    "HIGH": "2.9",
    "LOW": "2.7",
    "CLOSEP*": "2.8",
    "YCP*": "2.8",
    "CHANGE": "0",
    "TRADE": "62",
    "VALUE (mn)": "0.194",
    "VOLUME": "71004"
  },
  {
    "#": "258",
    "TRADING CODE": "OAL",
    "LTP*": "6.7",
    "HIGH": "6.8",
    "LOW": "6.6",
    "CLOSEP*": "6.7",
    "YCP*": "6.6",
    "CHANGE": "0.1",
    "TRADE": "97",
    "VALUE (mn)": "1.783",
    "VOLUME": "265427"
  },
  {
    "#": "259",
    "TRADING CODE": "OIMEX",
    "LTP*": "17.1",
    "HIGH": "17.4",
    "LOW": "17",
    "CLOSEP*": "17.1",
    "YCP*": "17.1",
    "CHANGE": "0",
    "TRADE": "407",
    "VALUE (mn)": "7.703",
    "VOLUME": "450719"
  },
  {
    "#": "260",
    "TRADING CODE": "OLYMPIC",
    "LTP*": "160.9",
    "HIGH": "161.9",
    "LOW": "160.1",
    "CLOSEP*": "160.9",
    "YCP*": "161",
    "CHANGE": "-0.1",
    "TRADE": "674",
    "VALUE (mn)": "31.249",
    "VOLUME": "194207"
  },
  {
    "#": "261",
    "TRADING CODE": "ONEBANKPLC",
    "LTP*": "7.9",
    "HIGH": "8",
    "LOW": "7.8",
    "CLOSEP*": "7.9",
    "YCP*": "7.8",
    "CHANGE": "0.1",
    "TRADE": "77",
    "VALUE (mn)": "2.781",
    "VOLUME": "352786"
  },
  {
    "#": "262",
    "TRADING CODE": "ORIONINFU",
    "LTP*": "291.2",
    "HIGH": "295.9",
    "LOW": "290.5",
    "CLOSEP*": "291.2",
    "YCP*": "290.9",
    "CHANGE": "0.3",
    "TRADE": "1748",
    "VALUE (mn)": "35.228",
    "VOLUME": "120581"
  },
  {
    "#": "263",
    "TRADING CODE": "ORIONPHARM",
    "LTP*": "30.3",
    "HIGH": "30.5",
    "LOW": "29.7",
    "CLOSEP*": "30.3",
    "YCP*": "30.1",
    "CHANGE": "0.2",
    "TRADE": "462",
    "VALUE (mn)": "11.07",
    "VOLUME": "367882"
  },
  {
    "#": "264",
    "TRADING CODE": "PADMALIFE",
    "LTP*": "19.1",
    "HIGH": "19.9",
    "LOW": "19",
    "CLOSEP*": "19.1",
    "YCP*": "19.5",
    "CHANGE": "-0.4",
    "TRADE": "192",
    "VALUE (mn)": "2.358",
    "VOLUME": "122458"
  },
  {
    "#": "265",
    "TRADING CODE": "PADMAOIL",
    "LTP*": "199.9",
    "HIGH": "201.4",
    "LOW": "198.5",
    "CLOSEP*": "199.9",
    "YCP*": "198.4",
    "CHANGE": "1.5",
    "TRADE": "483",
    "VALUE (mn)": "12.952",
    "VOLUME": "64820"
  },
  {
    "#": "266",
    "TRADING CODE": "PARAMOUNT",
    "LTP*": "63.2",
    "HIGH": "64.6",
    "LOW": "63.1",
    "CLOSEP*": "63.2",
    "YCP*": "63.5",
    "CHANGE": "-0.3",
    "TRADE": "711",
    "VALUE (mn)": "23.376",
    "VOLUME": "367647"
  },
  {
    "#": "267",
    "TRADING CODE": "PDL",
    "LTP*": "5.5",
    "HIGH": "5.7",
    "LOW": "5.4",
    "CLOSEP*": "5.5",
    "YCP*": "5.6",
    "CHANGE": "-0.1",
    "TRADE": "188",
    "VALUE (mn)": "2.049",
    "VOLUME": "371137"
  },
  {
    "#": "268",
    "TRADING CODE": "PENINSULA",
    "LTP*": "24.4",
    "HIGH": "24.6",
    "LOW": "24.3",
    "CLOSEP*": "24.4",
    "YCP*": "24.4",
    "CHANGE": "0",
    "TRADE": "610",
    "VALUE (mn)": "17.098",
    "VOLUME": "699143"
  },
  {
    "#": "269",
    "TRADING CODE": "PEOPLESINS",
    "LTP*": "61.1",
    "HIGH": "62.8",
    "LOW": "61",
    "CLOSEP*": "61.1",
    "YCP*": "61.7",
    "CHANGE": "-0.6",
    "TRADE": "1187",
    "VALUE (mn)": "59.296",
    "VOLUME": "960676"
  },
  {
    "#": "270",
    "TRADING CODE": "PF1STMF",
    "LTP*": "11.8",
    "HIGH": "11.9",
    "LOW": "11.4",
    "CLOSEP*": "11.8",
    "YCP*": "11.3",
    "CHANGE": "0.5",
    "TRADE": "805",
    "VALUE (mn)": "39.543",
    "VOLUME": "3381531"
  },
  {
    "#": "271",
    "TRADING CODE": "PHARMAID",
    "LTP*": "615.5",
    "HIGH": "620",
    "LOW": "610",
    "CLOSEP*": "615.5",
    "YCP*": "616.4",
    "CHANGE": "-0.9",
    "TRADE": "680",
    "VALUE (mn)": "13.403",
    "VOLUME": "21823"
  },
  {
    "#": "272",
    "TRADING CODE": "PHENIXINS",
    "LTP*": "46.7",
    "HIGH": "48.7",
    "LOW": "46.5",
    "CLOSEP*": "46.7",
    "YCP*": "47.6",
    "CHANGE": "-0.9",
    "TRADE": "1113",
    "VALUE (mn)": "35.85",
    "VOLUME": "753058"
  },
  {
    "#": "273",
    "TRADING CODE": "PHOENIXFIN",
    "LTP*": "3.6",
    "HIGH": "3.7",
    "LOW": "3.5",
    "CLOSEP*": "3.6",
    "YCP*": "3.5",
    "CHANGE": "0.1",
    "TRADE": "46",
    "VALUE (mn)": "0.377",
    "VOLUME": "105154"
  },
  {
    "#": "274",
    "TRADING CODE": "PHPMF1",
    "LTP*": "3.6",
    "HIGH": "3.6",
    "LOW": "3.4",
    "CLOSEP*": "3.6",
    "YCP*": "3.6",
    "CHANGE": "0",
    "TRADE": "252",
    "VALUE (mn)": "11.907",
    "VOLUME": "3369450"
  },
  {
    "#": "275",
    "TRADING CODE": "PIONEERINS",
    "LTP*": "71.2",
    "HIGH": "72.6",
    "LOW": "71",
    "CLOSEP*": "71.2",
    "YCP*": "71.6",
    "CHANGE": "-0.4",
    "TRADE": "1191",
    "VALUE (mn)": "52.894",
    "VOLUME": "737312"
  },
  {
    "#": "276",
    "TRADING CODE": "PLFSL",
    "LTP*": "1.3",
    "HIGH": "1.3",
    "LOW": "1.2",
    "CLOSEP*": "1.2",
    "YCP*": "1.3",
    "CHANGE": "0",
    "TRADE": "83",
    "VALUE (mn)": "0.898",
    "VOLUME": "709532"
  },
  {
    "#": "277",
    "TRADING CODE": "POPULAR1MF",
    "LTP*": "3.5",
    "HIGH": "3.6",
    "LOW": "3.4",
    "CLOSEP*": "3.5",
    "YCP*": "3.5",
    "CHANGE": "0",
    "TRADE": "86",
    "VALUE (mn)": "3.29",
    "VOLUME": "943701"
  },
  {
    "#": "278",
    "TRADING CODE": "POPULARLIF",
    "LTP*": "66",
    "HIGH": "66.7",
    "LOW": "64.1",
    "CLOSEP*": "66",
    "YCP*": "65.5",
    "CHANGE": "0.5",
    "TRADE": "1425",
    "VALUE (mn)": "72.881",
    "VOLUME": "1110763"
  },
  {
    "#": "279",
    "TRADING CODE": "POWERGRID",
    "LTP*": "41.6",
    "HIGH": "41.8",
    "LOW": "41.4",
    "CLOSEP*": "41.6",
    "YCP*": "41.4",
    "CHANGE": "0.2",
    "TRADE": "296",
    "VALUE (mn)": "5.899",
    "VOLUME": "141742"
  },
  {
    "#": "280",
    "TRADING CODE": "PRAGATIINS",
    "LTP*": "82.5",
    "HIGH": "84.7",
    "LOW": "82.3",
    "CLOSEP*": "82.5",
    "YCP*": "83.6",
    "CHANGE": "-1.1",
    "TRADE": "899",
    "VALUE (mn)": "42.662",
    "VOLUME": "512614"
  },
  {
    "#": "281",
    "TRADING CODE": "PRAGATILIF",
    "LTP*": "0",
    "HIGH": "0",
    "LOW": "0",
    "CLOSEP*": "197.3",
    "YCP*": "197.3",
    "CHANGE": "--",
    "TRADE": "0",
    "VALUE (mn)": "0",
    "VOLUME": "0"
  },
  {
    "#": "282",
    "TRADING CODE": "PREMIERBAN",
    "LTP*": "5",
    "HIGH": "5.1",
    "LOW": "4.9",
    "CLOSEP*": "5",
    "YCP*": "5",
    "CHANGE": "0",
    "TRADE": "203",
    "VALUE (mn)": "3.24",
    "VOLUME": "649180"
  },
  {
    "#": "283",
    "TRADING CODE": "PREMIERCEM",
    "LTP*": "52.8",
    "HIGH": "54.5",
    "LOW": "51.6",
    "CLOSEP*": "52.8",
    "YCP*": "53.5",
    "CHANGE": "-0.7",
    "TRADE": "2112",
    "VALUE (mn)": "94.176",
    "VOLUME": "1772273"
  },
  {
    "#": "284",
    "TRADING CODE": "PREMIERLEA",
    "LTP*": "2.1",
    "HIGH": "2.3",
    "LOW": "2.1",
    "CLOSEP*": "2.1",
    "YCP*": "2.2",
    "CHANGE": "-0.1",
    "TRADE": "97",
    "VALUE (mn)": "0.942",
    "VOLUME": "433996"
  },
  {
    "#": "285",
    "TRADING CODE": "PRIME1ICBA",
    "LTP*": "6",
    "HIGH": "6.2",
    "LOW": "5.8",
    "CLOSEP*": "6",
    "YCP*": "6.1",
    "CHANGE": "-0.1",
    "TRADE": "147",
    "VALUE (mn)": "3.01",
    "VOLUME": "504051"
  },
  {
    "#": "286",
    "TRADING CODE": "PRIMEBANK",
    "LTP*": "30.4",
    "HIGH": "30.7",
    "LOW": "29.9",
    "CLOSEP*": "30.4",
    "YCP*": "30",
    "CHANGE": "0.4",
    "TRADE": "442",
    "VALUE (mn)": "73.68",
    "VOLUME": "2443556"
  },
  {
    "#": "287",
    "TRADING CODE": "PRIMEFIN",
    "LTP*": "3.2",
    "HIGH": "3.3",
    "LOW": "3.1",
    "CLOSEP*": "3.2",
    "YCP*": "3.2",
    "CHANGE": "0",
    "TRADE": "81",
    "VALUE (mn)": "1.287",
    "VOLUME": "407182"
  },
  {
    "#": "288",
    "TRADING CODE": "PRIMEINSUR",
    "LTP*": "49.4",
    "HIGH": "51.8",
    "LOW": "48.8",
    "CLOSEP*": "49.4",
    "YCP*": "50",
    "CHANGE": "-0.6",
    "TRADE": "1020",
    "VALUE (mn)": "37.855",
    "VOLUME": "753623"
  },
  {
    "#": "289",
    "TRADING CODE": "PRIMELIFE",
    "LTP*": "44.5",
    "HIGH": "45.5",
    "LOW": "44.2",
    "CLOSEP*": "44.5",
    "YCP*": "45.1",
    "CHANGE": "-0.6",
    "TRADE": "274",
    "VALUE (mn)": "7.527",
    "VOLUME": "168472"
  },
  {
    "#": "290",
    "TRADING CODE": "PRIMETEX",
    "LTP*": "16.7",
    "HIGH": "17.1",
    "LOW": "16.7",
    "CLOSEP*": "16.7",
    "YCP*": "16.6",
    "CHANGE": "0.1",
    "TRADE": "123",
    "VALUE (mn)": "1.291",
    "VOLUME": "76598"
  },
  {
    "#": "291",
    "TRADING CODE": "PROGRESLIF",
    "LTP*": "43.3",
    "HIGH": "43.9",
    "LOW": "43",
    "CLOSEP*": "43.2",
    "YCP*": "43.6",
    "CHANGE": "-0.3",
    "TRADE": "75",
    "VALUE (mn)": "0.777",
    "VOLUME": "17836"
  },
  {
    "#": "292",
    "TRADING CODE": "PROVATIINS",
    "LTP*": "62.4",
    "HIGH": "65.9",
    "LOW": "61.7",
    "CLOSEP*": "62.4",
    "YCP*": "63.5",
    "CHANGE": "-1.1",
    "TRADE": "1461",
    "VALUE (mn)": "71.794",
    "VOLUME": "1131220"
  },
  {
    "#": "293",
    "TRADING CODE": "PTL",
    "LTP*": "66",
    "HIGH": "66.9",
    "LOW": "65.2",
    "CLOSEP*": "66",
    "YCP*": "65.2",
    "CHANGE": "0.8",
    "TRADE": "893",
    "VALUE (mn)": "48.812",
    "VOLUME": "737317"
  },
  {
    "#": "294",
    "TRADING CODE": "PUBALIBANK",
    "LTP*": "37.3",
    "HIGH": "37.8",
    "LOW": "37.1",
    "CLOSEP*": "37.3",
    "YCP*": "37.4",
    "CHANGE": "-0.1",
    "TRADE": "288",
    "VALUE (mn)": "13.247",
    "VOLUME": "354333"
  },
  {
    "#": "295",
    "TRADING CODE": "PURABIGEN",
    "LTP*": "34.5",
    "HIGH": "36.1",
    "LOW": "34.3",
    "CLOSEP*": "34.5",
    "YCP*": "34.3",
    "CHANGE": "0.2",
    "TRADE": "2350",
    "VALUE (mn)": "121.417",
    "VOLUME": "3452517"
  },
  {
    "#": "296",
    "TRADING CODE": "QUASEMIND",
    "LTP*": "46.8",
    "HIGH": "49.8",
    "LOW": "45.4",
    "CLOSEP*": "46.8",
    "YCP*": "45.3",
    "CHANGE": "1.5",
    "TRADE": "1370",
    "VALUE (mn)": "69.19",
    "VOLUME": "1491177"
  },
  {
    "#": "297",
    "TRADING CODE": "QUEENSOUTH",
    "LTP*": "16.2",
    "HIGH": "16.4",
    "LOW": "16",
    "CLOSEP*": "16.2",
    "YCP*": "16",
    "CHANGE": "0.2",
    "TRADE": "794",
    "VALUE (mn)": "39.054",
    "VOLUME": "2405006"
  },
  {
    "#": "298",
    "TRADING CODE": "RAHIMAFOOD",
    "LTP*": "94.1",
    "HIGH": "94.1",
    "LOW": "86.9",
    "CLOSEP*": "94.1",
    "YCP*": "85.6",
    "CHANGE": "8.5",
    "TRADE": "844",
    "VALUE (mn)": "14.82",
    "VOLUME": "160562"
  },
  {
    "#": "299",
    "TRADING CODE": "RAHIMTEXT",
    "LTP*": "228.2",
    "HIGH": "238.3",
    "LOW": "226",
    "CLOSEP*": "228.2",
    "YCP*": "230.1",
    "CHANGE": "-1.9",
    "TRADE": "1187",
    "VALUE (mn)": "30.825",
    "VOLUME": "132511"
  },
  {
    "#": "300",
    "TRADING CODE": "RAKCERAMIC",
    "LTP*": "30.5",
    "HIGH": "30.8",
    "LOW": "29.8",
    "CLOSEP*": "30.5",
    "YCP*": "30.2",
    "CHANGE": "0.3",
    "TRADE": "667",
    "VALUE (mn)": "20.177",
    "VOLUME": "665634"
  },
  {
    "#": "301",
    "TRADING CODE": "RANFOUNDRY",
    "LTP*": "166.6",
    "HIGH": "168",
    "LOW": "164.8",
    "CLOSEP*": "166.6",
    "YCP*": "164.1",
    "CHANGE": "2.5",
    "TRADE": "277",
    "VALUE (mn)": "6.124",
    "VOLUME": "36763"
  },
  {
    "#": "302",
    "TRADING CODE": "RDFOOD",
    "LTP*": "30.1",
    "HIGH": "30.9",
    "LOW": "30",
    "CLOSEP*": "30.1",
    "YCP*": "30.5",
    "CHANGE": "-0.4",
    "TRADE": "2135",
    "VALUE (mn)": "87.65",
    "VOLUME": "2889507"
  },
  {
    "#": "303",
    "TRADING CODE": "RECKITTBEN",
    "LTP*": "3323",
    "HIGH": "3332.1",
    "LOW": "3320",
    "CLOSEP*": "3324.8",
    "YCP*": "3332.2",
    "CHANGE": "-9.2",
    "TRADE": "176",
    "VALUE (mn)": "3.791",
    "VOLUME": "1140"
  },
  {
    "#": "304",
    "TRADING CODE": "REGENTTEX",
    "LTP*": "6",
    "HIGH": "6.2",
    "LOW": "5.9",
    "CLOSEP*": "6",
    "YCP*": "6.1",
    "CHANGE": "-0.1",
    "TRADE": "110",
    "VALUE (mn)": "1.14",
    "VOLUME": "190545"
  },
  {
    "#": "305",
    "TRADING CODE": "RELIANCE1",
    "LTP*": "11.9",
    "HIGH": "12.3",
    "LOW": "11.9",
    "CLOSEP*": "11.9",
    "YCP*": "12.1",
    "CHANGE": "-0.2",
    "TRADE": "379",
    "VALUE (mn)": "13.452",
    "VOLUME": "1118246"
  },
  {
    "#": "306",
    "TRADING CODE": "RELIANCINS",
    "LTP*": "118.9",
    "HIGH": "124.6",
    "LOW": "115.9",
    "CLOSEP*": "118.9",
    "YCP*": "120.7",
    "CHANGE": "-1.8",
    "TRADE": "818",
    "VALUE (mn)": "38.691",
    "VOLUME": "325516"
  },
  {
    "#": "307",
    "TRADING CODE": "RENATA",
    "LTP*": "469.1",
    "HIGH": "470",
    "LOW": "462.1",
    "CLOSEP*": "469.1",
    "YCP*": "464.3",
    "CHANGE": "4.8",
    "TRADE": "995",
    "VALUE (mn)": "30.732",
    "VOLUME": "65671"
  },
  {
    "#": "308",
    "TRADING CODE": "RENWICKJA",
    "LTP*": "904.6",
    "HIGH": "905.1",
    "LOW": "851",
    "CLOSEP*": "904.6",
    "YCP*": "842",
    "CHANGE": "62.6",
    "TRADE": "286",
    "VALUE (mn)": "5.807",
    "VOLUME": "6452"
  },
  {
    "#": "309",
    "TRADING CODE": "REPUBLIC",
    "LTP*": "40.9",
    "HIGH": "42.4",
    "LOW": "40.5",
    "CLOSEP*": "40.9",
    "YCP*": "41.8",
    "CHANGE": "-0.9",
    "TRADE": "810",
    "VALUE (mn)": "32.696",
    "VOLUME": "786158"
  },
  {
    "#": "310",
    "TRADING CODE": "RINGSHINE",
    "LTP*": "4",
    "HIGH": "4",
    "LOW": "3.7",
    "CLOSEP*": "4",
    "YCP*": "3.7",
    "CHANGE": "0.3",
    "TRADE": "663",
    "VALUE (mn)": "13.758",
    "VOLUME": "3546695"
  },
  {
    "#": "311",
    "TRADING CODE": "ROBI",
    "LTP*": "32.9",
    "HIGH": "33",
    "LOW": "32.3",
    "CLOSEP*": "32.9",
    "YCP*": "32.4",
    "CHANGE": "0.5",
    "TRADE": "1686",
    "VALUE (mn)": "130.213",
    "VOLUME": "3981170"
  },
  {
    "#": "312",
    "TRADING CODE": "RSRMSTEEL",
    "LTP*": "7.9",
    "HIGH": "8",
    "LOW": "7.8",
    "CLOSEP*": "7.8",
    "YCP*": "7.7",
    "CHANGE": "0.2",
    "TRADE": "49",
    "VALUE (mn)": "1.043",
    "VOLUME": "133279"
  },
  {
    "#": "313",
    "TRADING CODE": "RUNNERAUTO",
    "LTP*": "42.7",
    "HIGH": "43",
    "LOW": "42.6",
    "CLOSEP*": "42.7",
    "YCP*": "42.7",
    "CHANGE": "0",
    "TRADE": "681",
    "VALUE (mn)": "38.813",
    "VOLUME": "908265"
  },
  {
    "#": "314",
    "TRADING CODE": "RUPALIBANK",
    "LTP*": "18.3",
    "HIGH": "18.5",
    "LOW": "17.2",
    "CLOSEP*": "18.3",
    "YCP*": "16.9",
    "CHANGE": "1.4",
    "TRADE": "682",
    "VALUE (mn)": "21.561",
    "VOLUME": "1187873"
  },
  {
    "#": "315",
    "TRADING CODE": "RUPALIINS",
    "LTP*": "31.6",
    "HIGH": "33",
    "LOW": "31.3",
    "CLOSEP*": "31.6",
    "YCP*": "31.8",
    "CHANGE": "-0.2",
    "TRADE": "1570",
    "VALUE (mn)": "61.729",
    "VOLUME": "1913393"
  },
  {
    "#": "316",
    "TRADING CODE": "RUPALILIFE",
    "LTP*": "97.7",
    "HIGH": "98.9",
    "LOW": "96.6",
    "CLOSEP*": "97.7",
    "YCP*": "97.8",
    "CHANGE": "-0.1",
    "TRADE": "1446",
    "VALUE (mn)": "54.277",
    "VOLUME": "554677"
  },
  {
    "#": "317",
    "TRADING CODE": "SAFKOSPINN",
    "LTP*": "21.1",
    "HIGH": "21.5",
    "LOW": "21",
    "CLOSEP*": "21.1",
    "YCP*": "21",
    "CHANGE": "0.1",
    "TRADE": "71",
    "VALUE (mn)": "0.962",
    "VOLUME": "45542"
  },
  {
    "#": "318",
    "TRADING CODE": "SAIFPOWER",
    "LTP*": "10",
    "HIGH": "10.3",
    "LOW": "9.9",
    "CLOSEP*": "10",
    "YCP*": "10",
    "CHANGE": "0",
    "TRADE": "293",
    "VALUE (mn)": "5.746",
    "VOLUME": "571565"
  },
  {
    "#": "319",
    "TRADING CODE": "SAIHAMCOT",
    "LTP*": "21.1",
    "HIGH": "21.7",
    "LOW": "20.2",
    "CLOSEP*": "21.1",
    "YCP*": "20.2",
    "CHANGE": "0.9",
    "TRADE": "1929",
    "VALUE (mn)": "119.436",
    "VOLUME": "5698439"
  },
  {
    "#": "320",
    "TRADING CODE": "SAIHAMTEX",
    "LTP*": "19.9",
    "HIGH": "20.3",
    "LOW": "19.4",
    "CLOSEP*": "19.9",
    "YCP*": "19.4",
    "CHANGE": "0.5",
    "TRADE": "1120",
    "VALUE (mn)": "56.815",
    "VOLUME": "2855528"
  },
  {
    "#": "321",
    "TRADING CODE": "SALAMCRST",
    "LTP*": "14.2",
    "HIGH": "14.7",
    "LOW": "14.1",
    "CLOSEP*": "14.2",
    "YCP*": "14.4",
    "CHANGE": "-0.2",
    "TRADE": "275",
    "VALUE (mn)": "4.979",
    "VOLUME": "348915"
  },
  {
    "#": "322",
    "TRADING CODE": "SALVO",
    "LTP*": "38.5",
    "HIGH": "38.6",
    "LOW": "37.5",
    "CLOSEP*": "38.5",
    "YCP*": "37.6",
    "CHANGE": "0.9",
    "TRADE": "1311",
    "VALUE (mn)": "46.684",
    "VOLUME": "1225124"
  },
  {
    "#": "323",
    "TRADING CODE": "SAMATALETH",
    "LTP*": "106.5",
    "HIGH": "107.7",
    "LOW": "102.5",
    "CLOSEP*": "106.5",
    "YCP*": "102.6",
    "CHANGE": "3.9",
    "TRADE": "1050",
    "VALUE (mn)": "21.9",
    "VOLUME": "206939"
  },
  {
    "#": "324",
    "TRADING CODE": "SAMORITA",
    "LTP*": "95.9",
    "HIGH": "99.9",
    "LOW": "92.7",
    "CLOSEP*": "95.9",
    "YCP*": "93",
    "CHANGE": "2.9",
    "TRADE": "1707",
    "VALUE (mn)": "68.911",
    "VOLUME": "714371"
  },
  {
    "#": "325",
    "TRADING CODE": "SANDHANINS",
    "LTP*": "29",
    "HIGH": "29.8",
    "LOW": "28.8",
    "CLOSEP*": "29",
    "YCP*": "29.5",
    "CHANGE": "-0.5",
    "TRADE": "1764",
    "VALUE (mn)": "77.145",
    "VOLUME": "2627625"
  },
  {
    "#": "326",
    "TRADING CODE": "SAPORTL",
    "LTP*": "52.5",
    "HIGH": "53",
    "LOW": "50.9",
    "CLOSEP*": "52.5",
    "YCP*": "51.2",
    "CHANGE": "1.3",
    "TRADE": "3043",
    "VALUE (mn)": "267.575",
    "VOLUME": "5143123"
  },
  {
    "#": "327",
    "TRADING CODE": "SAVAREFR",
    "LTP*": "0",
    "HIGH": "0",
    "LOW": "0",
    "CLOSEP*": "215.5",
    "YCP*": "215.5",
    "CHANGE": "--",
    "TRADE": "0",
    "VALUE (mn)": "0",
    "VOLUME": "0"
  },
  {
    "#": "328",
    "TRADING CODE": "SBACBANK",
    "LTP*": "6.4",
    "HIGH": "6.6",
    "LOW": "6.4",
    "CLOSEP*": "6.4",
    "YCP*": "6.5",
    "CHANGE": "-0.1",
    "TRADE": "81",
    "VALUE (mn)": "0.6",
    "VOLUME": "92395"
  },
  {
    "#": "329",
    "TRADING CODE": "SEAPEARL",
    "LTP*": "42.8",
    "HIGH": "43.9",
    "LOW": "42.6",
    "CLOSEP*": "42.8",
    "YCP*": "43.1",
    "CHANGE": "-0.3",
    "TRADE": "2572",
    "VALUE (mn)": "104.93",
    "VOLUME": "2432537"
  },
  {
    "#": "330",
    "TRADING CODE": "SEMLFBSLGF",
    "LTP*": "6.8",
    "HIGH": "7",
    "LOW": "6.8",
    "CLOSEP*": "6.8",
    "YCP*": "6.9",
    "CHANGE": "-0.1",
    "TRADE": "83",
    "VALUE (mn)": "3.356",
    "VOLUME": "492696"
  },
  {
    "#": "331",
    "TRADING CODE": "SEMLIBBLSF",
    "LTP*": "7.8",
    "HIGH": "7.9",
    "LOW": "7.7",
    "CLOSEP*": "7.8",
    "YCP*": "7.8",
    "CHANGE": "0",
    "TRADE": "48",
    "VALUE (mn)": "1.385",
    "VOLUME": "177431"
  },
  {
    "#": "332",
    "TRADING CODE": "SEMLLECMF",
    "LTP*": "0",
    "HIGH": "0",
    "LOW": "0",
    "CLOSEP*": "7.4",
    "YCP*": "7.4",
    "CHANGE": "--",
    "TRADE": "0",
    "VALUE (mn)": "0",
    "VOLUME": "0"
  },
  {
    "#": "333",
    "TRADING CODE": "SHAHJABANK",
    "LTP*": "17.8",
    "HIGH": "17.9",
    "LOW": "17.5",
    "CLOSEP*": "17.8",
    "YCP*": "17.6",
    "CHANGE": "0.2",
    "TRADE": "179",
    "VALUE (mn)": "6.713",
    "VOLUME": "379621"
  },
  {
    "#": "334",
    "TRADING CODE": "SHARPIND",
    "LTP*": "30.3",
    "HIGH": "30.9",
    "LOW": "28.5",
    "CLOSEP*": "30.3",
    "YCP*": "29.2",
    "CHANGE": "1.1",
    "TRADE": "1844",
    "VALUE (mn)": "161.829",
    "VOLUME": "5457713"
  },
  {
    "#": "335",
    "TRADING CODE": "SHASHADNIM",
    "LTP*": "27",
    "HIGH": "27.3",
    "LOW": "26.8",
    "CLOSEP*": "27",
    "YCP*": "27",
    "CHANGE": "0",
    "TRADE": "355",
    "VALUE (mn)": "22.988",
    "VOLUME": "851099"
  },
  {
    "#": "336",
    "TRADING CODE": "SHEPHERD",
    "LTP*": "17.2",
    "HIGH": "17.4",
    "LOW": "16.9",
    "CLOSEP*": "17.2",
    "YCP*": "16.8",
    "CHANGE": "0.4",
    "TRADE": "972",
    "VALUE (mn)": "38.603",
    "VOLUME": "2243773"
  },
  {
    "#": "337",
    "TRADING CODE": "SHURWID",
    "LTP*": "6",
    "HIGH": "6",
    "LOW": "5.8",
    "CLOSEP*": "6",
    "YCP*": "5.9",
    "CHANGE": "0.1",
    "TRADE": "237",
    "VALUE (mn)": "1.288",
    "VOLUME": "216737"
  },
  {
    "#": "338",
    "TRADING CODE": "SHYAMPSUG",
    "LTP*": "338.1",
    "HIGH": "341.1",
    "LOW": "320",
    "CLOSEP*": "338.1",
    "YCP*": "320",
    "CHANGE": "18.1",
    "TRADE": "433",
    "VALUE (mn)": "10.848",
    "VOLUME": "32115"
  },
  {
    "#": "339",
    "TRADING CODE": "SIBL",
    "LTP*": "0",
    "HIGH": "0",
    "LOW": "0",
    "CLOSEP*": "3",
    "YCP*": "3",
    "CHANGE": "--",
    "TRADE": "0",
    "VALUE (mn)": "0",
    "VOLUME": "0"
  },
  {
    "#": "340",
    "TRADING CODE": "SICL",
    "LTP*": "42.1",
    "HIGH": "43.3",
    "LOW": "41.6",
    "CLOSEP*": "42.1",
    "YCP*": "41.5",
    "CHANGE": "0.6",
    "TRADE": "2186",
    "VALUE (mn)": "104.26",
    "VOLUME": "2446223"
  },
  {
    "#": "341",
    "TRADING CODE": "SILCOPHL",
    "LTP*": "21",
    "HIGH": "21.3",
    "LOW": "20.9",
    "CLOSEP*": "21",
    "YCP*": "21.1",
    "CHANGE": "-0.1",
    "TRADE": "684",
    "VALUE (mn)": "32.399",
    "VOLUME": "1538108"
  },
  {
    "#": "342",
    "TRADING CODE": "SILVAPHL",
    "LTP*": "16.4",
    "HIGH": "16.7",
    "LOW": "15.5",
    "CLOSEP*": "16.4",
    "YCP*": "15.6",
    "CHANGE": "0.8",
    "TRADE": "1477",
    "VALUE (mn)": "48.236",
    "VOLUME": "2996975"
  },
  {
    "#": "343",
    "TRADING CODE": "SIMTEX",
    "LTP*": "28.8",
    "HIGH": "29.6",
    "LOW": "28.6",
    "CLOSEP*": "28.8",
    "YCP*": "28.5",
    "CHANGE": "0.3",
    "TRADE": "2852",
    "VALUE (mn)": "146.457",
    "VOLUME": "5023058"
  },
  {
    "#": "344",
    "TRADING CODE": "SINGERBD",
    "LTP*": "75.7",
    "HIGH": "77.1",
    "LOW": "74",
    "CLOSEP*": "75.7",
    "YCP*": "74",
    "CHANGE": "1.7",
    "TRADE": "381",
    "VALUE (mn)": "5.463",
    "VOLUME": "71867"
  },
  {
    "#": "345",
    "TRADING CODE": "SINOBANGLA",
    "LTP*": "59.7",
    "HIGH": "60",
    "LOW": "58.4",
    "CLOSEP*": "59.7",
    "YCP*": "58.4",
    "CHANGE": "1.3",
    "TRADE": "1445",
    "VALUE (mn)": "63.703",
    "VOLUME": "1073247"
  },
  {
    "#": "346",
    "TRADING CODE": "SIPLC",
    "LTP*": "113.4",
    "HIGH": "115.8",
    "LOW": "112",
    "CLOSEP*": "113.4",
    "YCP*": "112.1",
    "CHANGE": "1.3",
    "TRADE": "489",
    "VALUE (mn)": "30.453",
    "VOLUME": "267681"
  },
  {
    "#": "347",
    "TRADING CODE": "SKTRIMS",
    "LTP*": "14.2",
    "HIGH": "14.5",
    "LOW": "13.7",
    "CLOSEP*": "14.2",
    "YCP*": "13.4",
    "CHANGE": "0.8",
    "TRADE": "402",
    "VALUE (mn)": "6.235",
    "VOLUME": "439067"
  },
  {
    "#": "348",
    "TRADING CODE": "SONALIANSH",
    "LTP*": "225.9",
    "HIGH": "229",
    "LOW": "224.5",
    "CLOSEP*": "225.9",
    "YCP*": "226.2",
    "CHANGE": "-0.3",
    "TRADE": "1750",
    "VALUE (mn)": "50.668",
    "VOLUME": "223447"
  },
  {
    "#": "349",
    "TRADING CODE": "SONALILIFE",
    "LTP*": "83",
    "HIGH": "84.9",
    "LOW": "82",
    "CLOSEP*": "83",
    "YCP*": "84.9",
    "CHANGE": "-1.9",
    "TRADE": "1567",
    "VALUE (mn)": "60.416",
    "VOLUME": "726386"
  },
  {
    "#": "350",
    "TRADING CODE": "SONALIPAPR",
    "LTP*": "255.9",
    "HIGH": "263.9",
    "LOW": "254.2",
    "CLOSEP*": "255.9",
    "YCP*": "258.3",
    "CHANGE": "-2.4",
    "TRADE": "1740",
    "VALUE (mn)": "60.021",
    "VOLUME": "232723"
  },
  {
    "#": "351",
    "TRADING CODE": "SONARBAINS",
    "LTP*": "44.8",
    "HIGH": "47.3",
    "LOW": "44.5",
    "CLOSEP*": "44.8",
    "YCP*": "46.3",
    "CHANGE": "-1.5",
    "TRADE": "1894",
    "VALUE (mn)": "73.046",
    "VOLUME": "1601606"
  },
  {
    "#": "352",
    "TRADING CODE": "SONARGAON",
    "LTP*": "93.1",
    "HIGH": "94.9",
    "LOW": "91.5",
    "CLOSEP*": "93.1",
    "YCP*": "91.5",
    "CHANGE": "1.6",
    "TRADE": "927",
    "VALUE (mn)": "24.287",
    "VOLUME": "260907"
  },
  {
    "#": "353",
    "TRADING CODE": "SOUTHEASTB",
    "LTP*": "10.3",
    "HIGH": "10.3",
    "LOW": "10.1",
    "CLOSEP*": "10.3",
    "YCP*": "10.2",
    "CHANGE": "0.1",
    "TRADE": "269",
    "VALUE (mn)": "13.564",
    "VOLUME": "1329894"
  },
  {
    "#": "354",
    "TRADING CODE": "SPCERAMICS",
    "LTP*": "23.8",
    "HIGH": "24.3",
    "LOW": "23.5",
    "CLOSEP*": "23.8",
    "YCP*": "24",
    "CHANGE": "-0.2",
    "TRADE": "1032",
    "VALUE (mn)": "33.896",
    "VOLUME": "1415148"
  },
  {
    "#": "355",
    "TRADING CODE": "SPCL",
    "LTP*": "58.5",
    "HIGH": "58.8",
    "LOW": "58.2",
    "CLOSEP*": "58.5",
    "YCP*": "58.3",
    "CHANGE": "0.2",
    "TRADE": "962",
    "VALUE (mn)": "62.94",
    "VOLUME": "1076908"
  },
  {
    "#": "356",
    "TRADING CODE": "SQUARETEXT",
    "LTP*": "52.2",
    "HIGH": "53",
    "LOW": "51.5",
    "CLOSEP*": "52.2",
    "YCP*": "51.6",
    "CHANGE": "0.6",
    "TRADE": "345",
    "VALUE (mn)": "14.057",
    "VOLUME": "268836"
  },
  {
    "#": "357",
    "TRADING CODE": "SQURPHARMA",
    "LTP*": "223.1",
    "HIGH": "223.4",
    "LOW": "221.3",
    "CLOSEP*": "223.1",
    "YCP*": "221.4",
    "CHANGE": "1.7",
    "TRADE": "1561",
    "VALUE (mn)": "104.333",
    "VOLUME": "469258"
  },
  {
    "#": "358",
    "TRADING CODE": "SSSTEEL",
    "LTP*": "7.2",
    "HIGH": "7.5",
    "LOW": "7.1",
    "CLOSEP*": "7.2",
    "YCP*": "7.3",
    "CHANGE": "-0.1",
    "TRADE": "418",
    "VALUE (mn)": "6.686",
    "VOLUME": "927684"
  },
  {
    "#": "359",
    "TRADING CODE": "STANCERAM",
    "LTP*": "73.7",
    "HIGH": "73.8",
    "LOW": "72",
    "CLOSEP*": "73.7",
    "YCP*": "71.5",
    "CHANGE": "2.2",
    "TRADE": "119",
    "VALUE (mn)": "2.961",
    "VOLUME": "40453"
  },
  {
    "#": "360",
    "TRADING CODE": "STANDARINS",
    "LTP*": "55.4",
    "HIGH": "56.8",
    "LOW": "55.1",
    "CLOSEP*": "55.4",
    "YCP*": "55.6",
    "CHANGE": "-0.2",
    "TRADE": "807",
    "VALUE (mn)": "29.573",
    "VOLUME": "529312"
  },
  {
    "#": "361",
    "TRADING CODE": "STANDBANKL",
    "LTP*": "4.8",
    "HIGH": "4.8",
    "LOW": "4.6",
    "CLOSEP*": "4.8",
    "YCP*": "4.6",
    "CHANGE": "0.2",
    "TRADE": "122",
    "VALUE (mn)": "2.879",
    "VOLUME": "613017"
  },
  {
    "#": "362",
    "TRADING CODE": "STYLECRAFT",
    "LTP*": "61",
    "HIGH": "61.7",
    "LOW": "58.1",
    "CLOSEP*": "61",
    "YCP*": "57.8",
    "CHANGE": "3.2",
    "TRADE": "374",
    "VALUE (mn)": "5.612",
    "VOLUME": "93743"
  },
  {
    "#": "363",
    "TRADING CODE": "SUMITPOWER",
    "LTP*": "17.6",
    "HIGH": "17.9",
    "LOW": "17.3",
    "CLOSEP*": "17.6",
    "YCP*": "17.5",
    "CHANGE": "0.1",
    "TRADE": "1181",
    "VALUE (mn)": "41.138",
    "VOLUME": "2336249"
  },
  {
    "#": "364",
    "TRADING CODE": "SUNLIFEINS",
    "LTP*": "73.1",
    "HIGH": "75.5",
    "LOW": "72.6",
    "CLOSEP*": "73.1",
    "YCP*": "75.7",
    "CHANGE": "-2.6",
    "TRADE": "1887",
    "VALUE (mn)": "78.588",
    "VOLUME": "1067818"
  },
  {
    "#": "365",
    "TRADING CODE": "TAKAFULINS",
    "LTP*": "49.5",
    "HIGH": "50.4",
    "LOW": "49.1",
    "CLOSEP*": "49.5",
    "YCP*": "48.9",
    "CHANGE": "0.6",
    "TRADE": "719",
    "VALUE (mn)": "23.557",
    "VOLUME": "472992"
  },
  {
    "#": "366",
    "TRADING CODE": "TALLUSPIN",
    "LTP*": "8.1",
    "HIGH": "8.2",
    "LOW": "8",
    "CLOSEP*": "8.1",
    "YCP*": "8",
    "CHANGE": "0.1",
    "TRADE": "151",
    "VALUE (mn)": "2.164",
    "VOLUME": "266919"
  },
  {
    "#": "367",
    "TRADING CODE": "TAMIJTEX",
    "LTP*": "142",
    "HIGH": "144",
    "LOW": "138.4",
    "CLOSEP*": "142",
    "YCP*": "137.4",
    "CHANGE": "4.6",
    "TRADE": "2092",
    "VALUE (mn)": "65.495",
    "VOLUME": "460185"
  },
  {
    "#": "368",
    "TRADING CODE": "TECHNODRUG",
    "LTP*": "43.1",
    "HIGH": "43.5",
    "LOW": "42.3",
    "CLOSEP*": "43.1",
    "YCP*": "42.5",
    "CHANGE": "0.6",
    "TRADE": "1317",
    "VALUE (mn)": "60.496",
    "VOLUME": "1414444"
  },
  {
    "#": "369",
    "TRADING CODE": "TILIL",
    "LTP*": "56.7",
    "HIGH": "58.9",
    "LOW": "56.6",
    "CLOSEP*": "56.7",
    "YCP*": "57.5",
    "CHANGE": "-0.8",
    "TRADE": "1747",
    "VALUE (mn)": "65.168",
    "VOLUME": "1135884"
  },
  {
    "#": "370",
    "TRADING CODE": "TITASGAS",
    "LTP*": "21.4",
    "HIGH": "21.6",
    "LOW": "21.1",
    "CLOSEP*": "21.4",
    "YCP*": "21.3",
    "CHANGE": "0.1",
    "TRADE": "910",
    "VALUE (mn)": "29.258",
    "VOLUME": "1369109"
  },
  {
    "#": "371",
    "TRADING CODE": "TOSRIFA",
    "LTP*": "23.6",
    "HIGH": "24.3",
    "LOW": "23.4",
    "CLOSEP*": "23.6",
    "YCP*": "23.6",
    "CHANGE": "0",
    "TRADE": "954",
    "VALUE (mn)": "34.472",
    "VOLUME": "1449361"
  },
  {
    "#": "372",
    "TRADING CODE": "TRUSTB1MF",
    "LTP*": "3.4",
    "HIGH": "3.5",
    "LOW": "3.3",
    "CLOSEP*": "3.4",
    "YCP*": "3.4",
    "CHANGE": "0",
    "TRADE": "139",
    "VALUE (mn)": "3.638",
    "VOLUME": "1072501"
  },
  {
    "#": "373",
    "TRADING CODE": "TRUSTBANK",
    "LTP*": "15.8",
    "HIGH": "15.9",
    "LOW": "15.7",
    "CLOSEP*": "15.8",
    "YCP*": "15.7",
    "CHANGE": "0.1",
    "TRADE": "656",
    "VALUE (mn)": "48.117",
    "VOLUME": "3043740"
  },
  {
    "#": "374",
    "TRADING CODE": "TUNGHAI",
    "LTP*": "2.7",
    "HIGH": "2.7",
    "LOW": "2.6",
    "CLOSEP*": "2.7",
    "YCP*": "2.5",
    "CHANGE": "0.2",
    "TRADE": "34",
    "VALUE (mn)": "0.958",
    "VOLUME": "360152"
  },
  {
    "#": "375",
    "TRADING CODE": "UCB",
    "LTP*": "9",
    "HIGH": "9.1",
    "LOW": "9",
    "CLOSEP*": "9",
    "YCP*": "9",
    "CHANGE": "0",
    "TRADE": "62",
    "VALUE (mn)": "1.58",
    "VOLUME": "174791"
  },
  {
    "#": "376",
    "TRADING CODE": "UNILEVERCL",
    "LTP*": "2068.2",
    "HIGH": "2072",
    "LOW": "2065",
    "CLOSEP*": "2068.2",
    "YCP*": "2067.5",
    "CHANGE": "0.7",
    "TRADE": "69",
    "VALUE (mn)": "0.849",
    "VOLUME": "410"
  },
  {
    "#": "377",
    "TRADING CODE": "UNIONBANK",
    "LTP*": "0",
    "HIGH": "0",
    "LOW": "0",
    "CLOSEP*": "1.5",
    "YCP*": "1.5",
    "CHANGE": "--",
    "TRADE": "0",
    "VALUE (mn)": "0",
    "VOLUME": "0"
  },
  {
    "#": "378",
    "TRADING CODE": "UNIONCAP",
    "LTP*": "4.4",
    "HIGH": "4.6",
    "LOW": "4.4",
    "CLOSEP*": "4.4",
    "YCP*": "4.5",
    "CHANGE": "-0.1",
    "TRADE": "87",
    "VALUE (mn)": "1.34",
    "VOLUME": "299693"
  },
  {
    "#": "379",
    "TRADING CODE": "UNIONINS",
    "LTP*": "53.1",
    "HIGH": "55.8",
    "LOW": "52.1",
    "CLOSEP*": "53.1",
    "YCP*": "52.8",
    "CHANGE": "0.3",
    "TRADE": "2020",
    "VALUE (mn)": "101.385",
    "VOLUME": "1890228"
  },
  {
    "#": "380",
    "TRADING CODE": "UNIQUEHRL",
    "LTP*": "47.3",
    "HIGH": "48.2",
    "LOW": "47",
    "CLOSEP*": "47.3",
    "YCP*": "47.5",
    "CHANGE": "-0.2",
    "TRADE": "1391",
    "VALUE (mn)": "51.98",
    "VOLUME": "1095142"
  },
  {
    "#": "381",
    "TRADING CODE": "UNITEDFIN",
    "LTP*": "16.3",
    "HIGH": "16.6",
    "LOW": "16.2",
    "CLOSEP*": "16.3",
    "YCP*": "16.6",
    "CHANGE": "-0.3",
    "TRADE": "565",
    "VALUE (mn)": "18.395",
    "VOLUME": "1122579"
  },
  {
    "#": "382",
    "TRADING CODE": "UNITEDINS",
    "LTP*": "48.9",
    "HIGH": "49.5",
    "LOW": "46.7",
    "CLOSEP*": "48.9",
    "YCP*": "46.9",
    "CHANGE": "2",
    "TRADE": "735",
    "VALUE (mn)": "21.386",
    "VOLUME": "440624"
  },
  {
    "#": "383",
    "TRADING CODE": "UPGDCL",
    "LTP*": "130.3",
    "HIGH": "131.3",
    "LOW": "129.1",
    "CLOSEP*": "130.3",
    "YCP*": "130.7",
    "CHANGE": "-0.4",
    "TRADE": "504",
    "VALUE (mn)": "14.769",
    "VOLUME": "113428"
  },
  {
    "#": "384",
    "TRADING CODE": "USMANIAGL",
    "LTP*": "78.3",
    "HIGH": "78.9",
    "LOW": "71.1",
    "CLOSEP*": "78.3",
    "YCP*": "74.2",
    "CHANGE": "4.1",
    "TRADE": "1098",
    "VALUE (mn)": "16.901",
    "VOLUME": "221761"
  },
  {
    "#": "385",
    "TRADING CODE": "UTTARABANK",
    "LTP*": "21.3",
    "HIGH": "21.5",
    "LOW": "21.2",
    "CLOSEP*": "21.3",
    "YCP*": "21.4",
    "CHANGE": "-0.1",
    "TRADE": "1676",
    "VALUE (mn)": "99.437",
    "VOLUME": "4666476"
  },
  {
    "#": "386",
    "TRADING CODE": "UTTARAFIN",
    "LTP*": "13.2",
    "HIGH": "13.4",
    "LOW": "13.2",
    "CLOSEP*": "13.2",
    "YCP*": "13.3",
    "CHANGE": "-0.1",
    "TRADE": "71",
    "VALUE (mn)": "0.633",
    "VOLUME": "47842"
  },
  {
    "#": "387",
    "TRADING CODE": "VAMLBDMF1",
    "LTP*": "0",
    "HIGH": "0",
    "LOW": "0",
    "CLOSEP*": "7.1",
    "YCP*": "7.1",
    "CHANGE": "--",
    "TRADE": "0",
    "VALUE (mn)": "0",
    "VOLUME": "0"
  },
  {
    "#": "388",
    "TRADING CODE": "VAMLRBBF",
    "LTP*": "7.8",
    "HIGH": "8.1",
    "LOW": "7.8",
    "CLOSEP*": "7.8",
    "YCP*": "7.8",
    "CHANGE": "0",
    "TRADE": "21",
    "VALUE (mn)": "1.65",
    "VOLUME": "211377"
  },
  {
    "#": "389",
    "TRADING CODE": "VFSTDL",
    "LTP*": "16.6",
    "HIGH": "17",
    "LOW": "16.6",
    "CLOSEP*": "16.6",
    "YCP*": "16.5",
    "CHANGE": "0.1",
    "TRADE": "982",
    "VALUE (mn)": "41.409",
    "VOLUME": "2474523"
  },
  {
    "#": "390",
    "TRADING CODE": "WALTONHIL",
    "LTP*": "404.5",
    "HIGH": "411",
    "LOW": "403",
    "CLOSEP*": "404.5",
    "YCP*": "409.9",
    "CHANGE": "-5.4",
    "TRADE": "1689",
    "VALUE (mn)": "33.398",
    "VOLUME": "82064"
  },
  {
    "#": "391",
    "TRADING CODE": "WATACHEM",
    "LTP*": "149",
    "HIGH": "149",
    "LOW": "144",
    "CLOSEP*": "147.8",
    "YCP*": "144",
    "CHANGE": "5",
    "TRADE": "634",
    "VALUE (mn)": "15.394",
    "VOLUME": "104756"
  },
  {
    "#": "392",
    "TRADING CODE": "WMSHIPYARD",
    "LTP*": "10.2",
    "HIGH": "10.2",
    "LOW": "9.9",
    "CLOSEP*": "10.2",
    "YCP*": "10",
    "CHANGE": "0.2",
    "TRADE": "467",
    "VALUE (mn)": "10.865",
    "VOLUME": "1076836"
  },
  {
    "#": "393",
    "TRADING CODE": "YPL",
    "LTP*": "24.9",
    "HIGH": "25.4",
    "LOW": "24.8",
    "CLOSEP*": "24.9",
    "YCP*": "25",
    "CHANGE": "-0.1",
    "TRADE": "379",
    "VALUE (mn)": "8.122",
    "VOLUME": "323780"
  },
  {
    "#": "394",
    "TRADING CODE": "ZAHEENSPIN",
    "LTP*": "5.6",
    "HIGH": "5.6",
    "LOW": "5.4",
    "CLOSEP*": "5.4",
    "YCP*": "5.3",
    "CHANGE": "0.3",
    "TRADE": "137",
    "VALUE (mn)": "1.374",
    "VOLUME": "251181"
  },
  {
    "#": "395",
    "TRADING CODE": "ZAHINTEX",
    "LTP*": "9.7",
    "HIGH": "10.1",
    "LOW": "9.3",
    "CLOSEP*": "9.7",
    "YCP*": "9.3",
    "CHANGE": "0.4",
    "TRADE": "254",
    "VALUE (mn)": "6.414",
    "VOLUME": "649758"
  },
  {
    "#": "396",
    "TRADING CODE": "ZEALBANGLA",
    "LTP*": "232.1",
    "HIGH": "233.2",
    "LOW": "214.1",
    "CLOSEP*": "232.1",
    "YCP*": "214.5",
    "CHANGE": "17.6",
    "TRADE": "647",
    "VALUE (mn)": "16.543",
    "VOLUME": "72313"
  }
]